{"name":"root","parent":"","style":{"color":{"r":0.0,"g":0.0,"b":0.0,"a":0.0},"size":0.0,"lineType":"ltNone","lineWidth":0.0,"fillColor":{"r":0.0,"g":0.0,"b":0.0,"a":0.0},"marker":"mkCircle","errorBarKind":"ebLines","gradient":null,"font":{"family":"","size":0.0,"bold":false,"slant":"fsNormal","color":{"r":0.0,"g":0.0,"b":0.0,"a":0.0},"alignKind":"taLeft"}},"xScale":{"low":0.0,"high":1.0},"yScale":{"low":0.0,"high":1.0},"rotate":null,"scale":null,"origin":{"x":{"pos":0.0,"kind":"ukRelative"},"y":{"pos":0.0,"kind":"ukRelative"}},"width":{"val":1.0,"unit":"ukRelative"},"height":{"val":1.0,"unit":"ukRelative"},"objects":[{"name":"","children":[],"style":{"color":{"r":0.0,"g":0.0,"b":0.0,"a":0.0},"size":0.0,"lineType":"ltNone","lineWidth":0.0,"fillColor":{"r":1.0,"g":1.0,"b":1.0,"a":1.0},"marker":"mkCircle","errorBarKind":"ebLines","gradient":null,"font":{"family":"","size":0.0,"bold":false,"slant":"fsNormal","color":{"r":0.0,"g":0.0,"b":0.0,"a":0.0},"alignKind":"taLeft"}},"rotateInView":null,"rotate":null,"kind":"goRect","reOrigin":{"x":{"pos":0.0,"kind":"ukRelative"},"y":{"pos":0.0,"kind":"ukRelative"}},"reWidth":{"val":1.0,"unit":"ukRelative"},"reHeight":{"val":1.0,"unit":"ukRelative"}}],"children":[{"name":"topLeft","parent":"root","style":{"color":{"r":0.0,"g":0.0,"b":0.0,"a":0.0},"size":0.0,"lineType":"ltNone","lineWidth":0.0,"fillColor":{"r":0.0,"g":0.0,"b":0.0,"a":0.0},"marker":"mkCircle","errorBarKind":"ebLines","gradient":null,"font":{"family":"","size":0.0,"bold":false,"slant":"fsNormal","color":{"r":0.0,"g":0.0,"b":0.0,"a":0.0},"alignKind":"taLeft"}},"xScale":{"low":0.0,"high":0.0},"yScale":{"low":0.0,"high":0.0},"rotate":null,"scale":null,"origin":{"x":{"pos":0.0,"kind":"ukRelative"},"y":{"pos":0.0,"kind":"ukRelative"}},"width":{"val":2.5,"unit":"ukCentimeter"},"height":{"val":1.25,"unit":"ukCentimeter"},"objects":[],"children":[],"wView":{"val":640.0,"unit":"ukPoint"},"hView":{"val":480.0,"unit":"ukPoint"},"wImg":{"val":640.0,"unit":"ukPoint"},"hImg":{"val":480.0,"unit":"ukPoint"},"backend":"bkCairo"},{"name":"title","parent":"root","style":{"color":{"r":0.0,"g":0.0,"b":0.0,"a":0.0},"size":0.0,"lineType":"ltNone","lineWidth":0.0,"fillColor":{"r":0.0,"g":0.0,"b":0.0,"a":0.0},"marker":"mkCircle","errorBarKind":"ebLines","gradient":null,"font":{"family":"","size":0.0,"bold":false,"slant":"fsNormal","color":{"r":0.0,"g":0.0,"b":0.0,"a":0.0},"alignKind":"taLeft"}},"xScale":{"low":0.0,"high":0.0},"yScale":{"low":0.0,"high":0.0},"rotate":null,"scale":null,"origin":{"x":{"pos":2.5,"kind":"ukCentimeter","length":{"val":22.493427424934275,"unit":"ukCentimeter"}},"y":{"pos":0.0,"kind":"ukRelative"}},"width":{"val":0.6665692667322834,"unit":"ukRelative"},"height":{"val":1.25,"unit":"ukCentimeter"},"objects":[],"children":[],"wView":{"val":640.0,"unit":"ukPoint"},"hView":{"val":480.0,"unit":"ukPoint"},"wImg":{"val":640.0,"unit":"ukPoint"},"hImg":{"val":480.0,"unit":"ukPoint"},"backend":"bkCairo"},{"name":"topRight","parent":"root","style":{"color":{"r":0.0,"g":0.0,"b":0.0,"a":0.0},"size":0.0,"lineType":"ltNone","lineWidth":0.0,"fillColor":{"r":0.0,"g":0.0,"b":0.0,"a":0.0},"marker":"mkCircle","errorBarKind":"ebLines","gradient":null,"font":{"family":"","size":0.0,"bold":false,"slant":"fsNormal","color":{"r":0.0,"g":0.0,"b":0.0,"a":0.0},"alignKind":"taLeft"}},"xScale":{"low":0.0,"high":0.0},"yScale":{"low":0.0,"high":0.0},"rotate":null,"scale":null,"origin":{"x":{"pos":17.493427424934275,"kind":"ukCentimeter","length":{"val":22.493427424934275,"unit":"ukCentimeter"}},"y":{"pos":0.0,"kind":"ukRelative"}},"width":{"val":5.0,"unit":"ukCentimeter"},"height":{"val":1.25,"unit":"ukCentimeter"},"objects":[],"children":[],"wView":{"val":640.0,"unit":"ukPoint"},"hView":{"val":480.0,"unit":"ukPoint"},"wImg":{"val":640.0,"unit":"ukPoint"},"hImg":{"val":480.0,"unit":"ukPoint"},"backend":"bkCairo"},{"name":"yLabel","parent":"root","style":{"color":{"r":0.0,"g":0.0,"b":0.0,"a":0.0},"size":0.0,"lineType":"ltNone","lineWidth":0.0,"fillColor":{"r":0.0,"g":0.0,"b":0.0,"a":0.0},"marker":"mkCircle","errorBarKind":"ebLines","gradient":null,"font":{"family":"","size":0.0,"bold":false,"slant":"fsNormal","color":{"r":0.0,"g":0.0,"b":0.0,"a":0.0},"alignKind":"taLeft"}},"xScale":{"low":0.0,"high":0.0},"yScale":{"low":0.0,"high":0.0},"rotate":null,"scale":null,"origin":{"x":{"pos":0.0,"kind":"ukRelative"},"y":{"pos":1.25,"kind":"ukCentimeter","length":{"val":16.870070568700708,"unit":"ukCentimeter"}}},"width":{"val":2.5,"unit":"ukCentimeter"},"height":{"val":0.8073511318897638,"unit":"ukRelative"},"objects":[],"children":[],"wView":{"val":640.0,"unit":"ukPoint"},"hView":{"val":480.0,"unit":"ukPoint"},"wImg":{"val":640.0,"unit":"ukPoint"},"hImg":{"val":480.0,"unit":"ukPoint"},"backend":"bkCairo"},{"name":"plot","parent":"root","style":{"color":{"r":0.0,"g":0.0,"b":0.0,"a":0.0},"size":0.0,"lineType":"ltNone","lineWidth":0.0,"fillColor":{"r":0.0,"g":0.0,"b":0.0,"a":0.0},"marker":"mkCircle","errorBarKind":"ebLines","gradient":null,"font":{"family":"","size":0.0,"bold":false,"slant":"fsNormal","color":{"r":0.0,"g":0.0,"b":0.0,"a":0.0},"alignKind":"taLeft"}},"xScale":{"low":0.0,"high":1.0},"yScale":{"low":0.0,"high":1.0},"rotate":null,"scale":null,"origin":{"x":{"pos":2.5,"kind":"ukCentimeter","length":{"val":22.493427424934275,"unit":"ukCentimeter"}},"y":{"pos":1.25,"kind":"ukCentimeter","length":{"val":16.870070568700708,"unit":"ukCentimeter"}}},"width":{"val":0.6665692667322834,"unit":"ukRelative"},"height":{"val":0.8073511318897638,"unit":"ukRelative"},"objects":[{"name":"","children":[],"style":{"color":{"r":0.0,"g":0.0,"b":0.0,"a":0.0},"size":0.0,"lineType":"ltNone","lineWidth":0.0,"fillColor":{"r":0.9200000166893005,"g":0.9200000166893005,"b":0.9200000166893005,"a":1.0},"marker":"mkCircle","errorBarKind":"ebLines","gradient":null,"font":{"family":"","size":0.0,"bold":false,"slant":"fsNormal","color":{"r":0.0,"g":0.0,"b":0.0,"a":0.0},"alignKind":"taLeft"}},"rotateInView":null,"rotate":null,"kind":"goRect","reOrigin":{"x":{"pos":0.0,"kind":"ukRelative"},"y":{"pos":0.0,"kind":"ukRelative"}},"reWidth":{"val":1.0,"unit":"ukRelative"},"reHeight":{"val":1.0,"unit":"ukRelative"}},{"name":"tick","children":[],"style":{"color":{"r":0.0,"g":0.0,"b":0.0,"a":1.0},"size":5.0,"lineType":"ltSolid","lineWidth":1.0,"fillColor":{"r":0.0,"g":0.0,"b":0.0,"a":0.0},"marker":"mkCircle","errorBarKind":"ebLines","gradient":null,"font":{"family":"","size":0.0,"bold":false,"slant":"fsNormal","color":{"r":0.0,"g":0.0,"b":0.0,"a":0.0},"alignKind":"taLeft"}},"rotateInView":null,"rotate":null,"kind":"goTick","tkMajor":true,"tkPos":{"x":{"pos":0.17555945212221888,"kind":"ukRelative"},"y":{"pos":1.0,"kind":"ukRelative"}},"tkAxis":"akX","tkKind":"tkOneSide","tkSecondary":false},{"name":"tick","children":[],"style":{"color":{"r":0.0,"g":0.0,"b":0.0,"a":1.0},"size":5.0,"lineType":"ltSolid","lineWidth":1.0,"fillColor":{"r":0.0,"g":0.0,"b":0.0,"a":0.0},"marker":"mkCircle","errorBarKind":"ebLines","gradient":null,"font":{"family":"","size":0.0,"bold":false,"slant":"fsNormal","color":{"r":0.0,"g":0.0,"b":0.0,"a":0.0},"alignKind":"taLeft"}},"rotateInView":null,"rotate":null,"kind":"goTick","tkMajor":true,"tkPos":{"x":{"pos":0.5,"kind":"ukRelative"},"y":{"pos":1.0,"kind":"ukRelative"}},"tkAxis":"akX","tkKind":"tkOneSide","tkSecondary":false},{"name":"tick","children":[],"style":{"color":{"r":0.0,"g":0.0,"b":0.0,"a":1.0},"size":5.0,"lineType":"ltSolid","lineWidth":1.0,"fillColor":{"r":0.0,"g":0.0,"b":0.0,"a":0.0},"marker":"mkCircle","errorBarKind":"ebLines","gradient":null,"font":{"family":"","size":0.0,"bold":false,"slant":"fsNormal","color":{"r":0.0,"g":0.0,"b":0.0,"a":0.0},"alignKind":"taLeft"}},"rotateInView":null,"rotate":null,"kind":"goTick","tkMajor":true,"tkPos":{"x":{"pos":0.824440547877781,"kind":"ukRelative"},"y":{"pos":1.0,"kind":"ukRelative"}},"tkAxis":"akX","tkKind":"tkOneSide","tkSecondary":false},{"name":"xtickLabel","children":[],"style":{"color":{"r":0.0,"g":0.0,"b":0.0,"a":0.0},"size":0.0,"lineType":"ltNone","lineWidth":0.0,"fillColor":{"r":0.0,"g":0.0,"b":0.0,"a":0.0},"marker":"mkCircle","errorBarKind":"ebLines","gradient":null,"font":{"family":"","size":0.0,"bold":false,"slant":"fsNormal","color":{"r":0.0,"g":0.0,"b":0.0,"a":0.0},"alignKind":"taLeft"}},"rotateInView":null,"rotate":null,"kind":"goTickLabel","txtText":"1","txtFont":{"family":"sans-serif","size":8.0,"bold":false,"slant":"fsNormal","color":{"r":0.0,"g":0.0,"b":0.0,"a":1.0},"alignKind":"taLeft"},"txtPos":{"x":{"pos":0.17555945212221888,"kind":"ukRelative"},"y":{"pos":1.0316105747862108,"kind":"ukRelative"}},"txtAlign":"taCenter","txtRotate":0.0},{"name":"xtickLabel","children":[],"style":{"color":{"r":0.0,"g":0.0,"b":0.0,"a":0.0},"size":0.0,"lineType":"ltNone","lineWidth":0.0,"fillColor":{"r":0.0,"g":0.0,"b":0.0,"a":0.0},"marker":"mkCircle","errorBarKind":"ebLines","gradient":null,"font":{"family":"","size":0.0,"bold":false,"slant":"fsNormal","color":{"r":0.0,"g":0.0,"b":0.0,"a":0.0},"alignKind":"taLeft"}},"rotateInView":null,"rotate":null,"kind":"goTickLabel","txtText":"2","txtFont":{"family":"sans-serif","size":8.0,"bold":false,"slant":"fsNormal","color":{"r":0.0,"g":0.0,"b":0.0,"a":1.0},"alignKind":"taLeft"},"txtPos":{"x":{"pos":0.5,"kind":"ukRelative"},"y":{"pos":1.0316105747862108,"kind":"ukRelative"}},"txtAlign":"taCenter","txtRotate":0.0},{"name":"xtickLabel","children":[],"style":{"color":{"r":0.0,"g":0.0,"b":0.0,"a":0.0},"size":0.0,"lineType":"ltNone","lineWidth":0.0,"fillColor":{"r":0.0,"g":0.0,"b":0.0,"a":0.0},"marker":"mkCircle","errorBarKind":"ebLines","gradient":null,"font":{"family":"","size":0.0,"bold":false,"slant":"fsNormal","color":{"r":0.0,"g":0.0,"b":0.0,"a":0.0},"alignKind":"taLeft"}},"rotateInView":null,"rotate":null,"kind":"goTickLabel","txtText":"3","txtFont":{"family":"sans-serif","size":8.0,"bold":false,"slant":"fsNormal","color":{"r":0.0,"g":0.0,"b":0.0,"a":1.0},"alignKind":"taLeft"},"txtPos":{"x":{"pos":0.824440547877781,"kind":"ukRelative"},"y":{"pos":1.0316105747862108,"kind":"ukRelative"}},"txtAlign":"taCenter","txtRotate":0.0},{"name":"tick","children":[],"style":{"color":{"r":0.0,"g":0.0,"b":0.0,"a":1.0},"size":5.0,"lineType":"ltSolid","lineWidth":1.0,"fillColor":{"r":0.0,"g":0.0,"b":0.0,"a":0.0},"marker":"mkCircle","errorBarKind":"ebLines","gradient":null,"font":{"family":"","size":0.0,"bold":false,"slant":"fsNormal","color":{"r":0.0,"g":0.0,"b":0.0,"a":0.0},"alignKind":"taLeft"}},"rotateInView":null,"rotate":null,"kind":"goTick","tkMajor":true,"tkPos":{"x":{"pos":0.0,"kind":"ukRelative"},"y":{"pos":0.25734210586469375,"kind":"ukRelative"}},"tkAxis":"akY","tkKind":"tkOneSide","tkSecondary":false},{"name":"tick","children":[],"style":{"color":{"r":0.0,"g":0.0,"b":0.0,"a":1.0},"size":5.0,"lineType":"ltSolid","lineWidth":1.0,"fillColor":{"r":0.0,"g":0.0,"b":0.0,"a":0.0},"marker":"mkCircle","errorBarKind":"ebLines","gradient":null,"font":{"family":"","size":0.0,"bold":false,"slant":"fsNormal","color":{"r":0.0,"g":0.0,"b":0.0,"a":0.0},"alignKind":"taLeft"}},"rotateInView":null,"rotate":null,"kind":"goTick","tkMajor":true,"tkPos":{"x":{"pos":0.0,"kind":"ukRelative"},"y":{"pos":0.7426578941353063,"kind":"ukRelative"}},"tkAxis":"akY","tkKind":"tkOneSide","tkSecondary":false},{"name":"ytickLabel","children":[],"style":{"color":{"r":0.0,"g":0.0,"b":0.0,"a":0.0},"size":0.0,"lineType":"ltNone","lineWidth":0.0,"fillColor":{"r":0.0,"g":0.0,"b":0.0,"a":0.0},"marker":"mkCircle","errorBarKind":"ebLines","gradient":null,"font":{"family":"","size":0.0,"bold":false,"slant":"fsNormal","color":{"r":0.0,"g":0.0,"b":0.0,"a":0.0},"alignKind":"taLeft"}},"rotateInView":null,"rotate":null,"kind":"goTickLabel","txtText":"a","txtFont":{"family":"sans-serif","size":8.0,"bold":false,"slant":"fsNormal","color":{"r":0.0,"g":0.0,"b":0.0,"a":1.0},"alignKind":"taLeft"},"txtPos":{"x":{"pos":-0.020510809127194704,"kind":"ukRelative"},"y":{"pos":0.25734210586469375,"kind":"ukRelative"}},"txtAlign":"taRight","txtRotate":0.0},{"name":"ytickLabel","children":[],"style":{"color":{"r":0.0,"g":0.0,"b":0.0,"a":0.0},"size":0.0,"lineType":"ltNone","lineWidth":0.0,"fillColor":{"r":0.0,"g":0.0,"b":0.0,"a":0.0},"marker":"mkCircle","errorBarKind":"ebLines","gradient":null,"font":{"family":"","size":0.0,"bold":false,"slant":"fsNormal","color":{"r":0.0,"g":0.0,"b":0.0,"a":0.0},"alignKind":"taLeft"}},"rotateInView":null,"rotate":null,"kind":"goTickLabel","txtText":"b","txtFont":{"family":"sans-serif","size":8.0,"bold":false,"slant":"fsNormal","color":{"r":0.0,"g":0.0,"b":0.0,"a":1.0},"alignKind":"taLeft"},"txtPos":{"x":{"pos":-0.020510809127194704,"kind":"ukRelative"},"y":{"pos":0.7426578941353063,"kind":"ukRelative"}},"txtAlign":"taRight","txtRotate":0.0},{"name":"xLabel","children":[],"style":{"color":{"r":0.0,"g":0.0,"b":0.0,"a":0.0},"size":0.0,"lineType":"ltNone","lineWidth":0.0,"fillColor":{"r":0.0,"g":0.0,"b":0.0,"a":0.0},"marker":"mkCircle","errorBarKind":"ebLines","gradient":null,"font":{"family":"","size":0.0,"bold":false,"slant":"fsNormal","color":{"r":0.0,"g":0.0,"b":0.0,"a":0.0},"alignKind":"taLeft"}},"rotateInView":null,"rotate":null,"kind":"goLabel","txtText":"pos","txtFont":{"family":"sans-serif","size":12.0,"bold":false,"slant":"fsNormal","color":{"r":0.0,"g":0.0,"b":0.0,"a":1.0},"alignKind":"taCenter"},"txtPos":{"x":{"pos":0.5,"kind":"ukRelative"},"y":{"pos":415.98129921259846,"kind":"ukPoint","length":{"val":387.52854330708664,"unit":"ukPoint"}}},"txtAlign":"taCenter","txtRotate":0.0},{"name":"yLabel","children":[],"style":{"color":{"r":0.0,"g":0.0,"b":0.0,"a":0.0},"size":0.0,"lineType":"ltNone","lineWidth":0.0,"fillColor":{"r":0.0,"g":0.0,"b":0.0,"a":0.0},"marker":"mkCircle","errorBarKind":"ebLines","gradient":null,"font":{"family":"","size":0.0,"bold":false,"slant":"fsNormal","color":{"r":0.0,"g":0.0,"b":0.0,"a":0.0},"alignKind":"taLeft"}},"rotateInView":null,"rotate":-90.0,"kind":"goLabel","txtText":"name","txtFont":{"family":"sans-serif","size":12.0,"bold":false,"slant":"fsNormal","color":{"r":0.0,"g":0.0,"b":0.0,"a":1.0},"alignKind":"taCenter"},"txtPos":{"x":{"pos":-28.452755905511808,"kind":"ukPoint","length":{"val":426.6043307086614,"unit":"ukPoint"}},"y":{"pos":0.5,"kind":"ukRelative"}},"txtAlign":"taCenter","txtRotate":0.0},{"name":"xGridLines","children":[],"style":{"color":{"r":1.0,"g":1.0,"b":1.0,"a":1.0},"size":0.0,"lineType":"ltSolid","lineWidth":1.0,"fillColor":{"r":0.0,"g":0.0,"b":0.0,"a":0.0},"marker":"mkCircle","errorBarKind":"ebLines","gradient":null,"font":{"family":"","size":0.0,"bold":false,"slant":"fsNormal","color":{"r":0.0,"g":0.0,"b":0.0,"a":0.0},"alignKind":"taLeft"}},"rotateInView":null,"rotate":null,"kind":"goGrid","gdOrigin":{"x":{"pos":0.0,"kind":"ukRelative"},"y":{"pos":0.0,"kind":"ukRelative"}},"gdOriginDiag":{"x":{"pos":0.0,"kind":"ukRelative"},"y":{"pos":0.0,"kind":"ukRelative"}},"gdXPos":[{"pos":0.17555945212221888,"kind":"ukRelative"},{"pos":0.5,"kind":"ukRelative"},{"pos":0.824440547877781,"kind":"ukRelative"}],"gdYPos":[{"pos":0.25734210586469375,"kind":"ukRelative"},{"pos":0.7426578941353063,"kind":"ukRelative"}]}],"children":[{"name":"data","parent":"plot","style":{"color":{"r":0.0,"g":0.0,"b":0.0,"a":0.0},"size":0.0,"lineType":"ltNone","lineWidth":0.0,"fillColor":{"r":0.0,"g":0.0,"b":0.0,"a":0.0},"marker":"mkCircle","errorBarKind":"ebLines","gradient":null,"font":{"family":"","size":0.0,"bold":false,"slant":"fsNormal","color":{"r":0.0,"g":0.0,"b":0.0,"a":0.0},"alignKind":"taLeft"}},"xScale":{"low":0.0,"high":1.0},"yScale":{"low":0.0,"high":1.0},"rotate":null,"scale":null,"origin":{"x":{"pos":0.0,"kind":"ukRelative"},"y":{"pos":0.0,"kind":"ukRelative"}},"width":{"val":1.0,"unit":"ukRelative"},"height":{"val":1.0,"unit":"ukRelative"},"objects":[],"children":[{"name":"data/layout_0","parent":"data","style":{"color":{"r":0.0,"g":0.0,"b":0.0,"a":0.0},"size":0.0,"lineType":"ltNone","lineWidth":0.0,"fillColor":{"r":0.0,"g":0.0,"b":0.0,"a":0.0},"marker":"mkCircle","errorBarKind":"ebLines","gradient":null,"font":{"family":"","size":0.0,"bold":false,"slant":"fsNormal","color":{"r":0.0,"g":0.0,"b":0.0,"a":0.0},"alignKind":"taLeft"}},"xScale":{"low":0.0,"high":1.0},"yScale":{"low":0.0,"high":1.0},"rotate":null,"scale":null,"origin":{"x":{"pos":0.0,"kind":"ukRelative"},"y":{"pos":0.0,"kind":"ukRelative"}},"width":{"val":0.2,"unit":"ukCentimeter"},"height":{"val":0.2,"unit":"ukCentimeter"},"objects":[],"children":[],"wView":{"val":426.6043307086614,"unit":"ukPoint"},"hView":{"val":387.52854330708664,"unit":"ukPoint"},"wImg":{"val":640.0,"unit":"ukPoint"},"hImg":{"val":480.0,"unit":"ukPoint"},"backend":"bkCairo"},{"name":"data/layout_1","parent":"data","style":{"color":{"r":0.0,"g":0.0,"b":0.0,"a":0.0},"size":0.0,"lineType":"ltNone","lineWidth":0.0,"fillColor":{"r":0.0,"g":0.0,"b":0.0,"a":0.0},"marker":"mkCircle","errorBarKind":"ebLines","gradient":null,"font":{"family":"","size":0.0,"bold":false,"slant":"fsNormal","color":{"r":0.0,"g":0.0,"b":0.0,"a":0.0},"alignKind":"taLeft"}},"xScale":{"low":0.0,"high":1.0},"yScale":{"low":0.0,"high":1.0},"rotate":null,"scale":null,"origin":{"x":{"pos":0.2,"kind":"ukCentimeter","length":{"val":14.993427424934273,"unit":"ukCentimeter"}},"y":{"pos":0.0,"kind":"ukRelative"}},"width":{"val":0.3244405478777811,"unit":"ukRelative"},"height":{"val":0.2,"unit":"ukCentimeter"},"objects":[],"children":[],"wView":{"val":426.6043307086614,"unit":"ukPoint"},"hView":{"val":387.52854330708664,"unit":"ukPoint"},"wImg":{"val":640.0,"unit":"ukPoint"},"hImg":{"val":480.0,"unit":"ukPoint"},"backend":"bkCairo"},{"name":"data/layout_2","parent":"data","style":{"color":{"r":0.0,"g":0.0,"b":0.0,"a":0.0},"size":0.0,"lineType":"ltNone","lineWidth":0.0,"fillColor":{"r":0.0,"g":0.0,"b":0.0,"a":0.0},"marker":"mkCircle","errorBarKind":"ebLines","gradient":null,"font":{"family":"","size":0.0,"bold":false,"slant":"fsNormal","color":{"r":0.0,"g":0.0,"b":0.0,"a":0.0},"alignKind":"taLeft"}},"xScale":{"low":0.0,"high":1.0},"yScale":{"low":0.0,"high":1.0},"rotate":null,"scale":null,"origin":{"x":{"pos":5.064475808311424,"kind":"ukCentimeter","length":{"val":14.993427424934273,"unit":"ukCentimeter"}},"y":{"pos":0.0,"kind":"ukRelative"}},"width":{"val":0.3244405478777811,"unit":"ukRelative"},"height":{"val":0.2,"unit":"ukCentimeter"},"objects":[],"children":[],"wView":{"val":426.6043307086614,"unit":"ukPoint"},"hView":{"val":387.52854330708664,"unit":"ukPoint"},"wImg":{"val":640.0,"unit":"ukPoint"},"hImg":{"val":480.0,"unit":"ukPoint"},"backend":"bkCairo"},{"name":"data/layout_3","parent":"data","style":{"color":{"r":0.0,"g":0.0,"b":0.0,"a":0.0},"size":0.0,"lineType":"ltNone","lineWidth":0.0,"fillColor":{"r":0.0,"g":0.0,"b":0.0,"a":0.0},"marker":"mkCircle","errorBarKind":"ebLines","gradient":null,"font":{"family":"","size":0.0,"bold":false,"slant":"fsNormal","color":{"r":0.0,"g":0.0,"b":0.0,"a":0.0},"alignKind":"taLeft"}},"xScale":{"low":0.0,"high":1.0},"yScale":{"low":0.0,"high":1.0},"rotate":null,"scale":null,"origin":{"x":{"pos":9.928951616622847,"kind":"ukCentimeter","length":{"val":14.993427424934273,"unit":"ukCentimeter"}},"y":{"pos":0.0,"kind":"ukRelative"}},"width":{"val":0.3244405478777811,"unit":"ukRelative"},"height":{"val":0.2,"unit":"ukCentimeter"},"objects":[],"children":[],"wView":{"val":426.6043307086614,"unit":"ukPoint"},"hView":{"val":387.52854330708664,"unit":"ukPoint"},"wImg":{"val":640.0,"unit":"ukPoint"},"hImg":{"val":480.0,"unit":"ukPoint"},"backend":"bkCairo"},{"name":"data/layout_4","parent":"data","style":{"color":{"r":0.0,"g":0.0,"b":0.0,"a":0.0},"size":0.0,"lineType":"ltNone","lineWidth":0.0,"fillColor":{"r":0.0,"g":0.0,"b":0.0,"a":0.0},"marker":"mkCircle","errorBarKind":"ebLines","gradient":null,"font":{"family":"","size":0.0,"bold":false,"slant":"fsNormal","color":{"r":0.0,"g":0.0,"b":0.0,"a":0.0},"alignKind":"taLeft"}},"xScale":{"low":0.0,"high":1.0},"yScale":{"low":0.0,"high":1.0},"rotate":null,"scale":null,"origin":{"x":{"pos":14.793427424934269,"kind":"ukCentimeter","length":{"val":14.993427424934273,"unit":"ukCentimeter"}},"y":{"pos":0.0,"kind":"ukRelative"}},"width":{"val":0.2,"unit":"ukCentimeter"},"height":{"val":0.2,"unit":"ukCentimeter"},"objects":[],"children":[],"wView":{"val":426.6043307086614,"unit":"ukPoint"},"hView":{"val":387.52854330708664,"unit":"ukPoint"},"wImg":{"val":640.0,"unit":"ukPoint"},"hImg":{"val":480.0,"unit":"ukPoint"},"backend":"bkCairo"},{"name":"data/layout_5","parent":"data","style":{"color":{"r":0.0,"g":0.0,"b":0.0,"a":0.0},"size":0.0,"lineType":"ltNone","lineWidth":0.0,"fillColor":{"r":0.0,"g":0.0,"b":0.0,"a":0.0},"marker":"mkCircle","errorBarKind":"ebLines","gradient":null,"font":{"family":"","size":0.0,"bold":false,"slant":"fsNormal","color":{"r":0.0,"g":0.0,"b":0.0,"a":0.0},"alignKind":"taLeft"}},"xScale":{"low":0.0,"high":1.0},"yScale":{"low":0.0,"high":1.0},"rotate":null,"scale":null,"origin":{"x":{"pos":0.0,"kind":"ukRelative"},"y":{"pos":0.2,"kind":"ukCentimeter","length":{"val":13.620070568700708,"unit":"ukCentimeter"}}},"width":{"val":0.2,"unit":"ukCentimeter"},"height":{"val":0.4853157882706125,"unit":"ukRelative"},"objects":[],"children":[],"wView":{"val":426.6043307086614,"unit":"ukPoint"},"hView":{"val":387.52854330708664,"unit":"ukPoint"},"wImg":{"val":640.0,"unit":"ukPoint"},"hImg":{"val":480.0,"unit":"ukPoint"},"backend":"bkCairo"},{"name":"data/layout_6","parent":"data","style":{"color":{"r":0.0,"g":0.0,"b":0.0,"a":0.0},"size":0.0,"lineType":"ltNone","lineWidth":0.0,"fillColor":{"r":0.0,"g":0.0,"b":0.0,"a":0.0},"marker":"mkCircle","errorBarKind":"ebLines","gradient":null,"font":{"family":"","size":0.0,"bold":false,"slant":"fsNormal","color":{"r":0.0,"g":0.0,"b":0.0,"a":0.0},"alignKind":"taLeft"}},"xScale":{"low":0.0,"high":1.0},"yScale":{"low":0.0,"high":1.0},"rotate":null,"scale":null,"origin":{"x":{"pos":0.2,"kind":"ukCentimeter","length":{"val":14.993427424934273,"unit":"ukCentimeter"}},"y":{"pos":0.2,"kind":"ukCentimeter","length":{"val":13.620070568700708,"unit":"ukCentimeter"}}},"width":{"val":0.3244405478777811,"unit":"ukRelative"},"height":{"val":0.4853157882706125,"unit":"ukRelative"},"objects":[{"name":"rect","children":[],"style":{"color":{"r":1.0,"g":0.0,"b":0.0,"a":1.0},"size":0.0,"lineType":"ltSolid","lineWidth":0.05,"fillColor":{"r":1.0,"g":0.0,"b":0.0,"a":1.0},"marker":"mkCircle","errorBarKind":"ebLines","gradient":null,"font":{"family":"","size":0.0,"bold":false,"slant":"fsNormal","color":{"r":0.0,"g":0.0,"b":0.0,"a":0.0},"alignKind":"taLeft"}},"rotateInView":null,"rotate":null,"kind":"goRect","reOrigin":{"x":{"pos":0.0,"kind":"ukRelative"},"y":{"pos":1.0,"kind":"ukRelative"}},"reWidth":{"val":1.0,"unit":"ukData"},"reHeight":{"val":-1.0,"unit":"ukData"}}],"children":[],"wView":{"val":426.6043307086614,"unit":"ukPoint"},"hView":{"val":387.52854330708664,"unit":"ukPoint"},"wImg":{"val":640.0,"unit":"ukPoint"},"hImg":{"val":480.0,"unit":"ukPoint"},"backend":"bkCairo"},{"name":"data/layout_7","parent":"data","style":{"color":{"r":0.0,"g":0.0,"b":0.0,"a":0.0},"size":0.0,"lineType":"ltNone","lineWidth":0.0,"fillColor":{"r":0.0,"g":0.0,"b":0.0,"a":0.0},"marker":"mkCircle","errorBarKind":"ebLines","gradient":null,"font":{"family":"","size":0.0,"bold":false,"slant":"fsNormal","color":{"r":0.0,"g":0.0,"b":0.0,"a":0.0},"alignKind":"taLeft"}},"xScale":{"low":0.0,"high":1.0},"yScale":{"low":0.0,"high":1.0},"rotate":null,"scale":null,"origin":{"x":{"pos":5.064475808311424,"kind":"ukCentimeter","length":{"val":14.993427424934273,"unit":"ukCentimeter"}},"y":{"pos":0.2,"kind":"ukCentimeter","length":{"val":13.620070568700708,"unit":"ukCentimeter"}}},"width":{"val":0.3244405478777811,"unit":"ukRelative"},"height":{"val":0.4853157882706125,"unit":"ukRelative"},"objects":[{"name":"rect","children":[],"style":{"color":{"r":0.0,"g":1.0,"b":0.0,"a":1.0},"size":0.0,"lineType":"ltSolid","lineWidth":0.05,"fillColor":{"r":0.0,"g":1.0,"b":0.0,"a":1.0},"marker":"mkCircle","errorBarKind":"ebLines","gradient":null,"font":{"family":"","size":0.0,"bold":false,"slant":"fsNormal","color":{"r":0.0,"g":0.0,"b":0.0,"a":0.0},"alignKind":"taLeft"}},"rotateInView":null,"rotate":null,"kind":"goRect","reOrigin":{"x":{"pos":0.0,"kind":"ukRelative"},"y":{"pos":1.0,"kind":"ukRelative"}},"reWidth":{"val":1.0,"unit":"ukData"},"reHeight":{"val":-1.0,"unit":"ukData"}}],"children":[],"wView":{"val":426.6043307086614,"unit":"ukPoint"},"hView":{"val":387.52854330708664,"unit":"ukPoint"},"wImg":{"val":640.0,"unit":"ukPoint"},"hImg":{"val":480.0,"unit":"ukPoint"},"backend":"bkCairo"},{"name":"data/layout_8","parent":"data","style":{"color":{"r":0.0,"g":0.0,"b":0.0,"a":0.0},"size":0.0,"lineType":"ltNone","lineWidth":0.0,"fillColor":{"r":0.0,"g":0.0,"b":0.0,"a":0.0},"marker":"mkCircle","errorBarKind":"ebLines","gradient":null,"font":{"family":"","size":0.0,"bold":false,"slant":"fsNormal","color":{"r":0.0,"g":0.0,"b":0.0,"a":0.0},"alignKind":"taLeft"}},"xScale":{"low":0.0,"high":1.0},"yScale":{"low":0.0,"high":1.0},"rotate":null,"scale":null,"origin":{"x":{"pos":9.928951616622847,"kind":"ukCentimeter","length":{"val":14.993427424934273,"unit":"ukCentimeter"}},"y":{"pos":0.2,"kind":"ukCentimeter","length":{"val":13.620070568700708,"unit":"ukCentimeter"}}},"width":{"val":0.3244405478777811,"unit":"ukRelative"},"height":{"val":0.4853157882706125,"unit":"ukRelative"},"objects":[{"name":"rect","children":[],"style":{"color":{"r":1.0,"g":0.0,"b":1.0,"a":1.0},"size":0.0,"lineType":"ltSolid","lineWidth":0.05,"fillColor":{"r":1.0,"g":0.0,"b":1.0,"a":1.0},"marker":"mkCircle","errorBarKind":"ebLines","gradient":null,"font":{"family":"","size":0.0,"bold":false,"slant":"fsNormal","color":{"r":0.0,"g":0.0,"b":0.0,"a":0.0},"alignKind":"taLeft"}},"rotateInView":null,"rotate":null,"kind":"goRect","reOrigin":{"x":{"pos":0.0,"kind":"ukRelative"},"y":{"pos":1.0,"kind":"ukRelative"}},"reWidth":{"val":1.0,"unit":"ukData"},"reHeight":{"val":-1.0,"unit":"ukData"}}],"children":[],"wView":{"val":426.6043307086614,"unit":"ukPoint"},"hView":{"val":387.52854330708664,"unit":"ukPoint"},"wImg":{"val":640.0,"unit":"ukPoint"},"hImg":{"val":480.0,"unit":"ukPoint"},"backend":"bkCairo"},{"name":"data/layout_9","parent":"data","style":{"color":{"r":0.0,"g":0.0,"b":0.0,"a":0.0},"size":0.0,"lineType":"ltNone","lineWidth":0.0,"fillColor":{"r":0.0,"g":0.0,"b":0.0,"a":0.0},"marker":"mkCircle","errorBarKind":"ebLines","gradient":null,"font":{"family":"","size":0.0,"bold":false,"slant":"fsNormal","color":{"r":0.0,"g":0.0,"b":0.0,"a":0.0},"alignKind":"taLeft"}},"xScale":{"low":0.0,"high":1.0},"yScale":{"low":0.0,"high":1.0},"rotate":null,"scale":null,"origin":{"x":{"pos":14.793427424934269,"kind":"ukCentimeter","length":{"val":14.993427424934273,"unit":"ukCentimeter"}},"y":{"pos":0.2,"kind":"ukCentimeter","length":{"val":13.620070568700708,"unit":"ukCentimeter"}}},"width":{"val":0.2,"unit":"ukCentimeter"},"height":{"val":0.4853157882706125,"unit":"ukRelative"},"objects":[],"children":[],"wView":{"val":426.6043307086614,"unit":"ukPoint"},"hView":{"val":387.52854330708664,"unit":"ukPoint"},"wImg":{"val":640.0,"unit":"ukPoint"},"hImg":{"val":480.0,"unit":"ukPoint"},"backend":"bkCairo"},{"name":"data/layout_10","parent":"data","style":{"color":{"r":0.0,"g":0.0,"b":0.0,"a":0.0},"size":0.0,"lineType":"ltNone","lineWidth":0.0,"fillColor":{"r":0.0,"g":0.0,"b":0.0,"a":0.0},"marker":"mkCircle","errorBarKind":"ebLines","gradient":null,"font":{"family":"","size":0.0,"bold":false,"slant":"fsNormal","color":{"r":0.0,"g":0.0,"b":0.0,"a":0.0},"alignKind":"taLeft"}},"xScale":{"low":0.0,"high":1.0},"yScale":{"low":0.0,"high":1.0},"rotate":null,"scale":null,"origin":{"x":{"pos":0.0,"kind":"ukRelative"},"y":{"pos":6.810035284350354,"kind":"ukCentimeter","length":{"val":13.620070568700708,"unit":"ukCentimeter"}}},"width":{"val":0.2,"unit":"ukCentimeter"},"height":{"val":0.4853157882706125,"unit":"ukRelative"},"objects":[],"children":[],"wView":{"val":426.6043307086614,"unit":"ukPoint"},"hView":{"val":387.52854330708664,"unit":"ukPoint"},"wImg":{"val":640.0,"unit":"ukPoint"},"hImg":{"val":480.0,"unit":"ukPoint"},"backend":"bkCairo"},{"name":"data/layout_11","parent":"data","style":{"color":{"r":0.0,"g":0.0,"b":0.0,"a":0.0},"size":0.0,"lineType":"ltNone","lineWidth":0.0,"fillColor":{"r":0.0,"g":0.0,"b":0.0,"a":0.0},"marker":"mkCircle","errorBarKind":"ebLines","gradient":null,"font":{"family":"","size":0.0,"bold":false,"slant":"fsNormal","color":{"r":0.0,"g":0.0,"b":0.0,"a":0.0},"alignKind":"taLeft"}},"xScale":{"low":0.0,"high":1.0},"yScale":{"low":0.0,"high":1.0},"rotate":null,"scale":null,"origin":{"x":{"pos":0.2,"kind":"ukCentimeter","length":{"val":14.993427424934273,"unit":"ukCentimeter"}},"y":{"pos":6.810035284350354,"kind":"ukCentimeter","length":{"val":13.620070568700708,"unit":"ukCentimeter"}}},"width":{"val":0.3244405478777811,"unit":"ukRelative"},"height":{"val":0.4853157882706125,"unit":"ukRelative"},"objects":[{"name":"rect","children":[],"style":{"color":{"r":1.0,"g":0.0,"b":1.0,"a":1.0},"size":0.0,"lineType":"ltSolid","lineWidth":0.05,"fillColor":{"r":1.0,"g":0.0,"b":1.0,"a":1.0},"marker":"mkCircle","errorBarKind":"ebLines","gradient":null,"font":{"family":"","size":0.0,"bold":false,"slant":"fsNormal","color":{"r":0.0,"g":0.0,"b":0.0,"a":0.0},"alignKind":"taLeft"}},"rotateInView":null,"rotate":null,"kind":"goRect","reOrigin":{"x":{"pos":0.0,"kind":"ukRelative"},"y":{"pos":1.0,"kind":"ukRelative"}},"reWidth":{"val":1.0,"unit":"ukData"},"reHeight":{"val":-1.0,"unit":"ukData"}}],"children":[],"wView":{"val":426.6043307086614,"unit":"ukPoint"},"hView":{"val":387.52854330708664,"unit":"ukPoint"},"wImg":{"val":640.0,"unit":"ukPoint"},"hImg":{"val":480.0,"unit":"ukPoint"},"backend":"bkCairo"},{"name":"data/layout_12","parent":"data","style":{"color":{"r":0.0,"g":0.0,"b":0.0,"a":0.0},"size":0.0,"lineType":"ltNone","lineWidth":0.0,"fillColor":{"r":0.0,"g":0.0,"b":0.0,"a":0.0},"marker":"mkCircle","errorBarKind":"ebLines","gradient":null,"font":{"family":"","size":0.0,"bold":false,"slant":"fsNormal","color":{"r":0.0,"g":0.0,"b":0.0,"a":0.0},"alignKind":"taLeft"}},"xScale":{"low":0.0,"high":1.0},"yScale":{"low":0.0,"high":1.0},"rotate":null,"scale":null,"origin":{"x":{"pos":5.064475808311424,"kind":"ukCentimeter","length":{"val":14.993427424934273,"unit":"ukCentimeter"}},"y":{"pos":6.810035284350354,"kind":"ukCentimeter","length":{"val":13.620070568700708,"unit":"ukCentimeter"}}},"width":{"val":0.3244405478777811,"unit":"ukRelative"},"height":{"val":0.4853157882706125,"unit":"ukRelative"},"objects":[{"name":"rect","children":[],"style":{"color":{"r":0.0,"g":0.0,"b":1.0,"a":1.0},"size":0.0,"lineType":"ltSolid","lineWidth":0.05,"fillColor":{"r":0.0,"g":0.0,"b":1.0,"a":1.0},"marker":"mkCircle","errorBarKind":"ebLines","gradient":null,"font":{"family":"","size":0.0,"bold":false,"slant":"fsNormal","color":{"r":0.0,"g":0.0,"b":0.0,"a":0.0},"alignKind":"taLeft"}},"rotateInView":null,"rotate":null,"kind":"goRect","reOrigin":{"x":{"pos":0.0,"kind":"ukRelative"},"y":{"pos":1.0,"kind":"ukRelative"}},"reWidth":{"val":1.0,"unit":"ukData"},"reHeight":{"val":-1.0,"unit":"ukData"}}],"children":[],"wView":{"val":426.6043307086614,"unit":"ukPoint"},"hView":{"val":387.52854330708664,"unit":"ukPoint"},"wImg":{"val":640.0,"unit":"ukPoint"},"hImg":{"val":480.0,"unit":"ukPoint"},"backend":"bkCairo"},{"name":"data/layout_13","parent":"data","style":{"color":{"r":0.0,"g":0.0,"b":0.0,"a":0.0},"size":0.0,"lineType":"ltNone","lineWidth":0.0,"fillColor":{"r":0.0,"g":0.0,"b":0.0,"a":0.0},"marker":"mkCircle","errorBarKind":"ebLines","gradient":null,"font":{"family":"","size":0.0,"bold":false,"slant":"fsNormal","color":{"r":0.0,"g":0.0,"b":0.0,"a":0.0},"alignKind":"taLeft"}},"xScale":{"low":0.0,"high":1.0},"yScale":{"low":0.0,"high":1.0},"rotate":null,"scale":null,"origin":{"x":{"pos":9.928951616622847,"kind":"ukCentimeter","length":{"val":14.993427424934273,"unit":"ukCentimeter"}},"y":{"pos":6.810035284350354,"kind":"ukCentimeter","length":{"val":13.620070568700708,"unit":"ukCentimeter"}}},"width":{"val":0.3244405478777811,"unit":"ukRelative"},"height":{"val":0.4853157882706125,"unit":"ukRelative"},"objects":[{"name":"rect","children":[],"style":{"color":{"r":1.0,"g":1.0,"b":0.0,"a":1.0},"size":0.0,"lineType":"ltSolid","lineWidth":0.05,"fillColor":{"r":1.0,"g":1.0,"b":0.0,"a":1.0},"marker":"mkCircle","errorBarKind":"ebLines","gradient":null,"font":{"family":"","size":0.0,"bold":false,"slant":"fsNormal","color":{"r":0.0,"g":0.0,"b":0.0,"a":0.0},"alignKind":"taLeft"}},"rotateInView":null,"rotate":null,"kind":"goRect","reOrigin":{"x":{"pos":0.0,"kind":"ukRelative"},"y":{"pos":1.0,"kind":"ukRelative"}},"reWidth":{"val":1.0,"unit":"ukData"},"reHeight":{"val":-1.0,"unit":"ukData"}}],"children":[],"wView":{"val":426.6043307086614,"unit":"ukPoint"},"hView":{"val":387.52854330708664,"unit":"ukPoint"},"wImg":{"val":640.0,"unit":"ukPoint"},"hImg":{"val":480.0,"unit":"ukPoint"},"backend":"bkCairo"},{"name":"data/layout_14","parent":"data","style":{"color":{"r":0.0,"g":0.0,"b":0.0,"a":0.0},"size":0.0,"lineType":"ltNone","lineWidth":0.0,"fillColor":{"r":0.0,"g":0.0,"b":0.0,"a":0.0},"marker":"mkCircle","errorBarKind":"ebLines","gradient":null,"font":{"family":"","size":0.0,"bold":false,"slant":"fsNormal","color":{"r":0.0,"g":0.0,"b":0.0,"a":0.0},"alignKind":"taLeft"}},"xScale":{"low":0.0,"high":1.0},"yScale":{"low":0.0,"high":1.0},"rotate":null,"scale":null,"origin":{"x":{"pos":14.793427424934269,"kind":"ukCentimeter","length":{"val":14.993427424934273,"unit":"ukCentimeter"}},"y":{"pos":6.810035284350354,"kind":"ukCentimeter","length":{"val":13.620070568700708,"unit":"ukCentimeter"}}},"width":{"val":0.2,"unit":"ukCentimeter"},"height":{"val":0.4853157882706125,"unit":"ukRelative"},"objects":[],"children":[],"wView":{"val":426.6043307086614,"unit":"ukPoint"},"hView":{"val":387.52854330708664,"unit":"ukPoint"},"wImg":{"val":640.0,"unit":"ukPoint"},"hImg":{"val":480.0,"unit":"ukPoint"},"backend":"bkCairo"},{"name":"data/layout_15","parent":"data","style":{"color":{"r":0.0,"g":0.0,"b":0.0,"a":0.0},"size":0.0,"lineType":"ltNone","lineWidth":0.0,"fillColor":{"r":0.0,"g":0.0,"b":0.0,"a":0.0},"marker":"mkCircle","errorBarKind":"ebLines","gradient":null,"font":{"family":"","size":0.0,"bold":false,"slant":"fsNormal","color":{"r":0.0,"g":0.0,"b":0.0,"a":0.0},"alignKind":"taLeft"}},"xScale":{"low":0.0,"high":1.0},"yScale":{"low":0.0,"high":1.0},"rotate":null,"scale":null,"origin":{"x":{"pos":0.0,"kind":"ukRelative"},"y":{"pos":13.420070568700709,"kind":"ukCentimeter","length":{"val":13.620070568700708,"unit":"ukCentimeter"}}},"width":{"val":0.2,"unit":"ukCentimeter"},"height":{"val":0.2,"unit":"ukCentimeter"},"objects":[],"children":[],"wView":{"val":426.6043307086614,"unit":"ukPoint"},"hView":{"val":387.52854330708664,"unit":"ukPoint"},"wImg":{"val":640.0,"unit":"ukPoint"},"hImg":{"val":480.0,"unit":"ukPoint"},"backend":"bkCairo"},{"name":"data/layout_16","parent":"data","style":{"color":{"r":0.0,"g":0.0,"b":0.0,"a":0.0},"size":0.0,"lineType":"ltNone","lineWidth":0.0,"fillColor":{"r":0.0,"g":0.0,"b":0.0,"a":0.0},"marker":"mkCircle","errorBarKind":"ebLines","gradient":null,"font":{"family":"","size":0.0,"bold":false,"slant":"fsNormal","color":{"r":0.0,"g":0.0,"b":0.0,"a":0.0},"alignKind":"taLeft"}},"xScale":{"low":0.0,"high":1.0},"yScale":{"low":0.0,"high":1.0},"rotate":null,"scale":null,"origin":{"x":{"pos":0.2,"kind":"ukCentimeter","length":{"val":14.993427424934273,"unit":"ukCentimeter"}},"y":{"pos":13.420070568700709,"kind":"ukCentimeter","length":{"val":13.620070568700708,"unit":"ukCentimeter"}}},"width":{"val":0.3244405478777811,"unit":"ukRelative"},"height":{"val":0.2,"unit":"ukCentimeter"},"objects":[],"children":[],"wView":{"val":426.6043307086614,"unit":"ukPoint"},"hView":{"val":387.52854330708664,"unit":"ukPoint"},"wImg":{"val":640.0,"unit":"ukPoint"},"hImg":{"val":480.0,"unit":"ukPoint"},"backend":"bkCairo"},{"name":"data/layout_17","parent":"data","style":{"color":{"r":0.0,"g":0.0,"b":0.0,"a":0.0},"size":0.0,"lineType":"ltNone","lineWidth":0.0,"fillColor":{"r":0.0,"g":0.0,"b":0.0,"a":0.0},"marker":"mkCircle","errorBarKind":"ebLines","gradient":null,"font":{"family":"","size":0.0,"bold":false,"slant":"fsNormal","color":{"r":0.0,"g":0.0,"b":0.0,"a":0.0},"alignKind":"taLeft"}},"xScale":{"low":0.0,"high":1.0},"yScale":{"low":0.0,"high":1.0},"rotate":null,"scale":null,"origin":{"x":{"pos":5.064475808311424,"kind":"ukCentimeter","length":{"val":14.993427424934273,"unit":"ukCentimeter"}},"y":{"pos":13.420070568700709,"kind":"ukCentimeter","length":{"val":13.620070568700708,"unit":"ukCentimeter"}}},"width":{"val":0.3244405478777811,"unit":"ukRelative"},"height":{"val":0.2,"unit":"ukCentimeter"},"objects":[],"children":[],"wView":{"val":426.6043307086614,"unit":"ukPoint"},"hView":{"val":387.52854330708664,"unit":"ukPoint"},"wImg":{"val":640.0,"unit":"ukPoint"},"hImg":{"val":480.0,"unit":"ukPoint"},"backend":"bkCairo"},{"name":"data/layout_18","parent":"data","style":{"color":{"r":0.0,"g":0.0,"b":0.0,"a":0.0},"size":0.0,"lineType":"ltNone","lineWidth":0.0,"fillColor":{"r":0.0,"g":0.0,"b":0.0,"a":0.0},"marker":"mkCircle","errorBarKind":"ebLines","gradient":null,"font":{"family":"","size":0.0,"bold":false,"slant":"fsNormal","color":{"r":0.0,"g":0.0,"b":0.0,"a":0.0},"alignKind":"taLeft"}},"xScale":{"low":0.0,"high":1.0},"yScale":{"low":0.0,"high":1.0},"rotate":null,"scale":null,"origin":{"x":{"pos":9.928951616622847,"kind":"ukCentimeter","length":{"val":14.993427424934273,"unit":"ukCentimeter"}},"y":{"pos":13.420070568700709,"kind":"ukCentimeter","length":{"val":13.620070568700708,"unit":"ukCentimeter"}}},"width":{"val":0.3244405478777811,"unit":"ukRelative"},"height":{"val":0.2,"unit":"ukCentimeter"},"objects":[],"children":[],"wView":{"val":426.6043307086614,"unit":"ukPoint"},"hView":{"val":387.52854330708664,"unit":"ukPoint"},"wImg":{"val":640.0,"unit":"ukPoint"},"hImg":{"val":480.0,"unit":"ukPoint"},"backend":"bkCairo"},{"name":"data/layout_19","parent":"data","style":{"color":{"r":0.0,"g":0.0,"b":0.0,"a":0.0},"size":0.0,"lineType":"ltNone","lineWidth":0.0,"fillColor":{"r":0.0,"g":0.0,"b":0.0,"a":0.0},"marker":"mkCircle","errorBarKind":"ebLines","gradient":null,"font":{"family":"","size":0.0,"bold":false,"slant":"fsNormal","color":{"r":0.0,"g":0.0,"b":0.0,"a":0.0},"alignKind":"taLeft"}},"xScale":{"low":0.0,"high":1.0},"yScale":{"low":0.0,"high":1.0},"rotate":null,"scale":null,"origin":{"x":{"pos":14.793427424934269,"kind":"ukCentimeter","length":{"val":14.993427424934273,"unit":"ukCentimeter"}},"y":{"pos":13.420070568700709,"kind":"ukCentimeter","length":{"val":13.620070568700708,"unit":"ukCentimeter"}}},"width":{"val":0.2,"unit":"ukCentimeter"},"height":{"val":0.2,"unit":"ukCentimeter"},"objects":[],"children":[],"wView":{"val":426.6043307086614,"unit":"ukPoint"},"hView":{"val":387.52854330708664,"unit":"ukPoint"},"wImg":{"val":640.0,"unit":"ukPoint"},"hImg":{"val":480.0,"unit":"ukPoint"},"backend":"bkCairo"}],"wView":{"val":426.6043307086614,"unit":"ukPoint"},"hView":{"val":387.52854330708664,"unit":"ukPoint"},"wImg":{"val":640.0,"unit":"ukPoint"},"hImg":{"val":480.0,"unit":"ukPoint"},"backend":"bkCairo"},{"name":"data","parent":"plot","style":{"color":{"r":0.0,"g":0.0,"b":0.0,"a":0.0},"size":0.0,"lineType":"ltNone","lineWidth":0.0,"fillColor":{"r":0.0,"g":0.0,"b":0.0,"a":0.0},"marker":"mkCircle","errorBarKind":"ebLines","gradient":null,"font":{"family":"","size":0.0,"bold":false,"slant":"fsNormal","color":{"r":0.0,"g":0.0,"b":0.0,"a":0.0},"alignKind":"taLeft"}},"xScale":{"low":0.0,"high":1.0},"yScale":{"low":0.0,"high":1.0},"rotate":null,"scale":null,"origin":{"x":{"pos":0.0,"kind":"ukRelative"},"y":{"pos":0.0,"kind":"ukRelative"}},"width":{"val":1.0,"unit":"ukRelative"},"height":{"val":1.0,"unit":"ukRelative"},"objects":[],"children":[{"name":"data/layout_0","parent":"data","style":{"color":{"r":0.0,"g":0.0,"b":0.0,"a":0.0},"size":0.0,"lineType":"ltNone","lineWidth":0.0,"fillColor":{"r":0.0,"g":0.0,"b":0.0,"a":0.0},"marker":"mkCircle","errorBarKind":"ebLines","gradient":null,"font":{"family":"","size":0.0,"bold":false,"slant":"fsNormal","color":{"r":0.0,"g":0.0,"b":0.0,"a":0.0},"alignKind":"taLeft"}},"xScale":{"low":0.0,"high":1.0},"yScale":{"low":0.0,"high":1.0},"rotate":null,"scale":null,"origin":{"x":{"pos":0.0,"kind":"ukRelative"},"y":{"pos":0.0,"kind":"ukRelative"}},"width":{"val":0.2,"unit":"ukCentimeter"},"height":{"val":0.2,"unit":"ukCentimeter"},"objects":[],"children":[],"wView":{"val":426.6043307086614,"unit":"ukPoint"},"hView":{"val":387.52854330708664,"unit":"ukPoint"},"wImg":{"val":640.0,"unit":"ukPoint"},"hImg":{"val":480.0,"unit":"ukPoint"},"backend":"bkCairo"},{"name":"data/layout_1","parent":"data","style":{"color":{"r":0.0,"g":0.0,"b":0.0,"a":0.0},"size":0.0,"lineType":"ltNone","lineWidth":0.0,"fillColor":{"r":0.0,"g":0.0,"b":0.0,"a":0.0},"marker":"mkCircle","errorBarKind":"ebLines","gradient":null,"font":{"family":"","size":0.0,"bold":false,"slant":"fsNormal","color":{"r":0.0,"g":0.0,"b":0.0,"a":0.0},"alignKind":"taLeft"}},"xScale":{"low":0.0,"high":1.0},"yScale":{"low":0.0,"high":1.0},"rotate":null,"scale":null,"origin":{"x":{"pos":0.2,"kind":"ukCentimeter","length":{"val":14.993427424934273,"unit":"ukCentimeter"}},"y":{"pos":0.0,"kind":"ukRelative"}},"width":{"val":0.3244405478777811,"unit":"ukRelative"},"height":{"val":0.2,"unit":"ukCentimeter"},"objects":[],"children":[],"wView":{"val":426.6043307086614,"unit":"ukPoint"},"hView":{"val":387.52854330708664,"unit":"ukPoint"},"wImg":{"val":640.0,"unit":"ukPoint"},"hImg":{"val":480.0,"unit":"ukPoint"},"backend":"bkCairo"},{"name":"data/layout_2","parent":"data","style":{"color":{"r":0.0,"g":0.0,"b":0.0,"a":0.0},"size":0.0,"lineType":"ltNone","lineWidth":0.0,"fillColor":{"r":0.0,"g":0.0,"b":0.0,"a":0.0},"marker":"mkCircle","errorBarKind":"ebLines","gradient":null,"font":{"family":"","size":0.0,"bold":false,"slant":"fsNormal","color":{"r":0.0,"g":0.0,"b":0.0,"a":0.0},"alignKind":"taLeft"}},"xScale":{"low":0.0,"high":1.0},"yScale":{"low":0.0,"high":1.0},"rotate":null,"scale":null,"origin":{"x":{"pos":5.064475808311424,"kind":"ukCentimeter","length":{"val":14.993427424934273,"unit":"ukCentimeter"}},"y":{"pos":0.0,"kind":"ukRelative"}},"width":{"val":0.3244405478777811,"unit":"ukRelative"},"height":{"val":0.2,"unit":"ukCentimeter"},"objects":[],"children":[],"wView":{"val":426.6043307086614,"unit":"ukPoint"},"hView":{"val":387.52854330708664,"unit":"ukPoint"},"wImg":{"val":640.0,"unit":"ukPoint"},"hImg":{"val":480.0,"unit":"ukPoint"},"backend":"bkCairo"},{"name":"data/layout_3","parent":"data","style":{"color":{"r":0.0,"g":0.0,"b":0.0,"a":0.0},"size":0.0,"lineType":"ltNone","lineWidth":0.0,"fillColor":{"r":0.0,"g":0.0,"b":0.0,"a":0.0},"marker":"mkCircle","errorBarKind":"ebLines","gradient":null,"font":{"family":"","size":0.0,"bold":false,"slant":"fsNormal","color":{"r":0.0,"g":0.0,"b":0.0,"a":0.0},"alignKind":"taLeft"}},"xScale":{"low":0.0,"high":1.0},"yScale":{"low":0.0,"high":1.0},"rotate":null,"scale":null,"origin":{"x":{"pos":9.928951616622847,"kind":"ukCentimeter","length":{"val":14.993427424934273,"unit":"ukCentimeter"}},"y":{"pos":0.0,"kind":"ukRelative"}},"width":{"val":0.3244405478777811,"unit":"ukRelative"},"height":{"val":0.2,"unit":"ukCentimeter"},"objects":[],"children":[],"wView":{"val":426.6043307086614,"unit":"ukPoint"},"hView":{"val":387.52854330708664,"unit":"ukPoint"},"wImg":{"val":640.0,"unit":"ukPoint"},"hImg":{"val":480.0,"unit":"ukPoint"},"backend":"bkCairo"},{"name":"data/layout_4","parent":"data","style":{"color":{"r":0.0,"g":0.0,"b":0.0,"a":0.0},"size":0.0,"lineType":"ltNone","lineWidth":0.0,"fillColor":{"r":0.0,"g":0.0,"b":0.0,"a":0.0},"marker":"mkCircle","errorBarKind":"ebLines","gradient":null,"font":{"family":"","size":0.0,"bold":false,"slant":"fsNormal","color":{"r":0.0,"g":0.0,"b":0.0,"a":0.0},"alignKind":"taLeft"}},"xScale":{"low":0.0,"high":1.0},"yScale":{"low":0.0,"high":1.0},"rotate":null,"scale":null,"origin":{"x":{"pos":14.793427424934269,"kind":"ukCentimeter","length":{"val":14.993427424934273,"unit":"ukCentimeter"}},"y":{"pos":0.0,"kind":"ukRelative"}},"width":{"val":0.2,"unit":"ukCentimeter"},"height":{"val":0.2,"unit":"ukCentimeter"},"objects":[],"children":[],"wView":{"val":426.6043307086614,"unit":"ukPoint"},"hView":{"val":387.52854330708664,"unit":"ukPoint"},"wImg":{"val":640.0,"unit":"ukPoint"},"hImg":{"val":480.0,"unit":"ukPoint"},"backend":"bkCairo"},{"name":"data/layout_5","parent":"data","style":{"color":{"r":0.0,"g":0.0,"b":0.0,"a":0.0},"size":0.0,"lineType":"ltNone","lineWidth":0.0,"fillColor":{"r":0.0,"g":0.0,"b":0.0,"a":0.0},"marker":"mkCircle","errorBarKind":"ebLines","gradient":null,"font":{"family":"","size":0.0,"bold":false,"slant":"fsNormal","color":{"r":0.0,"g":0.0,"b":0.0,"a":0.0},"alignKind":"taLeft"}},"xScale":{"low":0.0,"high":1.0},"yScale":{"low":0.0,"high":1.0},"rotate":null,"scale":null,"origin":{"x":{"pos":0.0,"kind":"ukRelative"},"y":{"pos":0.2,"kind":"ukCentimeter","length":{"val":13.620070568700708,"unit":"ukCentimeter"}}},"width":{"val":0.2,"unit":"ukCentimeter"},"height":{"val":0.4853157882706125,"unit":"ukRelative"},"objects":[],"children":[],"wView":{"val":426.6043307086614,"unit":"ukPoint"},"hView":{"val":387.52854330708664,"unit":"ukPoint"},"wImg":{"val":640.0,"unit":"ukPoint"},"hImg":{"val":480.0,"unit":"ukPoint"},"backend":"bkCairo"},{"name":"data/layout_6","parent":"data","style":{"color":{"r":0.0,"g":0.0,"b":0.0,"a":0.0},"size":0.0,"lineType":"ltNone","lineWidth":0.0,"fillColor":{"r":0.0,"g":0.0,"b":0.0,"a":0.0},"marker":"mkCircle","errorBarKind":"ebLines","gradient":null,"font":{"family":"","size":0.0,"bold":false,"slant":"fsNormal","color":{"r":0.0,"g":0.0,"b":0.0,"a":0.0},"alignKind":"taLeft"}},"xScale":{"low":0.0,"high":1.0},"yScale":{"low":0.0,"high":1.0},"rotate":null,"scale":null,"origin":{"x":{"pos":0.2,"kind":"ukCentimeter","length":{"val":14.993427424934273,"unit":"ukCentimeter"}},"y":{"pos":0.2,"kind":"ukCentimeter","length":{"val":13.620070568700708,"unit":"ukCentimeter"}}},"width":{"val":0.3244405478777811,"unit":"ukRelative"},"height":{"val":0.4853157882706125,"unit":"ukRelative"},"objects":[{"name":"text","children":[],"style":{"color":{"r":0.0,"g":0.0,"b":0.0,"a":0.0},"size":0.0,"lineType":"ltNone","lineWidth":0.0,"fillColor":{"r":0.0,"g":0.0,"b":0.0,"a":0.0},"marker":"mkCircle","errorBarKind":"ebLines","gradient":null,"font":{"family":"","size":0.0,"bold":false,"slant":"fsNormal","color":{"r":0.0,"g":0.0,"b":0.0,"a":0.0},"alignKind":"taLeft"}},"rotateInView":null,"rotate":null,"kind":"goText","txtText":"0","txtFont":{"family":"sans-serif","size":62.5,"bold":false,"slant":"fsNormal","color":{"r":0.0,"g":0.0,"b":0.0,"a":1.0},"alignKind":"taCenter"},"txtPos":{"x":{"pos":0.5,"kind":"ukRelative"},"y":{"pos":0.5,"kind":"ukRelative"}},"txtAlign":"taCenter","txtRotate":0.0}],"children":[],"wView":{"val":426.6043307086614,"unit":"ukPoint"},"hView":{"val":387.52854330708664,"unit":"ukPoint"},"wImg":{"val":640.0,"unit":"ukPoint"},"hImg":{"val":480.0,"unit":"ukPoint"},"backend":"bkCairo"},{"name":"data/layout_7","parent":"data","style":{"color":{"r":0.0,"g":0.0,"b":0.0,"a":0.0},"size":0.0,"lineType":"ltNone","lineWidth":0.0,"fillColor":{"r":0.0,"g":0.0,"b":0.0,"a":0.0},"marker":"mkCircle","errorBarKind":"ebLines","gradient":null,"font":{"family":"","size":0.0,"bold":false,"slant":"fsNormal","color":{"r":0.0,"g":0.0,"b":0.0,"a":0.0},"alignKind":"taLeft"}},"xScale":{"low":0.0,"high":1.0},"yScale":{"low":0.0,"high":1.0},"rotate":null,"scale":null,"origin":{"x":{"pos":5.064475808311424,"kind":"ukCentimeter","length":{"val":14.993427424934273,"unit":"ukCentimeter"}},"y":{"pos":0.2,"kind":"ukCentimeter","length":{"val":13.620070568700708,"unit":"ukCentimeter"}}},"width":{"val":0.3244405478777811,"unit":"ukRelative"},"height":{"val":0.4853157882706125,"unit":"ukRelative"},"objects":[{"name":"text","children":[],"style":{"color":{"r":0.0,"g":0.0,"b":0.0,"a":0.0},"size":0.0,"lineType":"ltNone","lineWidth":0.0,"fillColor":{"r":0.0,"g":0.0,"b":0.0,"a":0.0},"marker":"mkCircle","errorBarKind":"ebLines","gradient":null,"font":{"family":"","size":0.0,"bold":false,"slant":"fsNormal","color":{"r":0.0,"g":0.0,"b":0.0,"a":0.0},"alignKind":"taLeft"}},"rotateInView":null,"rotate":null,"kind":"goText","txtText":"1","txtFont":{"family":"sans-serif","size":62.5,"bold":false,"slant":"fsNormal","color":{"r":0.0,"g":0.0,"b":0.0,"a":1.0},"alignKind":"taCenter"},"txtPos":{"x":{"pos":0.5,"kind":"ukRelative"},"y":{"pos":0.5,"kind":"ukRelative"}},"txtAlign":"taCenter","txtRotate":0.0}],"children":[],"wView":{"val":426.6043307086614,"unit":"ukPoint"},"hView":{"val":387.52854330708664,"unit":"ukPoint"},"wImg":{"val":640.0,"unit":"ukPoint"},"hImg":{"val":480.0,"unit":"ukPoint"},"backend":"bkCairo"},{"name":"data/layout_8","parent":"data","style":{"color":{"r":0.0,"g":0.0,"b":0.0,"a":0.0},"size":0.0,"lineType":"ltNone","lineWidth":0.0,"fillColor":{"r":0.0,"g":0.0,"b":0.0,"a":0.0},"marker":"mkCircle","errorBarKind":"ebLines","gradient":null,"font":{"family":"","size":0.0,"bold":false,"slant":"fsNormal","color":{"r":0.0,"g":0.0,"b":0.0,"a":0.0},"alignKind":"taLeft"}},"xScale":{"low":0.0,"high":1.0},"yScale":{"low":0.0,"high":1.0},"rotate":null,"scale":null,"origin":{"x":{"pos":9.928951616622847,"kind":"ukCentimeter","length":{"val":14.993427424934273,"unit":"ukCentimeter"}},"y":{"pos":0.2,"kind":"ukCentimeter","length":{"val":13.620070568700708,"unit":"ukCentimeter"}}},"width":{"val":0.3244405478777811,"unit":"ukRelative"},"height":{"val":0.4853157882706125,"unit":"ukRelative"},"objects":[{"name":"text","children":[],"style":{"color":{"r":0.0,"g":0.0,"b":0.0,"a":0.0},"size":0.0,"lineType":"ltNone","lineWidth":0.0,"fillColor":{"r":0.0,"g":0.0,"b":0.0,"a":0.0},"marker":"mkCircle","errorBarKind":"ebLines","gradient":null,"font":{"family":"","size":0.0,"bold":false,"slant":"fsNormal","color":{"r":0.0,"g":0.0,"b":0.0,"a":0.0},"alignKind":"taLeft"}},"rotateInView":null,"rotate":null,"kind":"goText","txtText":"4","txtFont":{"family":"sans-serif","size":62.5,"bold":false,"slant":"fsNormal","color":{"r":0.0,"g":0.0,"b":0.0,"a":1.0},"alignKind":"taCenter"},"txtPos":{"x":{"pos":0.5,"kind":"ukRelative"},"y":{"pos":0.5,"kind":"ukRelative"}},"txtAlign":"taCenter","txtRotate":0.0}],"children":[],"wView":{"val":426.6043307086614,"unit":"ukPoint"},"hView":{"val":387.52854330708664,"unit":"ukPoint"},"wImg":{"val":640.0,"unit":"ukPoint"},"hImg":{"val":480.0,"unit":"ukPoint"},"backend":"bkCairo"},{"name":"data/layout_9","parent":"data","style":{"color":{"r":0.0,"g":0.0,"b":0.0,"a":0.0},"size":0.0,"lineType":"ltNone","lineWidth":0.0,"fillColor":{"r":0.0,"g":0.0,"b":0.0,"a":0.0},"marker":"mkCircle","errorBarKind":"ebLines","gradient":null,"font":{"family":"","size":0.0,"bold":false,"slant":"fsNormal","color":{"r":0.0,"g":0.0,"b":0.0,"a":0.0},"alignKind":"taLeft"}},"xScale":{"low":0.0,"high":1.0},"yScale":{"low":0.0,"high":1.0},"rotate":null,"scale":null,"origin":{"x":{"pos":14.793427424934269,"kind":"ukCentimeter","length":{"val":14.993427424934273,"unit":"ukCentimeter"}},"y":{"pos":0.2,"kind":"ukCentimeter","length":{"val":13.620070568700708,"unit":"ukCentimeter"}}},"width":{"val":0.2,"unit":"ukCentimeter"},"height":{"val":0.4853157882706125,"unit":"ukRelative"},"objects":[],"children":[],"wView":{"val":426.6043307086614,"unit":"ukPoint"},"hView":{"val":387.52854330708664,"unit":"ukPoint"},"wImg":{"val":640.0,"unit":"ukPoint"},"hImg":{"val":480.0,"unit":"ukPoint"},"backend":"bkCairo"},{"name":"data/layout_10","parent":"data","style":{"color":{"r":0.0,"g":0.0,"b":0.0,"a":0.0},"size":0.0,"lineType":"ltNone","lineWidth":0.0,"fillColor":{"r":0.0,"g":0.0,"b":0.0,"a":0.0},"marker":"mkCircle","errorBarKind":"ebLines","gradient":null,"font":{"family":"","size":0.0,"bold":false,"slant":"fsNormal","color":{"r":0.0,"g":0.0,"b":0.0,"a":0.0},"alignKind":"taLeft"}},"xScale":{"low":0.0,"high":1.0},"yScale":{"low":0.0,"high":1.0},"rotate":null,"scale":null,"origin":{"x":{"pos":0.0,"kind":"ukRelative"},"y":{"pos":6.810035284350354,"kind":"ukCentimeter","length":{"val":13.620070568700708,"unit":"ukCentimeter"}}},"width":{"val":0.2,"unit":"ukCentimeter"},"height":{"val":0.4853157882706125,"unit":"ukRelative"},"objects":[],"children":[],"wView":{"val":426.6043307086614,"unit":"ukPoint"},"hView":{"val":387.52854330708664,"unit":"ukPoint"},"wImg":{"val":640.0,"unit":"ukPoint"},"hImg":{"val":480.0,"unit":"ukPoint"},"backend":"bkCairo"},{"name":"data/layout_11","parent":"data","style":{"color":{"r":0.0,"g":0.0,"b":0.0,"a":0.0},"size":0.0,"lineType":"ltNone","lineWidth":0.0,"fillColor":{"r":0.0,"g":0.0,"b":0.0,"a":0.0},"marker":"mkCircle","errorBarKind":"ebLines","gradient":null,"font":{"family":"","size":0.0,"bold":false,"slant":"fsNormal","color":{"r":0.0,"g":0.0,"b":0.0,"a":0.0},"alignKind":"taLeft"}},"xScale":{"low":0.0,"high":1.0},"yScale":{"low":0.0,"high":1.0},"rotate":null,"scale":null,"origin":{"x":{"pos":0.2,"kind":"ukCentimeter","length":{"val":14.993427424934273,"unit":"ukCentimeter"}},"y":{"pos":6.810035284350354,"kind":"ukCentimeter","length":{"val":13.620070568700708,"unit":"ukCentimeter"}}},"width":{"val":0.3244405478777811,"unit":"ukRelative"},"height":{"val":0.4853157882706125,"unit":"ukRelative"},"objects":[{"name":"text","children":[],"style":{"color":{"r":0.0,"g":0.0,"b":0.0,"a":0.0},"size":0.0,"lineType":"ltNone","lineWidth":0.0,"fillColor":{"r":0.0,"g":0.0,"b":0.0,"a":0.0},"marker":"mkCircle","errorBarKind":"ebLines","gradient":null,"font":{"family":"","size":0.0,"bold":false,"slant":"fsNormal","color":{"r":0.0,"g":0.0,"b":0.0,"a":0.0},"alignKind":"taLeft"}},"rotateInView":null,"rotate":null,"kind":"goText","txtText":"4","txtFont":{"family":"sans-serif","size":62.5,"bold":false,"slant":"fsNormal","color":{"r":0.0,"g":0.0,"b":0.0,"a":1.0},"alignKind":"taCenter"},"txtPos":{"x":{"pos":0.5,"kind":"ukRelative"},"y":{"pos":0.5,"kind":"ukRelative"}},"txtAlign":"taCenter","txtRotate":0.0}],"children":[],"wView":{"val":426.6043307086614,"unit":"ukPoint"},"hView":{"val":387.52854330708664,"unit":"ukPoint"},"wImg":{"val":640.0,"unit":"ukPoint"},"hImg":{"val":480.0,"unit":"ukPoint"},"backend":"bkCairo"},{"name":"data/layout_12","parent":"data","style":{"color":{"r":0.0,"g":0.0,"b":0.0,"a":0.0},"size":0.0,"lineType":"ltNone","lineWidth":0.0,"fillColor":{"r":0.0,"g":0.0,"b":0.0,"a":0.0},"marker":"mkCircle","errorBarKind":"ebLines","gradient":null,"font":{"family":"","size":0.0,"bold":false,"slant":"fsNormal","color":{"r":0.0,"g":0.0,"b":0.0,"a":0.0},"alignKind":"taLeft"}},"xScale":{"low":0.0,"high":1.0},"yScale":{"low":0.0,"high":1.0},"rotate":null,"scale":null,"origin":{"x":{"pos":5.064475808311424,"kind":"ukCentimeter","length":{"val":14.993427424934273,"unit":"ukCentimeter"}},"y":{"pos":6.810035284350354,"kind":"ukCentimeter","length":{"val":13.620070568700708,"unit":"ukCentimeter"}}},"width":{"val":0.3244405478777811,"unit":"ukRelative"},"height":{"val":0.4853157882706125,"unit":"ukRelative"},"objects":[{"name":"text","children":[],"style":{"color":{"r":0.0,"g":0.0,"b":0.0,"a":0.0},"size":0.0,"lineType":"ltNone","lineWidth":0.0,"fillColor":{"r":0.0,"g":0.0,"b":0.0,"a":0.0},"marker":"mkCircle","errorBarKind":"ebLines","gradient":null,"font":{"family":"","size":0.0,"bold":false,"slant":"fsNormal","color":{"r":0.0,"g":0.0,"b":0.0,"a":0.0},"alignKind":"taLeft"}},"rotateInView":null,"rotate":null,"kind":"goText","txtText":"2","txtFont":{"family":"sans-serif","size":62.5,"bold":false,"slant":"fsNormal","color":{"r":0.0,"g":0.0,"b":0.0,"a":1.0},"alignKind":"taCenter"},"txtPos":{"x":{"pos":0.5,"kind":"ukRelative"},"y":{"pos":0.5,"kind":"ukRelative"}},"txtAlign":"taCenter","txtRotate":0.0}],"children":[],"wView":{"val":426.6043307086614,"unit":"ukPoint"},"hView":{"val":387.52854330708664,"unit":"ukPoint"},"wImg":{"val":640.0,"unit":"ukPoint"},"hImg":{"val":480.0,"unit":"ukPoint"},"backend":"bkCairo"},{"name":"data/layout_13","parent":"data","style":{"color":{"r":0.0,"g":0.0,"b":0.0,"a":0.0},"size":0.0,"lineType":"ltNone","lineWidth":0.0,"fillColor":{"r":0.0,"g":0.0,"b":0.0,"a":0.0},"marker":"mkCircle","errorBarKind":"ebLines","gradient":null,"font":{"family":"","size":0.0,"bold":false,"slant":"fsNormal","color":{"r":0.0,"g":0.0,"b":0.0,"a":0.0},"alignKind":"taLeft"}},"xScale":{"low":0.0,"high":1.0},"yScale":{"low":0.0,"high":1.0},"rotate":null,"scale":null,"origin":{"x":{"pos":9.928951616622847,"kind":"ukCentimeter","length":{"val":14.993427424934273,"unit":"ukCentimeter"}},"y":{"pos":6.810035284350354,"kind":"ukCentimeter","length":{"val":13.620070568700708,"unit":"ukCentimeter"}}},"width":{"val":0.3244405478777811,"unit":"ukRelative"},"height":{"val":0.4853157882706125,"unit":"ukRelative"},"objects":[{"name":"text","children":[],"style":{"color":{"r":0.0,"g":0.0,"b":0.0,"a":0.0},"size":0.0,"lineType":"ltNone","lineWidth":0.0,"fillColor":{"r":0.0,"g":0.0,"b":0.0,"a":0.0},"marker":"mkCircle","errorBarKind":"ebLines","gradient":null,"font":{"family":"","size":0.0,"bold":false,"slant":"fsNormal","color":{"r":0.0,"g":0.0,"b":0.0,"a":0.0},"alignKind":"taLeft"}},"rotateInView":null,"rotate":null,"kind":"goText","txtText":"3","txtFont":{"family":"sans-serif","size":62.5,"bold":false,"slant":"fsNormal","color":{"r":0.0,"g":0.0,"b":0.0,"a":1.0},"alignKind":"taCenter"},"txtPos":{"x":{"pos":0.5,"kind":"ukRelative"},"y":{"pos":0.5,"kind":"ukRelative"}},"txtAlign":"taCenter","txtRotate":0.0}],"children":[],"wView":{"val":426.6043307086614,"unit":"ukPoint"},"hView":{"val":387.52854330708664,"unit":"ukPoint"},"wImg":{"val":640.0,"unit":"ukPoint"},"hImg":{"val":480.0,"unit":"ukPoint"},"backend":"bkCairo"},{"name":"data/layout_14","parent":"data","style":{"color":{"r":0.0,"g":0.0,"b":0.0,"a":0.0},"size":0.0,"lineType":"ltNone","lineWidth":0.0,"fillColor":{"r":0.0,"g":0.0,"b":0.0,"a":0.0},"marker":"mkCircle","errorBarKind":"ebLines","gradient":null,"font":{"family":"","size":0.0,"bold":false,"slant":"fsNormal","color":{"r":0.0,"g":0.0,"b":0.0,"a":0.0},"alignKind":"taLeft"}},"xScale":{"low":0.0,"high":1.0},"yScale":{"low":0.0,"high":1.0},"rotate":null,"scale":null,"origin":{"x":{"pos":14.793427424934269,"kind":"ukCentimeter","length":{"val":14.993427424934273,"unit":"ukCentimeter"}},"y":{"pos":6.810035284350354,"kind":"ukCentimeter","length":{"val":13.620070568700708,"unit":"ukCentimeter"}}},"width":{"val":0.2,"unit":"ukCentimeter"},"height":{"val":0.4853157882706125,"unit":"ukRelative"},"objects":[],"children":[],"wView":{"val":426.6043307086614,"unit":"ukPoint"},"hView":{"val":387.52854330708664,"unit":"ukPoint"},"wImg":{"val":640.0,"unit":"ukPoint"},"hImg":{"val":480.0,"unit":"ukPoint"},"backend":"bkCairo"},{"name":"data/layout_15","parent":"data","style":{"color":{"r":0.0,"g":0.0,"b":0.0,"a":0.0},"size":0.0,"lineType":"ltNone","lineWidth":0.0,"fillColor":{"r":0.0,"g":0.0,"b":0.0,"a":0.0},"marker":"mkCircle","errorBarKind":"ebLines","gradient":null,"font":{"family":"","size":0.0,"bold":false,"slant":"fsNormal","color":{"r":0.0,"g":0.0,"b":0.0,"a":0.0},"alignKind":"taLeft"}},"xScale":{"low":0.0,"high":1.0},"yScale":{"low":0.0,"high":1.0},"rotate":null,"scale":null,"origin":{"x":{"pos":0.0,"kind":"ukRelative"},"y":{"pos":13.420070568700709,"kind":"ukCentimeter","length":{"val":13.620070568700708,"unit":"ukCentimeter"}}},"width":{"val":0.2,"unit":"ukCentimeter"},"height":{"val":0.2,"unit":"ukCentimeter"},"objects":[],"children":[],"wView":{"val":426.6043307086614,"unit":"ukPoint"},"hView":{"val":387.52854330708664,"unit":"ukPoint"},"wImg":{"val":640.0,"unit":"ukPoint"},"hImg":{"val":480.0,"unit":"ukPoint"},"backend":"bkCairo"},{"name":"data/layout_16","parent":"data","style":{"color":{"r":0.0,"g":0.0,"b":0.0,"a":0.0},"size":0.0,"lineType":"ltNone","lineWidth":0.0,"fillColor":{"r":0.0,"g":0.0,"b":0.0,"a":0.0},"marker":"mkCircle","errorBarKind":"ebLines","gradient":null,"font":{"family":"","size":0.0,"bold":false,"slant":"fsNormal","color":{"r":0.0,"g":0.0,"b":0.0,"a":0.0},"alignKind":"taLeft"}},"xScale":{"low":0.0,"high":1.0},"yScale":{"low":0.0,"high":1.0},"rotate":null,"scale":null,"origin":{"x":{"pos":0.2,"kind":"ukCentimeter","length":{"val":14.993427424934273,"unit":"ukCentimeter"}},"y":{"pos":13.420070568700709,"kind":"ukCentimeter","length":{"val":13.620070568700708,"unit":"ukCentimeter"}}},"width":{"val":0.3244405478777811,"unit":"ukRelative"},"height":{"val":0.2,"unit":"ukCentimeter"},"objects":[],"children":[],"wView":{"val":426.6043307086614,"unit":"ukPoint"},"hView":{"val":387.52854330708664,"unit":"ukPoint"},"wImg":{"val":640.0,"unit":"ukPoint"},"hImg":{"val":480.0,"unit":"ukPoint"},"backend":"bkCairo"},{"name":"data/layout_17","parent":"data","style":{"color":{"r":0.0,"g":0.0,"b":0.0,"a":0.0},"size":0.0,"lineType":"ltNone","lineWidth":0.0,"fillColor":{"r":0.0,"g":0.0,"b":0.0,"a":0.0},"marker":"mkCircle","errorBarKind":"ebLines","gradient":null,"font":{"family":"","size":0.0,"bold":false,"slant":"fsNormal","color":{"r":0.0,"g":0.0,"b":0.0,"a":0.0},"alignKind":"taLeft"}},"xScale":{"low":0.0,"high":1.0},"yScale":{"low":0.0,"high":1.0},"rotate":null,"scale":null,"origin":{"x":{"pos":5.064475808311424,"kind":"ukCentimeter","length":{"val":14.993427424934273,"unit":"ukCentimeter"}},"y":{"pos":13.420070568700709,"kind":"ukCentimeter","length":{"val":13.620070568700708,"unit":"ukCentimeter"}}},"width":{"val":0.3244405478777811,"unit":"ukRelative"},"height":{"val":0.2,"unit":"ukCentimeter"},"objects":[],"children":[],"wView":{"val":426.6043307086614,"unit":"ukPoint"},"hView":{"val":387.52854330708664,"unit":"ukPoint"},"wImg":{"val":640.0,"unit":"ukPoint"},"hImg":{"val":480.0,"unit":"ukPoint"},"backend":"bkCairo"},{"name":"data/layout_18","parent":"data","style":{"color":{"r":0.0,"g":0.0,"b":0.0,"a":0.0},"size":0.0,"lineType":"ltNone","lineWidth":0.0,"fillColor":{"r":0.0,"g":0.0,"b":0.0,"a":0.0},"marker":"mkCircle","errorBarKind":"ebLines","gradient":null,"font":{"family":"","size":0.0,"bold":false,"slant":"fsNormal","color":{"r":0.0,"g":0.0,"b":0.0,"a":0.0},"alignKind":"taLeft"}},"xScale":{"low":0.0,"high":1.0},"yScale":{"low":0.0,"high":1.0},"rotate":null,"scale":null,"origin":{"x":{"pos":9.928951616622847,"kind":"ukCentimeter","length":{"val":14.993427424934273,"unit":"ukCentimeter"}},"y":{"pos":13.420070568700709,"kind":"ukCentimeter","length":{"val":13.620070568700708,"unit":"ukCentimeter"}}},"width":{"val":0.3244405478777811,"unit":"ukRelative"},"height":{"val":0.2,"unit":"ukCentimeter"},"objects":[],"children":[],"wView":{"val":426.6043307086614,"unit":"ukPoint"},"hView":{"val":387.52854330708664,"unit":"ukPoint"},"wImg":{"val":640.0,"unit":"ukPoint"},"hImg":{"val":480.0,"unit":"ukPoint"},"backend":"bkCairo"},{"name":"data/layout_19","parent":"data","style":{"color":{"r":0.0,"g":0.0,"b":0.0,"a":0.0},"size":0.0,"lineType":"ltNone","lineWidth":0.0,"fillColor":{"r":0.0,"g":0.0,"b":0.0,"a":0.0},"marker":"mkCircle","errorBarKind":"ebLines","gradient":null,"font":{"family":"","size":0.0,"bold":false,"slant":"fsNormal","color":{"r":0.0,"g":0.0,"b":0.0,"a":0.0},"alignKind":"taLeft"}},"xScale":{"low":0.0,"high":1.0},"yScale":{"low":0.0,"high":1.0},"rotate":null,"scale":null,"origin":{"x":{"pos":14.793427424934269,"kind":"ukCentimeter","length":{"val":14.993427424934273,"unit":"ukCentimeter"}},"y":{"pos":13.420070568700709,"kind":"ukCentimeter","length":{"val":13.620070568700708,"unit":"ukCentimeter"}}},"width":{"val":0.2,"unit":"ukCentimeter"},"height":{"val":0.2,"unit":"ukCentimeter"},"objects":[],"children":[],"wView":{"val":426.6043307086614,"unit":"ukPoint"},"hView":{"val":387.52854330708664,"unit":"ukPoint"},"wImg":{"val":640.0,"unit":"ukPoint"},"hImg":{"val":480.0,"unit":"ukPoint"},"backend":"bkCairo"}],"wView":{"val":426.6043307086614,"unit":"ukPoint"},"hView":{"val":387.52854330708664,"unit":"ukPoint"},"wImg":{"val":640.0,"unit":"ukPoint"},"hImg":{"val":480.0,"unit":"ukPoint"},"backend":"bkCairo"}],"wView":{"val":640.0,"unit":"ukPoint"},"hView":{"val":480.0,"unit":"ukPoint"},"wImg":{"val":640.0,"unit":"ukPoint"},"hImg":{"val":480.0,"unit":"ukPoint"},"backend":"bkCairo"},{"name":"legend","parent":"root","style":{"color":{"r":0.0,"g":0.0,"b":0.0,"a":0.0},"size":0.0,"lineType":"ltNone","lineWidth":0.0,"fillColor":{"r":0.0,"g":0.0,"b":0.0,"a":0.0},"marker":"mkCircle","errorBarKind":"ebLines","gradient":null,"font":{"family":"","size":0.0,"bold":false,"slant":"fsNormal","color":{"r":0.0,"g":0.0,"b":0.0,"a":0.0},"alignKind":"taLeft"}},"xScale":{"low":0.0,"high":0.0},"yScale":{"low":0.0,"high":0.0},"rotate":null,"scale":null,"origin":{"x":{"pos":17.493427424934275,"kind":"ukCentimeter","length":{"val":22.493427424934275,"unit":"ukCentimeter"}},"y":{"pos":1.25,"kind":"ukCentimeter","length":{"val":16.870070568700708,"unit":"ukCentimeter"}}},"width":{"val":5.0,"unit":"ukCentimeter"},"height":{"val":0.8073511318897638,"unit":"ukRelative"},"objects":[],"children":[{"name":"legend/layout_0","parent":"legend","style":{"color":{"r":0.0,"g":0.0,"b":0.0,"a":0.0},"size":0.0,"lineType":"ltNone","lineWidth":0.0,"fillColor":{"r":0.0,"g":0.0,"b":0.0,"a":0.0},"marker":"mkCircle","errorBarKind":"ebLines","gradient":null,"font":{"family":"","size":0.0,"bold":false,"slant":"fsNormal","color":{"r":0.0,"g":0.0,"b":0.0,"a":0.0},"alignKind":"taLeft"}},"xScale":{"low":0.0,"high":0.0},"yScale":{"low":0.0,"high":0.0},"rotate":null,"scale":null,"origin":{"x":{"pos":0.0,"kind":"ukRelative"},"y":{"pos":0.0,"kind":"ukRelative"}},"width":{"val":1.0,"unit":"ukRelative"},"height":{"val":0.27055919172832077,"unit":"ukRelative"},"objects":[],"children":[],"wView":{"val":142.26377952755905,"unit":"ukPoint"},"hView":{"val":387.52854330708664,"unit":"ukPoint"},"wImg":{"val":640.0,"unit":"ukPoint"},"hImg":{"val":480.0,"unit":"ukPoint"},"backend":"bkCairo"},{"name":"legend","parent":"root","style":{"color":{"r":0.0,"g":0.0,"b":0.0,"a":0.0},"size":0.0,"lineType":"ltNone","lineWidth":0.0,"fillColor":{"r":0.0,"g":0.0,"b":0.0,"a":0.0},"marker":"mkCircle","errorBarKind":"ebLines","gradient":null,"font":{"family":"","size":0.0,"bold":false,"slant":"fsNormal","color":{"r":0.0,"g":0.0,"b":0.0,"a":0.0},"alignKind":"taLeft"}},"xScale":{"low":0.0,"high":0.0},"yScale":{"low":0.0,"high":0.0},"rotate":null,"scale":null,"origin":{"x":{"pos":0.0,"kind":"ukRelative"},"y":{"pos":0.27055919172832077,"kind":"ukRelative"}},"width":{"val":5.0,"unit":"ukCentimeter"},"height":{"val":6.25,"unit":"ukCentimeter"},"objects":[],"children":[{"name":"legend/layout_0","parent":"legend","style":{"color":{"r":0.0,"g":0.0,"b":0.0,"a":0.0},"size":0.0,"lineType":"ltNone","lineWidth":0.0,"fillColor":{"r":0.0,"g":0.0,"b":0.0,"a":0.0},"marker":"mkCircle","errorBarKind":"ebLines","gradient":null,"font":{"family":"","size":0.0,"bold":false,"slant":"fsNormal","color":{"r":0.0,"g":0.0,"b":0.0,"a":0.0},"alignKind":"taLeft"}},"xScale":{"low":0.0,"high":0.0},"yScale":{"low":0.0,"high":0.0},"rotate":null,"scale":null,"origin":{"x":{"pos":0.0,"kind":"ukRelative"},"y":{"pos":0.0,"kind":"ukRelative"}},"width":{"val":0.49999999999999994,"unit":"ukCentimeter"},"height":{"val":0.9999999999999999,"unit":"ukCentimeter"},"objects":[],"children":[],"wView":{"val":142.26377952755905,"unit":"ukPoint"},"hView":{"val":387.52854330708664,"unit":"ukPoint"},"wImg":{"val":640.0,"unit":"ukPoint"},"hImg":{"val":480.0,"unit":"ukPoint"},"backend":"bkCairo"},{"name":"legend/layout_1","parent":"legend","style":{"color":{"r":0.0,"g":0.0,"b":0.0,"a":0.0},"size":0.0,"lineType":"ltNone","lineWidth":0.0,"fillColor":{"r":0.0,"g":0.0,"b":0.0,"a":0.0},"marker":"mkCircle","errorBarKind":"ebLines","gradient":null,"font":{"family":"","size":0.0,"bold":false,"slant":"fsNormal","color":{"r":0.0,"g":0.0,"b":0.0,"a":0.0},"alignKind":"taLeft"}},"xScale":{"low":0.0,"high":0.0},"yScale":{"low":0.0,"high":0.0},"rotate":null,"scale":null,"origin":{"x":{"pos":0.49999999999999994,"kind":"ukCentimeter","length":{"val":5.0,"unit":"ukCentimeter"}},"y":{"pos":0.0,"kind":"ukRelative"}},"width":{"val":0.9,"unit":"ukRelative"},"height":{"val":0.9999999999999999,"unit":"ukCentimeter"},"objects":[{"name":"legendHeader","children":[],"style":{"color":{"r":0.0,"g":0.0,"b":0.0,"a":0.0},"size":0.0,"lineType":"ltNone","lineWidth":0.0,"fillColor":{"r":0.0,"g":0.0,"b":0.0,"a":0.0},"marker":"mkCircle","errorBarKind":"ebLines","gradient":null,"font":{"family":"","size":0.0,"bold":false,"slant":"fsNormal","color":{"r":0.0,"g":0.0,"b":0.0,"a":0.0},"alignKind":"taLeft"}},"rotateInView":null,"rotate":null,"kind":"goText","txtText":"n","txtFont":{"family":"sans-serif","size":12.0,"bold":true,"slant":"fsNormal","color":{"r":0.0,"g":0.0,"b":0.0,"a":1.0},"alignKind":"taLeft"},"txtPos":{"x":{"pos":0.0,"kind":"ukRelative"},"y":{"pos":0.5,"kind":"ukRelative"}},"txtAlign":"taLeft","txtRotate":0.0}],"children":[],"wView":{"val":142.26377952755905,"unit":"ukPoint"},"hView":{"val":387.52854330708664,"unit":"ukPoint"},"wImg":{"val":640.0,"unit":"ukPoint"},"hImg":{"val":480.0,"unit":"ukPoint"},"backend":"bkCairo"},{"name":"legend/layout_2","parent":"legend","style":{"color":{"r":0.0,"g":0.0,"b":0.0,"a":0.0},"size":0.0,"lineType":"ltNone","lineWidth":0.0,"fillColor":{"r":0.0,"g":0.0,"b":0.0,"a":0.0},"marker":"mkCircle","errorBarKind":"ebLines","gradient":null,"font":{"family":"","size":0.0,"bold":false,"slant":"fsNormal","color":{"r":0.0,"g":0.0,"b":0.0,"a":0.0},"alignKind":"taLeft"}},"xScale":{"low":0.0,"high":0.0},"yScale":{"low":0.0,"high":0.0},"rotate":null,"scale":null,"origin":{"x":{"pos":0.0,"kind":"ukRelative"},"y":{"pos":0.9999999999999999,"kind":"ukCentimeter","length":{"val":13.620070568700708,"unit":"ukCentimeter"}}},"width":{"val":0.49999999999999994,"unit":"ukCentimeter"},"height":{"val":5.25,"unit":"ukCentimeter"},"objects":[],"children":[],"wView":{"val":142.26377952755905,"unit":"ukPoint"},"hView":{"val":387.52854330708664,"unit":"ukPoint"},"wImg":{"val":640.0,"unit":"ukPoint"},"hImg":{"val":480.0,"unit":"ukPoint"},"backend":"bkCairo"},{"name":"legend/layout_3","parent":"legend","style":{"color":{"r":0.0,"g":0.0,"b":0.0,"a":0.0},"size":0.0,"lineType":"ltNone","lineWidth":0.0,"fillColor":{"r":0.0,"g":0.0,"b":0.0,"a":0.0},"marker":"mkCircle","errorBarKind":"ebLines","gradient":null,"font":{"family":"","size":0.0,"bold":false,"slant":"fsNormal","color":{"r":0.0,"g":0.0,"b":0.0,"a":0.0},"alignKind":"taLeft"}},"xScale":{"low":0.0,"high":0.0},"yScale":{"low":0.0,"high":0.0},"rotate":null,"scale":null,"origin":{"x":{"pos":0.49999999999999994,"kind":"ukCentimeter","length":{"val":5.0,"unit":"ukCentimeter"}},"y":{"pos":0.9999999999999999,"kind":"ukCentimeter","length":{"val":13.620070568700708,"unit":"ukCentimeter"}}},"width":{"val":0.9,"unit":"ukRelative"},"height":{"val":5.25,"unit":"ukCentimeter"},"objects":[],"children":[{"name":"legend/layout_3/layout_0","parent":"legend/layout_3","style":{"color":{"r":0.0,"g":0.0,"b":0.0,"a":0.0},"size":0.0,"lineType":"ltNone","lineWidth":0.0,"fillColor":{"r":0.0,"g":0.0,"b":0.0,"a":0.0},"marker":"mkCircle","errorBarKind":"ebLines","gradient":null,"font":{"family":"","size":0.0,"bold":false,"slant":"fsNormal","color":{"r":0.0,"g":0.0,"b":0.0,"a":0.0},"alignKind":"taLeft"}},"xScale":{"low":0.0,"high":0.0},"yScale":{"low":0.0,"high":0.0},"rotate":null,"scale":null,"origin":{"x":{"pos":0.0,"kind":"ukRelative"},"y":{"pos":0.0,"kind":"ukRelative"}},"width":{"val":0.9999999999999999,"unit":"ukCentimeter"},"height":{"val":1.05,"unit":"ukCentimeter"},"objects":[{"name":"markerRectangle","children":[],"style":{"color":{"r":1.0,"g":1.0,"b":1.0,"a":1.0},"size":0.0,"lineType":"ltSolid","lineWidth":1.0,"fillColor":{"r":0.9200000166893005,"g":0.9200000166893005,"b":0.9200000166893005,"a":1.0},"marker":"mkCircle","errorBarKind":"ebLines","gradient":null,"font":{"family":"","size":0.0,"bold":false,"slant":"fsNormal","color":{"r":0.0,"g":0.0,"b":0.0,"a":0.0},"alignKind":"taLeft"}},"rotateInView":null,"rotate":null,"kind":"goRect","reOrigin":{"x":{"pos":0.0,"kind":"ukRelative"},"y":{"pos":0.025,"kind":"ukCentimeter","length":{"val":1.05,"unit":"ukCentimeter"}}},"reWidth":{"val":1.0,"unit":"ukCentimeter"},"reHeight":{"val":1.0,"unit":"ukCentimeter"}},{"name":"markerPoint","children":[],"style":{"color":{"r":0.0,"g":0.0,"b":0.0,"a":0.0},"size":0.0,"lineType":"ltNone","lineWidth":0.0,"fillColor":{"r":0.0,"g":0.0,"b":0.0,"a":0.0},"marker":"mkCircle","errorBarKind":"ebLines","gradient":null,"font":{"family":"","size":0.0,"bold":false,"slant":"fsNormal","color":{"r":0.0,"g":0.0,"b":0.0,"a":0.0},"alignKind":"taLeft"}},"rotateInView":null,"rotate":null,"kind":"goPoint","ptMarker":"mkCircle","ptSize":3.0,"ptColor":{"r":1.0,"g":0.0,"b":0.0,"a":1.0},"ptPos":{"x":{"pos":0.5,"kind":"ukRelative"},"y":{"pos":0.5,"kind":"ukRelative"}}}],"children":[],"wView":{"val":128.03740157480314,"unit":"ukPoint"},"hView":{"val":149.37696850393698,"unit":"ukPoint"},"wImg":{"val":640.0,"unit":"ukPoint"},"hImg":{"val":480.0,"unit":"ukPoint"},"backend":"bkCairo"},{"name":"legend/layout_3/layout_1","parent":"legend/layout_3","style":{"color":{"r":0.0,"g":0.0,"b":0.0,"a":0.0},"size":0.0,"lineType":"ltNone","lineWidth":0.0,"fillColor":{"r":0.0,"g":0.0,"b":0.0,"a":0.0},"marker":"mkCircle","errorBarKind":"ebLines","gradient":null,"font":{"family":"","size":0.0,"bold":false,"slant":"fsNormal","color":{"r":0.0,"g":0.0,"b":0.0,"a":0.0},"alignKind":"taLeft"}},"xScale":{"low":0.0,"high":0.0},"yScale":{"low":0.0,"high":0.0},"rotate":null,"scale":null,"origin":{"x":{"pos":0.9999999999999999,"kind":"ukCentimeter","length":{"val":4.5,"unit":"ukCentimeter"}},"y":{"pos":0.0,"kind":"ukRelative"}},"width":{"val":0.3,"unit":"ukCentimeter"},"height":{"val":1.05,"unit":"ukCentimeter"},"objects":[],"children":[],"wView":{"val":128.03740157480314,"unit":"ukPoint"},"hView":{"val":149.37696850393698,"unit":"ukPoint"},"wImg":{"val":640.0,"unit":"ukPoint"},"hImg":{"val":480.0,"unit":"ukPoint"},"backend":"bkCairo"},{"name":"legend/layout_3/layout_2","parent":"legend/layout_3","style":{"color":{"r":0.0,"g":0.0,"b":0.0,"a":0.0},"size":0.0,"lineType":"ltNone","lineWidth":0.0,"fillColor":{"r":0.0,"g":0.0,"b":0.0,"a":0.0},"marker":"mkCircle","errorBarKind":"ebLines","gradient":null,"font":{"family":"","size":0.0,"bold":false,"slant":"fsNormal","color":{"r":0.0,"g":0.0,"b":0.0,"a":0.0},"alignKind":"taLeft"}},"xScale":{"low":0.0,"high":0.0},"yScale":{"low":0.0,"high":0.0},"rotate":null,"scale":null,"origin":{"x":{"pos":36.988582677165354,"kind":"ukPoint","length":{"val":128.03740157480314,"unit":"ukPoint"}},"y":{"pos":0.0,"kind":"ukRelative"}},"width":{"val":0.7111111111111111,"unit":"ukRelative"},"height":{"val":1.05,"unit":"ukCentimeter"},"objects":[{"name":"markerText","children":[],"style":{"color":{"r":0.0,"g":0.0,"b":0.0,"a":0.0},"size":0.0,"lineType":"ltNone","lineWidth":0.0,"fillColor":{"r":0.0,"g":0.0,"b":0.0,"a":0.0},"marker":"mkCircle","errorBarKind":"ebLines","gradient":null,"font":{"family":"","size":0.0,"bold":false,"slant":"fsNormal","color":{"r":0.0,"g":0.0,"b":0.0,"a":0.0},"alignKind":"taLeft"}},"rotateInView":null,"rotate":null,"kind":"goText","txtText":"0","txtFont":{"family":"sans-serif","size":12.0,"bold":false,"slant":"fsNormal","color":{"r":0.0,"g":0.0,"b":0.0,"a":1.0},"alignKind":"taLeft"},"txtPos":{"x":{"pos":0.0,"kind":"ukRelative"},"y":{"pos":0.5,"kind":"ukRelative"}},"txtAlign":"taLeft","txtRotate":0.0}],"children":[],"wView":{"val":128.03740157480314,"unit":"ukPoint"},"hView":{"val":149.37696850393698,"unit":"ukPoint"},"wImg":{"val":640.0,"unit":"ukPoint"},"hImg":{"val":480.0,"unit":"ukPoint"},"backend":"bkCairo"},{"name":"legend/layout_3/layout_3","parent":"legend/layout_3","style":{"color":{"r":0.0,"g":0.0,"b":0.0,"a":0.0},"size":0.0,"lineType":"ltNone","lineWidth":0.0,"fillColor":{"r":0.0,"g":0.0,"b":0.0,"a":0.0},"marker":"mkCircle","errorBarKind":"ebLines","gradient":null,"font":{"family":"","size":0.0,"bold":false,"slant":"fsNormal","color":{"r":0.0,"g":0.0,"b":0.0,"a":0.0},"alignKind":"taLeft"}},"xScale":{"low":0.0,"high":0.0},"yScale":{"low":0.0,"high":0.0},"rotate":null,"scale":null,"origin":{"x":{"pos":0.0,"kind":"ukRelative"},"y":{"pos":1.05,"kind":"ukCentimeter","length":{"val":5.25,"unit":"ukCentimeter"}}},"width":{"val":0.9999999999999999,"unit":"ukCentimeter"},"height":{"val":1.05,"unit":"ukCentimeter"},"objects":[{"name":"markerRectangle","children":[],"style":{"color":{"r":1.0,"g":1.0,"b":1.0,"a":1.0},"size":0.0,"lineType":"ltSolid","lineWidth":1.0,"fillColor":{"r":0.9200000166893005,"g":0.9200000166893005,"b":0.9200000166893005,"a":1.0},"marker":"mkCircle","errorBarKind":"ebLines","gradient":null,"font":{"family":"","size":0.0,"bold":false,"slant":"fsNormal","color":{"r":0.0,"g":0.0,"b":0.0,"a":0.0},"alignKind":"taLeft"}},"rotateInView":null,"rotate":null,"kind":"goRect","reOrigin":{"x":{"pos":0.0,"kind":"ukRelative"},"y":{"pos":0.025,"kind":"ukCentimeter","length":{"val":1.05,"unit":"ukCentimeter"}}},"reWidth":{"val":1.0,"unit":"ukCentimeter"},"reHeight":{"val":1.0,"unit":"ukCentimeter"}},{"name":"markerPoint","children":[],"style":{"color":{"r":0.0,"g":0.0,"b":0.0,"a":0.0},"size":0.0,"lineType":"ltNone","lineWidth":0.0,"fillColor":{"r":0.0,"g":0.0,"b":0.0,"a":0.0},"marker":"mkCircle","errorBarKind":"ebLines","gradient":null,"font":{"family":"","size":0.0,"bold":false,"slant":"fsNormal","color":{"r":0.0,"g":0.0,"b":0.0,"a":0.0},"alignKind":"taLeft"}},"rotateInView":null,"rotate":null,"kind":"goPoint","ptMarker":"mkCircle","ptSize":3.0,"ptColor":{"r":0.0,"g":1.0,"b":0.0,"a":1.0},"ptPos":{"x":{"pos":0.5,"kind":"ukRelative"},"y":{"pos":0.5,"kind":"ukRelative"}}}],"children":[],"wView":{"val":128.03740157480314,"unit":"ukPoint"},"hView":{"val":149.37696850393698,"unit":"ukPoint"},"wImg":{"val":640.0,"unit":"ukPoint"},"hImg":{"val":480.0,"unit":"ukPoint"},"backend":"bkCairo"},{"name":"legend/layout_3/layout_4","parent":"legend/layout_3","style":{"color":{"r":0.0,"g":0.0,"b":0.0,"a":0.0},"size":0.0,"lineType":"ltNone","lineWidth":0.0,"fillColor":{"r":0.0,"g":0.0,"b":0.0,"a":0.0},"marker":"mkCircle","errorBarKind":"ebLines","gradient":null,"font":{"family":"","size":0.0,"bold":false,"slant":"fsNormal","color":{"r":0.0,"g":0.0,"b":0.0,"a":0.0},"alignKind":"taLeft"}},"xScale":{"low":0.0,"high":0.0},"yScale":{"low":0.0,"high":0.0},"rotate":null,"scale":null,"origin":{"x":{"pos":0.9999999999999999,"kind":"ukCentimeter","length":{"val":4.5,"unit":"ukCentimeter"}},"y":{"pos":1.05,"kind":"ukCentimeter","length":{"val":5.25,"unit":"ukCentimeter"}}},"width":{"val":0.3,"unit":"ukCentimeter"},"height":{"val":1.05,"unit":"ukCentimeter"},"objects":[],"children":[],"wView":{"val":128.03740157480314,"unit":"ukPoint"},"hView":{"val":149.37696850393698,"unit":"ukPoint"},"wImg":{"val":640.0,"unit":"ukPoint"},"hImg":{"val":480.0,"unit":"ukPoint"},"backend":"bkCairo"},{"name":"legend/layout_3/layout_5","parent":"legend/layout_3","style":{"color":{"r":0.0,"g":0.0,"b":0.0,"a":0.0},"size":0.0,"lineType":"ltNone","lineWidth":0.0,"fillColor":{"r":0.0,"g":0.0,"b":0.0,"a":0.0},"marker":"mkCircle","errorBarKind":"ebLines","gradient":null,"font":{"family":"","size":0.0,"bold":false,"slant":"fsNormal","color":{"r":0.0,"g":0.0,"b":0.0,"a":0.0},"alignKind":"taLeft"}},"xScale":{"low":0.0,"high":0.0},"yScale":{"low":0.0,"high":0.0},"rotate":null,"scale":null,"origin":{"x":{"pos":36.988582677165354,"kind":"ukPoint","length":{"val":128.03740157480314,"unit":"ukPoint"}},"y":{"pos":1.05,"kind":"ukCentimeter","length":{"val":5.25,"unit":"ukCentimeter"}}},"width":{"val":0.7111111111111111,"unit":"ukRelative"},"height":{"val":1.05,"unit":"ukCentimeter"},"objects":[{"name":"markerText","children":[],"style":{"color":{"r":0.0,"g":0.0,"b":0.0,"a":0.0},"size":0.0,"lineType":"ltNone","lineWidth":0.0,"fillColor":{"r":0.0,"g":0.0,"b":0.0,"a":0.0},"marker":"mkCircle","errorBarKind":"ebLines","gradient":null,"font":{"family":"","size":0.0,"bold":false,"slant":"fsNormal","color":{"r":0.0,"g":0.0,"b":0.0,"a":0.0},"alignKind":"taLeft"}},"rotateInView":null,"rotate":null,"kind":"goText","txtText":"1","txtFont":{"family":"sans-serif","size":12.0,"bold":false,"slant":"fsNormal","color":{"r":0.0,"g":0.0,"b":0.0,"a":1.0},"alignKind":"taLeft"},"txtPos":{"x":{"pos":0.0,"kind":"ukRelative"},"y":{"pos":0.5,"kind":"ukRelative"}},"txtAlign":"taLeft","txtRotate":0.0}],"children":[],"wView":{"val":128.03740157480314,"unit":"ukPoint"},"hView":{"val":149.37696850393698,"unit":"ukPoint"},"wImg":{"val":640.0,"unit":"ukPoint"},"hImg":{"val":480.0,"unit":"ukPoint"},"backend":"bkCairo"},{"name":"legend/layout_3/layout_6","parent":"legend/layout_3","style":{"color":{"r":0.0,"g":0.0,"b":0.0,"a":0.0},"size":0.0,"lineType":"ltNone","lineWidth":0.0,"fillColor":{"r":0.0,"g":0.0,"b":0.0,"a":0.0},"marker":"mkCircle","errorBarKind":"ebLines","gradient":null,"font":{"family":"","size":0.0,"bold":false,"slant":"fsNormal","color":{"r":0.0,"g":0.0,"b":0.0,"a":0.0},"alignKind":"taLeft"}},"xScale":{"low":0.0,"high":0.0},"yScale":{"low":0.0,"high":0.0},"rotate":null,"scale":null,"origin":{"x":{"pos":0.0,"kind":"ukRelative"},"y":{"pos":59.7507874015748,"kind":"ukPoint","length":{"val":149.37696850393698,"unit":"ukPoint"}}},"width":{"val":0.9999999999999999,"unit":"ukCentimeter"},"height":{"val":1.05,"unit":"ukCentimeter"},"objects":[{"name":"markerRectangle","children":[],"style":{"color":{"r":1.0,"g":1.0,"b":1.0,"a":1.0},"size":0.0,"lineType":"ltSolid","lineWidth":1.0,"fillColor":{"r":0.9200000166893005,"g":0.9200000166893005,"b":0.9200000166893005,"a":1.0},"marker":"mkCircle","errorBarKind":"ebLines","gradient":null,"font":{"family":"","size":0.0,"bold":false,"slant":"fsNormal","color":{"r":0.0,"g":0.0,"b":0.0,"a":0.0},"alignKind":"taLeft"}},"rotateInView":null,"rotate":null,"kind":"goRect","reOrigin":{"x":{"pos":0.0,"kind":"ukRelative"},"y":{"pos":0.025,"kind":"ukCentimeter","length":{"val":1.05,"unit":"ukCentimeter"}}},"reWidth":{"val":1.0,"unit":"ukCentimeter"},"reHeight":{"val":1.0,"unit":"ukCentimeter"}},{"name":"markerPoint","children":[],"style":{"color":{"r":0.0,"g":0.0,"b":0.0,"a":0.0},"size":0.0,"lineType":"ltNone","lineWidth":0.0,"fillColor":{"r":0.0,"g":0.0,"b":0.0,"a":0.0},"marker":"mkCircle","errorBarKind":"ebLines","gradient":null,"font":{"family":"","size":0.0,"bold":false,"slant":"fsNormal","color":{"r":0.0,"g":0.0,"b":0.0,"a":0.0},"alignKind":"taLeft"}},"rotateInView":null,"rotate":null,"kind":"goPoint","ptMarker":"mkCircle","ptSize":3.0,"ptColor":{"r":0.0,"g":0.0,"b":1.0,"a":1.0},"ptPos":{"x":{"pos":0.5,"kind":"ukRelative"},"y":{"pos":0.5,"kind":"ukRelative"}}}],"children":[],"wView":{"val":128.03740157480314,"unit":"ukPoint"},"hView":{"val":149.37696850393698,"unit":"ukPoint"},"wImg":{"val":640.0,"unit":"ukPoint"},"hImg":{"val":480.0,"unit":"ukPoint"},"backend":"bkCairo"},{"name":"legend/layout_3/layout_7","parent":"legend/layout_3","style":{"color":{"r":0.0,"g":0.0,"b":0.0,"a":0.0},"size":0.0,"lineType":"ltNone","lineWidth":0.0,"fillColor":{"r":0.0,"g":0.0,"b":0.0,"a":0.0},"marker":"mkCircle","errorBarKind":"ebLines","gradient":null,"font":{"family":"","size":0.0,"bold":false,"slant":"fsNormal","color":{"r":0.0,"g":0.0,"b":0.0,"a":0.0},"alignKind":"taLeft"}},"xScale":{"low":0.0,"high":0.0},"yScale":{"low":0.0,"high":0.0},"rotate":null,"scale":null,"origin":{"x":{"pos":0.9999999999999999,"kind":"ukCentimeter","length":{"val":4.5,"unit":"ukCentimeter"}},"y":{"pos":59.7507874015748,"kind":"ukPoint","length":{"val":149.37696850393698,"unit":"ukPoint"}}},"width":{"val":0.3,"unit":"ukCentimeter"},"height":{"val":1.05,"unit":"ukCentimeter"},"objects":[],"children":[],"wView":{"val":128.03740157480314,"unit":"ukPoint"},"hView":{"val":149.37696850393698,"unit":"ukPoint"},"wImg":{"val":640.0,"unit":"ukPoint"},"hImg":{"val":480.0,"unit":"ukPoint"},"backend":"bkCairo"},{"name":"legend/layout_3/layout_8","parent":"legend/layout_3","style":{"color":{"r":0.0,"g":0.0,"b":0.0,"a":0.0},"size":0.0,"lineType":"ltNone","lineWidth":0.0,"fillColor":{"r":0.0,"g":0.0,"b":0.0,"a":0.0},"marker":"mkCircle","errorBarKind":"ebLines","gradient":null,"font":{"family":"","size":0.0,"bold":false,"slant":"fsNormal","color":{"r":0.0,"g":0.0,"b":0.0,"a":0.0},"alignKind":"taLeft"}},"xScale":{"low":0.0,"high":0.0},"yScale":{"low":0.0,"high":0.0},"rotate":null,"scale":null,"origin":{"x":{"pos":36.988582677165354,"kind":"ukPoint","length":{"val":128.03740157480314,"unit":"ukPoint"}},"y":{"pos":59.7507874015748,"kind":"ukPoint","length":{"val":149.37696850393698,"unit":"ukPoint"}}},"width":{"val":0.7111111111111111,"unit":"ukRelative"},"height":{"val":1.05,"unit":"ukCentimeter"},"objects":[{"name":"markerText","children":[],"style":{"color":{"r":0.0,"g":0.0,"b":0.0,"a":0.0},"size":0.0,"lineType":"ltNone","lineWidth":0.0,"fillColor":{"r":0.0,"g":0.0,"b":0.0,"a":0.0},"marker":"mkCircle","errorBarKind":"ebLines","gradient":null,"font":{"family":"","size":0.0,"bold":false,"slant":"fsNormal","color":{"r":0.0,"g":0.0,"b":0.0,"a":0.0},"alignKind":"taLeft"}},"rotateInView":null,"rotate":null,"kind":"goText","txtText":"2","txtFont":{"family":"sans-serif","size":12.0,"bold":false,"slant":"fsNormal","color":{"r":0.0,"g":0.0,"b":0.0,"a":1.0},"alignKind":"taLeft"},"txtPos":{"x":{"pos":0.0,"kind":"ukRelative"},"y":{"pos":0.5,"kind":"ukRelative"}},"txtAlign":"taLeft","txtRotate":0.0}],"children":[],"wView":{"val":128.03740157480314,"unit":"ukPoint"},"hView":{"val":149.37696850393698,"unit":"ukPoint"},"wImg":{"val":640.0,"unit":"ukPoint"},"hImg":{"val":480.0,"unit":"ukPoint"},"backend":"bkCairo"},{"name":"legend/layout_3/layout_9","parent":"legend/layout_3","style":{"color":{"r":0.0,"g":0.0,"b":0.0,"a":0.0},"size":0.0,"lineType":"ltNone","lineWidth":0.0,"fillColor":{"r":0.0,"g":0.0,"b":0.0,"a":0.0},"marker":"mkCircle","errorBarKind":"ebLines","gradient":null,"font":{"family":"","size":0.0,"bold":false,"slant":"fsNormal","color":{"r":0.0,"g":0.0,"b":0.0,"a":0.0},"alignKind":"taLeft"}},"xScale":{"low":0.0,"high":0.0},"yScale":{"low":0.0,"high":0.0},"rotate":null,"scale":null,"origin":{"x":{"pos":0.0,"kind":"ukRelative"},"y":{"pos":89.6261811023622,"kind":"ukPoint","length":{"val":149.37696850393698,"unit":"ukPoint"}}},"width":{"val":0.9999999999999999,"unit":"ukCentimeter"},"height":{"val":1.05,"unit":"ukCentimeter"},"objects":[{"name":"markerRectangle","children":[],"style":{"color":{"r":1.0,"g":1.0,"b":1.0,"a":1.0},"size":0.0,"lineType":"ltSolid","lineWidth":1.0,"fillColor":{"r":0.9200000166893005,"g":0.9200000166893005,"b":0.9200000166893005,"a":1.0},"marker":"mkCircle","errorBarKind":"ebLines","gradient":null,"font":{"family":"","size":0.0,"bold":false,"slant":"fsNormal","color":{"r":0.0,"g":0.0,"b":0.0,"a":0.0},"alignKind":"taLeft"}},"rotateInView":null,"rotate":null,"kind":"goRect","reOrigin":{"x":{"pos":0.0,"kind":"ukRelative"},"y":{"pos":0.025,"kind":"ukCentimeter","length":{"val":1.05,"unit":"ukCentimeter"}}},"reWidth":{"val":1.0,"unit":"ukCentimeter"},"reHeight":{"val":1.0,"unit":"ukCentimeter"}},{"name":"markerPoint","children":[],"style":{"color":{"r":0.0,"g":0.0,"b":0.0,"a":0.0},"size":0.0,"lineType":"ltNone","lineWidth":0.0,"fillColor":{"r":0.0,"g":0.0,"b":0.0,"a":0.0},"marker":"mkCircle","errorBarKind":"ebLines","gradient":null,"font":{"family":"","size":0.0,"bold":false,"slant":"fsNormal","color":{"r":0.0,"g":0.0,"b":0.0,"a":0.0},"alignKind":"taLeft"}},"rotateInView":null,"rotate":null,"kind":"goPoint","ptMarker":"mkCircle","ptSize":3.0,"ptColor":{"r":1.0,"g":1.0,"b":0.0,"a":1.0},"ptPos":{"x":{"pos":0.5,"kind":"ukRelative"},"y":{"pos":0.5,"kind":"ukRelative"}}}],"children":[],"wView":{"val":128.03740157480314,"unit":"ukPoint"},"hView":{"val":149.37696850393698,"unit":"ukPoint"},"wImg":{"val":640.0,"unit":"ukPoint"},"hImg":{"val":480.0,"unit":"ukPoint"},"backend":"bkCairo"},{"name":"legend/layout_3/layout_10","parent":"legend/layout_3","style":{"color":{"r":0.0,"g":0.0,"b":0.0,"a":0.0},"size":0.0,"lineType":"ltNone","lineWidth":0.0,"fillColor":{"r":0.0,"g":0.0,"b":0.0,"a":0.0},"marker":"mkCircle","errorBarKind":"ebLines","gradient":null,"font":{"family":"","size":0.0,"bold":false,"slant":"fsNormal","color":{"r":0.0,"g":0.0,"b":0.0,"a":0.0},"alignKind":"taLeft"}},"xScale":{"low":0.0,"high":0.0},"yScale":{"low":0.0,"high":0.0},"rotate":null,"scale":null,"origin":{"x":{"pos":0.9999999999999999,"kind":"ukCentimeter","length":{"val":4.5,"unit":"ukCentimeter"}},"y":{"pos":89.6261811023622,"kind":"ukPoint","length":{"val":149.37696850393698,"unit":"ukPoint"}}},"width":{"val":0.3,"unit":"ukCentimeter"},"height":{"val":1.05,"unit":"ukCentimeter"},"objects":[],"children":[],"wView":{"val":128.03740157480314,"unit":"ukPoint"},"hView":{"val":149.37696850393698,"unit":"ukPoint"},"wImg":{"val":640.0,"unit":"ukPoint"},"hImg":{"val":480.0,"unit":"ukPoint"},"backend":"bkCairo"},{"name":"legend/layout_3/layout_11","parent":"legend/layout_3","style":{"color":{"r":0.0,"g":0.0,"b":0.0,"a":0.0},"size":0.0,"lineType":"ltNone","lineWidth":0.0,"fillColor":{"r":0.0,"g":0.0,"b":0.0,"a":0.0},"marker":"mkCircle","errorBarKind":"ebLines","gradient":null,"font":{"family":"","size":0.0,"bold":false,"slant":"fsNormal","color":{"r":0.0,"g":0.0,"b":0.0,"a":0.0},"alignKind":"taLeft"}},"xScale":{"low":0.0,"high":0.0},"yScale":{"low":0.0,"high":0.0},"rotate":null,"scale":null,"origin":{"x":{"pos":36.988582677165354,"kind":"ukPoint","length":{"val":128.03740157480314,"unit":"ukPoint"}},"y":{"pos":89.6261811023622,"kind":"ukPoint","length":{"val":149.37696850393698,"unit":"ukPoint"}}},"width":{"val":0.7111111111111111,"unit":"ukRelative"},"height":{"val":1.05,"unit":"ukCentimeter"},"objects":[{"name":"markerText","children":[],"style":{"color":{"r":0.0,"g":0.0,"b":0.0,"a":0.0},"size":0.0,"lineType":"ltNone","lineWidth":0.0,"fillColor":{"r":0.0,"g":0.0,"b":0.0,"a":0.0},"marker":"mkCircle","errorBarKind":"ebLines","gradient":null,"font":{"family":"","size":0.0,"bold":false,"slant":"fsNormal","color":{"r":0.0,"g":0.0,"b":0.0,"a":0.0},"alignKind":"taLeft"}},"rotateInView":null,"rotate":null,"kind":"goText","txtText":"3","txtFont":{"family":"sans-serif","size":12.0,"bold":false,"slant":"fsNormal","color":{"r":0.0,"g":0.0,"b":0.0,"a":1.0},"alignKind":"taLeft"},"txtPos":{"x":{"pos":0.0,"kind":"ukRelative"},"y":{"pos":0.5,"kind":"ukRelative"}},"txtAlign":"taLeft","txtRotate":0.0}],"children":[],"wView":{"val":128.03740157480314,"unit":"ukPoint"},"hView":{"val":149.37696850393698,"unit":"ukPoint"},"wImg":{"val":640.0,"unit":"ukPoint"},"hImg":{"val":480.0,"unit":"ukPoint"},"backend":"bkCairo"},{"name":"legend/layout_3/layout_12","parent":"legend/layout_3","style":{"color":{"r":0.0,"g":0.0,"b":0.0,"a":0.0},"size":0.0,"lineType":"ltNone","lineWidth":0.0,"fillColor":{"r":0.0,"g":0.0,"b":0.0,"a":0.0},"marker":"mkCircle","errorBarKind":"ebLines","gradient":null,"font":{"family":"","size":0.0,"bold":false,"slant":"fsNormal","color":{"r":0.0,"g":0.0,"b":0.0,"a":0.0},"alignKind":"taLeft"}},"xScale":{"low":0.0,"high":0.0},"yScale":{"low":0.0,"high":0.0},"rotate":null,"scale":null,"origin":{"x":{"pos":0.0,"kind":"ukRelative"},"y":{"pos":119.5015748031496,"kind":"ukPoint","length":{"val":149.37696850393698,"unit":"ukPoint"}}},"width":{"val":0.9999999999999999,"unit":"ukCentimeter"},"height":{"val":1.05,"unit":"ukCentimeter"},"objects":[{"name":"markerRectangle","children":[],"style":{"color":{"r":1.0,"g":1.0,"b":1.0,"a":1.0},"size":0.0,"lineType":"ltSolid","lineWidth":1.0,"fillColor":{"r":0.9200000166893005,"g":0.9200000166893005,"b":0.9200000166893005,"a":1.0},"marker":"mkCircle","errorBarKind":"ebLines","gradient":null,"font":{"family":"","size":0.0,"bold":false,"slant":"fsNormal","color":{"r":0.0,"g":0.0,"b":0.0,"a":0.0},"alignKind":"taLeft"}},"rotateInView":null,"rotate":null,"kind":"goRect","reOrigin":{"x":{"pos":0.0,"kind":"ukRelative"},"y":{"pos":0.025,"kind":"ukCentimeter","length":{"val":1.05,"unit":"ukCentimeter"}}},"reWidth":{"val":1.0,"unit":"ukCentimeter"},"reHeight":{"val":1.0,"unit":"ukCentimeter"}},{"name":"markerPoint","children":[],"style":{"color":{"r":0.0,"g":0.0,"b":0.0,"a":0.0},"size":0.0,"lineType":"ltNone","lineWidth":0.0,"fillColor":{"r":0.0,"g":0.0,"b":0.0,"a":0.0},"marker":"mkCircle","errorBarKind":"ebLines","gradient":null,"font":{"family":"","size":0.0,"bold":false,"slant":"fsNormal","color":{"r":0.0,"g":0.0,"b":0.0,"a":0.0},"alignKind":"taLeft"}},"rotateInView":null,"rotate":null,"kind":"goPoint","ptMarker":"mkCircle","ptSize":3.0,"ptColor":{"r":1.0,"g":0.0,"b":1.0,"a":1.0},"ptPos":{"x":{"pos":0.5,"kind":"ukRelative"},"y":{"pos":0.5,"kind":"ukRelative"}}}],"children":[],"wView":{"val":128.03740157480314,"unit":"ukPoint"},"hView":{"val":149.37696850393698,"unit":"ukPoint"},"wImg":{"val":640.0,"unit":"ukPoint"},"hImg":{"val":480.0,"unit":"ukPoint"},"backend":"bkCairo"},{"name":"legend/layout_3/layout_13","parent":"legend/layout_3","style":{"color":{"r":0.0,"g":0.0,"b":0.0,"a":0.0},"size":0.0,"lineType":"ltNone","lineWidth":0.0,"fillColor":{"r":0.0,"g":0.0,"b":0.0,"a":0.0},"marker":"mkCircle","errorBarKind":"ebLines","gradient":null,"font":{"family":"","size":0.0,"bold":false,"slant":"fsNormal","color":{"r":0.0,"g":0.0,"b":0.0,"a":0.0},"alignKind":"taLeft"}},"xScale":{"low":0.0,"high":0.0},"yScale":{"low":0.0,"high":0.0},"rotate":null,"scale":null,"origin":{"x":{"pos":0.9999999999999999,"kind":"ukCentimeter","length":{"val":4.5,"unit":"ukCentimeter"}},"y":{"pos":119.5015748031496,"kind":"ukPoint","length":{"val":149.37696850393698,"unit":"ukPoint"}}},"width":{"val":0.3,"unit":"ukCentimeter"},"height":{"val":1.05,"unit":"ukCentimeter"},"objects":[],"children":[],"wView":{"val":128.03740157480314,"unit":"ukPoint"},"hView":{"val":149.37696850393698,"unit":"ukPoint"},"wImg":{"val":640.0,"unit":"ukPoint"},"hImg":{"val":480.0,"unit":"ukPoint"},"backend":"bkCairo"},{"name":"legend/layout_3/layout_14","parent":"legend/layout_3","style":{"color":{"r":0.0,"g":0.0,"b":0.0,"a":0.0},"size":0.0,"lineType":"ltNone","lineWidth":0.0,"fillColor":{"r":0.0,"g":0.0,"b":0.0,"a":0.0},"marker":"mkCircle","errorBarKind":"ebLines","gradient":null,"font":{"family":"","size":0.0,"bold":false,"slant":"fsNormal","color":{"r":0.0,"g":0.0,"b":0.0,"a":0.0},"alignKind":"taLeft"}},"xScale":{"low":0.0,"high":0.0},"yScale":{"low":0.0,"high":0.0},"rotate":null,"scale":null,"origin":{"x":{"pos":36.988582677165354,"kind":"ukPoint","length":{"val":128.03740157480314,"unit":"ukPoint"}},"y":{"pos":119.5015748031496,"kind":"ukPoint","length":{"val":149.37696850393698,"unit":"ukPoint"}}},"width":{"val":0.7111111111111111,"unit":"ukRelative"},"height":{"val":1.05,"unit":"ukCentimeter"},"objects":[{"name":"markerText","children":[],"style":{"color":{"r":0.0,"g":0.0,"b":0.0,"a":0.0},"size":0.0,"lineType":"ltNone","lineWidth":0.0,"fillColor":{"r":0.0,"g":0.0,"b":0.0,"a":0.0},"marker":"mkCircle","errorBarKind":"ebLines","gradient":null,"font":{"family":"","size":0.0,"bold":false,"slant":"fsNormal","color":{"r":0.0,"g":0.0,"b":0.0,"a":0.0},"alignKind":"taLeft"}},"rotateInView":null,"rotate":null,"kind":"goText","txtText":"4","txtFont":{"family":"sans-serif","size":12.0,"bold":false,"slant":"fsNormal","color":{"r":0.0,"g":0.0,"b":0.0,"a":1.0},"alignKind":"taLeft"},"txtPos":{"x":{"pos":0.0,"kind":"ukRelative"},"y":{"pos":0.5,"kind":"ukRelative"}},"txtAlign":"taLeft","txtRotate":0.0}],"children":[],"wView":{"val":128.03740157480314,"unit":"ukPoint"},"hView":{"val":149.37696850393698,"unit":"ukPoint"},"wImg":{"val":640.0,"unit":"ukPoint"},"hImg":{"val":480.0,"unit":"ukPoint"},"backend":"bkCairo"}],"wView":{"val":142.26377952755905,"unit":"ukPoint"},"hView":{"val":387.52854330708664,"unit":"ukPoint"},"wImg":{"val":640.0,"unit":"ukPoint"},"hImg":{"val":480.0,"unit":"ukPoint"},"backend":"bkCairo"}],"wView":{"val":640.0,"unit":"ukPoint"},"hView":{"val":480.0,"unit":"ukPoint"},"wImg":{"val":640.0,"unit":"ukPoint"},"hImg":{"val":480.0,"unit":"ukPoint"},"backend":"bkCairo"},{"name":"legend/layout_2","parent":"legend","style":{"color":{"r":0.0,"g":0.0,"b":0.0,"a":0.0},"size":0.0,"lineType":"ltNone","lineWidth":0.0,"fillColor":{"r":0.0,"g":0.0,"b":0.0,"a":0.0},"marker":"mkCircle","errorBarKind":"ebLines","gradient":null,"font":{"family":"","size":0.0,"bold":false,"slant":"fsNormal","color":{"r":0.0,"g":0.0,"b":0.0,"a":0.0},"alignKind":"taLeft"}},"xScale":{"low":0.0,"high":0.0},"yScale":{"low":0.0,"high":0.0},"rotate":null,"scale":null,"origin":{"x":{"pos":0.0,"kind":"ukRelative"},"y":{"pos":9.935035284350354,"kind":"ukCentimeter","length":{"val":13.620070568700708,"unit":"ukCentimeter"}}},"width":{"val":1.0,"unit":"ukRelative"},"height":{"val":0.27055919172832077,"unit":"ukRelative"},"objects":[],"children":[],"wView":{"val":142.26377952755905,"unit":"ukPoint"},"hView":{"val":387.52854330708664,"unit":"ukPoint"},"wImg":{"val":640.0,"unit":"ukPoint"},"hImg":{"val":480.0,"unit":"ukPoint"},"backend":"bkCairo"}],"wView":{"val":640.0,"unit":"ukPoint"},"hView":{"val":480.0,"unit":"ukPoint"},"wImg":{"val":640.0,"unit":"ukPoint"},"hImg":{"val":480.0,"unit":"ukPoint"},"backend":"bkCairo"},{"name":"bottomLeft","parent":"root","style":{"color":{"r":0.0,"g":0.0,"b":0.0,"a":0.0},"size":0.0,"lineType":"ltNone","lineWidth":0.0,"fillColor":{"r":0.0,"g":0.0,"b":0.0,"a":0.0},"marker":"mkCircle","errorBarKind":"ebLines","gradient":null,"font":{"family":"","size":0.0,"bold":false,"slant":"fsNormal","color":{"r":0.0,"g":0.0,"b":0.0,"a":0.0},"alignKind":"taLeft"}},"xScale":{"low":0.0,"high":0.0},"yScale":{"low":0.0,"high":0.0},"rotate":null,"scale":null,"origin":{"x":{"pos":0.0,"kind":"ukRelative"},"y":{"pos":14.87007056870071,"kind":"ukCentimeter","length":{"val":16.870070568700708,"unit":"ukCentimeter"}}},"width":{"val":2.5,"unit":"ukCentimeter"},"height":{"val":1.9999999999999998,"unit":"ukCentimeter"},"objects":[],"children":[],"wView":{"val":640.0,"unit":"ukPoint"},"hView":{"val":480.0,"unit":"ukPoint"},"wImg":{"val":640.0,"unit":"ukPoint"},"hImg":{"val":480.0,"unit":"ukPoint"},"backend":"bkCairo"},{"name":"xLabel","parent":"root","style":{"color":{"r":0.0,"g":0.0,"b":0.0,"a":0.0},"size":0.0,"lineType":"ltNone","lineWidth":0.0,"fillColor":{"r":0.0,"g":0.0,"b":0.0,"a":0.0},"marker":"mkCircle","errorBarKind":"ebLines","gradient":null,"font":{"family":"","size":0.0,"bold":false,"slant":"fsNormal","color":{"r":0.0,"g":0.0,"b":0.0,"a":0.0},"alignKind":"taLeft"}},"xScale":{"low":0.0,"high":0.0},"yScale":{"low":0.0,"high":0.0},"rotate":null,"scale":null,"origin":{"x":{"pos":2.5,"kind":"ukCentimeter","length":{"val":22.493427424934275,"unit":"ukCentimeter"}},"y":{"pos":14.87007056870071,"kind":"ukCentimeter","length":{"val":16.870070568700708,"unit":"ukCentimeter"}}},"width":{"val":0.6665692667322834,"unit":"ukRelative"},"height":{"val":1.9999999999999998,"unit":"ukCentimeter"},"objects":[],"children":[],"wView":{"val":640.0,"unit":"ukPoint"},"hView":{"val":480.0,"unit":"ukPoint"},"wImg":{"val":640.0,"unit":"ukPoint"},"hImg":{"val":480.0,"unit":"ukPoint"},"backend":"bkCairo"},{"name":"bottomRight","parent":"root","style":{"color":{"r":0.0,"g":0.0,"b":0.0,"a":0.0},"size":0.0,"lineType":"ltNone","lineWidth":0.0,"fillColor":{"r":0.0,"g":0.0,"b":0.0,"a":0.0},"marker":"mkCircle","errorBarKind":"ebLines","gradient":null,"font":{"family":"","size":0.0,"bold":false,"slant":"fsNormal","color":{"r":0.0,"g":0.0,"b":0.0,"a":0.0},"alignKind":"taLeft"}},"xScale":{"low":0.0,"high":0.0},"yScale":{"low":0.0,"high":0.0},"rotate":null,"scale":null,"origin":{"x":{"pos":17.493427424934275,"kind":"ukCentimeter","length":{"val":22.493427424934275,"unit":"ukCentimeter"}},"y":{"pos":14.87007056870071,"kind":"ukCentimeter","length":{"val":16.870070568700708,"unit":"ukCentimeter"}}},"width":{"val":5.0,"unit":"ukCentimeter"},"height":{"val":1.9999999999999998,"unit":"ukCentimeter"},"objects":[],"children":[],"wView":{"val":640.0,"unit":"ukPoint"},"hView":{"val":480.0,"unit":"ukPoint"},"wImg":{"val":640.0,"unit":"ukPoint"},"hImg":{"val":480.0,"unit":"ukPoint"},"backend":"bkCairo"}],"wView":{"val":640.0,"unit":"ukPoint"},"hView":{"val":480.0,"unit":"ukPoint"},"wImg":{"val":640.0,"unit":"ukPoint"},"hImg":{"val":480.0,"unit":"ukPoint"},"backend":"bkCairo"}