{"name":"root","parent":"","style":{"color":{"r":0.0,"g":0.0,"b":0.0,"a":0.0},"size":0.0,"lineType":"ltNone","lineWidth":0.0,"fillColor":{"r":0.0,"g":0.0,"b":0.0,"a":0.0},"marker":"mkCircle","errorBarKind":"ebLines","gradient":null,"font":{"family":"","size":0.0,"bold":false,"slant":"fsNormal","color":{"r":0.0,"g":0.0,"b":0.0,"a":0.0},"alignKind":"taLeft"}},"xScale":{"low":0.0,"high":1.2},"yScale":{"low":-0.05,"high":0.5},"rotate":null,"scale":null,"origin":{"x":{"pos":0.0,"kind":"ukRelative"},"y":{"pos":0.0,"kind":"ukRelative"}},"width":{"val":1.0,"unit":"ukRelative"},"height":{"val":1.0,"unit":"ukRelative"},"objects":[{"name":"","children":[],"style":{"color":{"r":0.0,"g":0.0,"b":0.0,"a":0.0},"size":0.0,"lineType":"ltNone","lineWidth":0.0,"fillColor":{"r":0.0,"g":0.0,"b":0.0,"a":0.0},"marker":"mkCircle","errorBarKind":"ebLines","gradient":null,"font":{"family":"","size":0.0,"bold":false,"slant":"fsNormal","color":{"r":0.0,"g":0.0,"b":0.0,"a":0.0},"alignKind":"taLeft"}},"rotateInView":null,"rotate":null,"kind":"goRect","reOrigin":{"x":{"pos":0.0,"kind":"ukRelative"},"y":{"pos":0.0,"kind":"ukRelative"}},"reWidth":{"val":1.0,"unit":"ukRelative"},"reHeight":{"val":1.0,"unit":"ukRelative"}}],"children":[{"name":"topLeft","parent":"root","style":{"color":{"r":0.0,"g":0.0,"b":0.0,"a":0.0},"size":0.0,"lineType":"ltNone","lineWidth":0.0,"fillColor":{"r":0.0,"g":0.0,"b":0.0,"a":0.0},"marker":"mkCircle","errorBarKind":"ebLines","gradient":null,"font":{"family":"","size":0.0,"bold":false,"slant":"fsNormal","color":{"r":0.0,"g":0.0,"b":0.0,"a":0.0},"alignKind":"taLeft"}},"xScale":{"low":0.0,"high":0.0},"yScale":{"low":0.0,"high":0.0},"rotate":null,"scale":null,"origin":{"x":{"pos":0.0,"kind":"ukRelative"},"y":{"pos":0.0,"kind":"ukRelative"}},"width":{"val":2.5,"unit":"ukCentimeter"},"height":{"val":0.9999999999999999,"unit":"ukCentimeter"},"objects":[],"children":[],"wView":{"val":640.0,"unit":"ukPoint"},"hView":{"val":480.0,"unit":"ukPoint"},"wImg":{"val":640.0,"unit":"ukPoint"},"hImg":{"val":480.0,"unit":"ukPoint"},"backend":"bkCairo"},{"name":"title","parent":"root","style":{"color":{"r":0.0,"g":0.0,"b":0.0,"a":0.0},"size":0.0,"lineType":"ltNone","lineWidth":0.0,"fillColor":{"r":0.0,"g":0.0,"b":0.0,"a":0.0},"marker":"mkCircle","errorBarKind":"ebLines","gradient":null,"font":{"family":"","size":0.0,"bold":false,"slant":"fsNormal","color":{"r":0.0,"g":0.0,"b":0.0,"a":0.0},"alignKind":"taLeft"}},"xScale":{"low":0.0,"high":0.0},"yScale":{"low":0.0,"high":0.0},"rotate":null,"scale":null,"origin":{"x":{"pos":2.5,"kind":"ukCentimeter","length":{"val":22.49342742493427,"unit":"ukCentimeter"}},"y":{"pos":0.0,"kind":"ukRelative"}},"width":{"val":0.8443989911417322,"unit":"ukRelative"},"height":{"val":0.9999999999999999,"unit":"ukCentimeter"},"objects":[],"children":[],"wView":{"val":640.0,"unit":"ukPoint"},"hView":{"val":480.0,"unit":"ukPoint"},"wImg":{"val":640.0,"unit":"ukPoint"},"hImg":{"val":480.0,"unit":"ukPoint"},"backend":"bkCairo"},{"name":"topRight","parent":"root","style":{"color":{"r":0.0,"g":0.0,"b":0.0,"a":0.0},"size":0.0,"lineType":"ltNone","lineWidth":0.0,"fillColor":{"r":0.0,"g":0.0,"b":0.0,"a":0.0},"marker":"mkCircle","errorBarKind":"ebLines","gradient":null,"font":{"family":"","size":0.0,"bold":false,"slant":"fsNormal","color":{"r":0.0,"g":0.0,"b":0.0,"a":0.0},"alignKind":"taLeft"}},"xScale":{"low":0.0,"high":0.0},"yScale":{"low":0.0,"high":0.0},"rotate":null,"scale":null,"origin":{"x":{"pos":21.49342742493427,"kind":"ukCentimeter","length":{"val":22.49342742493427,"unit":"ukCentimeter"}},"y":{"pos":0.0,"kind":"ukRelative"}},"width":{"val":0.9999999999999999,"unit":"ukCentimeter"},"height":{"val":0.9999999999999999,"unit":"ukCentimeter"},"objects":[],"children":[],"wView":{"val":640.0,"unit":"ukPoint"},"hView":{"val":480.0,"unit":"ukPoint"},"wImg":{"val":640.0,"unit":"ukPoint"},"hImg":{"val":480.0,"unit":"ukPoint"},"backend":"bkCairo"},{"name":"yLabel","parent":"root","style":{"color":{"r":0.0,"g":0.0,"b":0.0,"a":0.0},"size":0.0,"lineType":"ltNone","lineWidth":0.0,"fillColor":{"r":0.0,"g":0.0,"b":0.0,"a":0.0},"marker":"mkCircle","errorBarKind":"ebLines","gradient":null,"font":{"family":"","size":0.0,"bold":false,"slant":"fsNormal","color":{"r":0.0,"g":0.0,"b":0.0,"a":0.0},"alignKind":"taLeft"}},"xScale":{"low":0.0,"high":0.0},"yScale":{"low":0.0,"high":0.0},"rotate":null,"scale":null,"origin":{"x":{"pos":0.0,"kind":"ukRelative"},"y":{"pos":0.9999999999999999,"kind":"ukCentimeter","length":{"val":16.87007056870071,"unit":"ukCentimeter"}}},"width":{"val":2.5,"unit":"ukCentimeter"},"height":{"val":0.8221702755905512,"unit":"ukRelative"},"objects":[],"children":[],"wView":{"val":640.0,"unit":"ukPoint"},"hView":{"val":480.0,"unit":"ukPoint"},"wImg":{"val":640.0,"unit":"ukPoint"},"hImg":{"val":480.0,"unit":"ukPoint"},"backend":"bkCairo"},{"name":"plot","parent":"root","style":{"color":{"r":0.0,"g":0.0,"b":0.0,"a":0.0},"size":0.0,"lineType":"ltNone","lineWidth":0.0,"fillColor":{"r":0.0,"g":0.0,"b":0.0,"a":0.0},"marker":"mkCircle","errorBarKind":"ebLines","gradient":null,"font":{"family":"","size":0.0,"bold":false,"slant":"fsNormal","color":{"r":0.0,"g":0.0,"b":0.0,"a":0.0},"alignKind":"taLeft"}},"xScale":{"low":0.0,"high":1.2},"yScale":{"low":-0.05,"high":0.5},"rotate":null,"scale":null,"origin":{"x":{"pos":2.5,"kind":"ukCentimeter","length":{"val":22.49342742493427,"unit":"ukCentimeter"}},"y":{"pos":0.9999999999999999,"kind":"ukCentimeter","length":{"val":16.87007056870071,"unit":"ukCentimeter"}}},"width":{"val":0.8443989911417322,"unit":"ukRelative"},"height":{"val":0.8221702755905512,"unit":"ukRelative"},"objects":[{"name":"","children":[],"style":{"color":{"r":0.0,"g":0.0,"b":0.0,"a":0.0},"size":0.0,"lineType":"ltNone","lineWidth":0.0,"fillColor":{"r":0.9200000166893005,"g":0.9200000166893005,"b":0.9200000166893005,"a":1.0},"marker":"mkCircle","errorBarKind":"ebLines","gradient":null,"font":{"family":"","size":0.0,"bold":false,"slant":"fsNormal","color":{"r":0.0,"g":0.0,"b":0.0,"a":0.0},"alignKind":"taLeft"}},"rotateInView":null,"rotate":null,"kind":"goRect","reOrigin":{"x":{"pos":0.0,"kind":"ukRelative"},"y":{"pos":0.0,"kind":"ukRelative"}},"reWidth":{"val":1.0,"unit":"ukRelative"},"reHeight":{"val":1.0,"unit":"ukRelative"}},{"name":"tick","children":[],"style":{"color":{"r":0.0,"g":0.0,"b":0.0,"a":1.0},"size":5.0,"lineType":"ltSolid","lineWidth":1.0,"fillColor":{"r":0.0,"g":0.0,"b":0.0,"a":0.0},"marker":"mkCircle","errorBarKind":"ebLines","gradient":null,"font":{"family":"","size":0.0,"bold":false,"slant":"fsNormal","color":{"r":0.0,"g":0.0,"b":0.0,"a":0.0},"alignKind":"taLeft"}},"rotateInView":null,"rotate":null,"kind":"goTick","tkMajor":true,"tkPos":{"x":{"pos":0.0,"kind":"ukData","scale":{"low":0.0,"high":1.2},"axis":"akX"},"y":{"pos":1.0,"kind":"ukRelative"}},"tkAxis":"akX","tkKind":"tkOneSide","tkSecondary":false},{"name":"tick","children":[],"style":{"color":{"r":0.0,"g":0.0,"b":0.0,"a":1.0},"size":5.0,"lineType":"ltSolid","lineWidth":1.0,"fillColor":{"r":0.0,"g":0.0,"b":0.0,"a":0.0},"marker":"mkCircle","errorBarKind":"ebLines","gradient":null,"font":{"family":"","size":0.0,"bold":false,"slant":"fsNormal","color":{"r":0.0,"g":0.0,"b":0.0,"a":0.0},"alignKind":"taLeft"}},"rotateInView":null,"rotate":null,"kind":"goTick","tkMajor":true,"tkPos":{"x":{"pos":0.2,"kind":"ukData","scale":{"low":0.0,"high":1.2},"axis":"akX"},"y":{"pos":1.0,"kind":"ukRelative"}},"tkAxis":"akX","tkKind":"tkOneSide","tkSecondary":false},{"name":"tick","children":[],"style":{"color":{"r":0.0,"g":0.0,"b":0.0,"a":1.0},"size":5.0,"lineType":"ltSolid","lineWidth":1.0,"fillColor":{"r":0.0,"g":0.0,"b":0.0,"a":0.0},"marker":"mkCircle","errorBarKind":"ebLines","gradient":null,"font":{"family":"","size":0.0,"bold":false,"slant":"fsNormal","color":{"r":0.0,"g":0.0,"b":0.0,"a":0.0},"alignKind":"taLeft"}},"rotateInView":null,"rotate":null,"kind":"goTick","tkMajor":true,"tkPos":{"x":{"pos":0.4,"kind":"ukData","scale":{"low":0.0,"high":1.2},"axis":"akX"},"y":{"pos":1.0,"kind":"ukRelative"}},"tkAxis":"akX","tkKind":"tkOneSide","tkSecondary":false},{"name":"tick","children":[],"style":{"color":{"r":0.0,"g":0.0,"b":0.0,"a":1.0},"size":5.0,"lineType":"ltSolid","lineWidth":1.0,"fillColor":{"r":0.0,"g":0.0,"b":0.0,"a":0.0},"marker":"mkCircle","errorBarKind":"ebLines","gradient":null,"font":{"family":"","size":0.0,"bold":false,"slant":"fsNormal","color":{"r":0.0,"g":0.0,"b":0.0,"a":0.0},"alignKind":"taLeft"}},"rotateInView":null,"rotate":null,"kind":"goTick","tkMajor":true,"tkPos":{"x":{"pos":0.6000000000000001,"kind":"ukData","scale":{"low":0.0,"high":1.2},"axis":"akX"},"y":{"pos":1.0,"kind":"ukRelative"}},"tkAxis":"akX","tkKind":"tkOneSide","tkSecondary":false},{"name":"tick","children":[],"style":{"color":{"r":0.0,"g":0.0,"b":0.0,"a":1.0},"size":5.0,"lineType":"ltSolid","lineWidth":1.0,"fillColor":{"r":0.0,"g":0.0,"b":0.0,"a":0.0},"marker":"mkCircle","errorBarKind":"ebLines","gradient":null,"font":{"family":"","size":0.0,"bold":false,"slant":"fsNormal","color":{"r":0.0,"g":0.0,"b":0.0,"a":0.0},"alignKind":"taLeft"}},"rotateInView":null,"rotate":null,"kind":"goTick","tkMajor":true,"tkPos":{"x":{"pos":0.8,"kind":"ukData","scale":{"low":0.0,"high":1.2},"axis":"akX"},"y":{"pos":1.0,"kind":"ukRelative"}},"tkAxis":"akX","tkKind":"tkOneSide","tkSecondary":false},{"name":"tick","children":[],"style":{"color":{"r":0.0,"g":0.0,"b":0.0,"a":1.0},"size":5.0,"lineType":"ltSolid","lineWidth":1.0,"fillColor":{"r":0.0,"g":0.0,"b":0.0,"a":0.0},"marker":"mkCircle","errorBarKind":"ebLines","gradient":null,"font":{"family":"","size":0.0,"bold":false,"slant":"fsNormal","color":{"r":0.0,"g":0.0,"b":0.0,"a":0.0},"alignKind":"taLeft"}},"rotateInView":null,"rotate":null,"kind":"goTick","tkMajor":true,"tkPos":{"x":{"pos":1.0,"kind":"ukData","scale":{"low":0.0,"high":1.2},"axis":"akX"},"y":{"pos":1.0,"kind":"ukRelative"}},"tkAxis":"akX","tkKind":"tkOneSide","tkSecondary":false},{"name":"tick","children":[],"style":{"color":{"r":0.0,"g":0.0,"b":0.0,"a":1.0},"size":5.0,"lineType":"ltSolid","lineWidth":1.0,"fillColor":{"r":0.0,"g":0.0,"b":0.0,"a":0.0},"marker":"mkCircle","errorBarKind":"ebLines","gradient":null,"font":{"family":"","size":0.0,"bold":false,"slant":"fsNormal","color":{"r":0.0,"g":0.0,"b":0.0,"a":0.0},"alignKind":"taLeft"}},"rotateInView":null,"rotate":null,"kind":"goTick","tkMajor":true,"tkPos":{"x":{"pos":1.2,"kind":"ukData","scale":{"low":0.0,"high":1.2},"axis":"akX"},"y":{"pos":1.0,"kind":"ukRelative"}},"tkAxis":"akX","tkKind":"tkOneSide","tkSecondary":false},{"name":"xtickLabel","children":[],"style":{"color":{"r":0.0,"g":0.0,"b":0.0,"a":0.0},"size":0.0,"lineType":"ltNone","lineWidth":0.0,"fillColor":{"r":0.0,"g":0.0,"b":0.0,"a":0.0},"marker":"mkCircle","errorBarKind":"ebLines","gradient":null,"font":{"family":"","size":0.0,"bold":false,"slant":"fsNormal","color":{"r":0.0,"g":0.0,"b":0.0,"a":0.0},"alignKind":"taLeft"}},"rotateInView":null,"rotate":null,"kind":"goTickLabel","txtText":"0","txtFont":{"family":"sans-serif","size":8.0,"bold":false,"slant":"fsNormal","color":{"r":0.0,"g":0.0,"b":0.0,"a":1.0},"alignKind":"taLeft"},"txtPos":{"x":{"pos":0.0,"kind":"ukData","scale":{"low":0.0,"high":1.2},"axis":"akX"},"y":{"pos":1.036048843264598,"kind":"ukRelative"}},"txtAlign":"taCenter","txtRotate":0.0},{"name":"xtickLabel","children":[],"style":{"color":{"r":0.0,"g":0.0,"b":0.0,"a":0.0},"size":0.0,"lineType":"ltNone","lineWidth":0.0,"fillColor":{"r":0.0,"g":0.0,"b":0.0,"a":0.0},"marker":"mkCircle","errorBarKind":"ebLines","gradient":null,"font":{"family":"","size":0.0,"bold":false,"slant":"fsNormal","color":{"r":0.0,"g":0.0,"b":0.0,"a":0.0},"alignKind":"taLeft"}},"rotateInView":null,"rotate":null,"kind":"goTickLabel","txtText":"0.2","txtFont":{"family":"sans-serif","size":8.0,"bold":false,"slant":"fsNormal","color":{"r":0.0,"g":0.0,"b":0.0,"a":1.0},"alignKind":"taLeft"},"txtPos":{"x":{"pos":0.2,"kind":"ukData","scale":{"low":0.0,"high":1.2},"axis":"akX"},"y":{"pos":1.036048843264598,"kind":"ukRelative"}},"txtAlign":"taCenter","txtRotate":0.0},{"name":"xtickLabel","children":[],"style":{"color":{"r":0.0,"g":0.0,"b":0.0,"a":0.0},"size":0.0,"lineType":"ltNone","lineWidth":0.0,"fillColor":{"r":0.0,"g":0.0,"b":0.0,"a":0.0},"marker":"mkCircle","errorBarKind":"ebLines","gradient":null,"font":{"family":"","size":0.0,"bold":false,"slant":"fsNormal","color":{"r":0.0,"g":0.0,"b":0.0,"a":0.0},"alignKind":"taLeft"}},"rotateInView":null,"rotate":null,"kind":"goTickLabel","txtText":"0.4","txtFont":{"family":"sans-serif","size":8.0,"bold":false,"slant":"fsNormal","color":{"r":0.0,"g":0.0,"b":0.0,"a":1.0},"alignKind":"taLeft"},"txtPos":{"x":{"pos":0.4,"kind":"ukData","scale":{"low":0.0,"high":1.2},"axis":"akX"},"y":{"pos":1.036048843264598,"kind":"ukRelative"}},"txtAlign":"taCenter","txtRotate":0.0},{"name":"xtickLabel","children":[],"style":{"color":{"r":0.0,"g":0.0,"b":0.0,"a":0.0},"size":0.0,"lineType":"ltNone","lineWidth":0.0,"fillColor":{"r":0.0,"g":0.0,"b":0.0,"a":0.0},"marker":"mkCircle","errorBarKind":"ebLines","gradient":null,"font":{"family":"","size":0.0,"bold":false,"slant":"fsNormal","color":{"r":0.0,"g":0.0,"b":0.0,"a":0.0},"alignKind":"taLeft"}},"rotateInView":null,"rotate":null,"kind":"goTickLabel","txtText":"0.6","txtFont":{"family":"sans-serif","size":8.0,"bold":false,"slant":"fsNormal","color":{"r":0.0,"g":0.0,"b":0.0,"a":1.0},"alignKind":"taLeft"},"txtPos":{"x":{"pos":0.6000000000000001,"kind":"ukData","scale":{"low":0.0,"high":1.2},"axis":"akX"},"y":{"pos":1.036048843264598,"kind":"ukRelative"}},"txtAlign":"taCenter","txtRotate":0.0},{"name":"xtickLabel","children":[],"style":{"color":{"r":0.0,"g":0.0,"b":0.0,"a":0.0},"size":0.0,"lineType":"ltNone","lineWidth":0.0,"fillColor":{"r":0.0,"g":0.0,"b":0.0,"a":0.0},"marker":"mkCircle","errorBarKind":"ebLines","gradient":null,"font":{"family":"","size":0.0,"bold":false,"slant":"fsNormal","color":{"r":0.0,"g":0.0,"b":0.0,"a":0.0},"alignKind":"taLeft"}},"rotateInView":null,"rotate":null,"kind":"goTickLabel","txtText":"0.8","txtFont":{"family":"sans-serif","size":8.0,"bold":false,"slant":"fsNormal","color":{"r":0.0,"g":0.0,"b":0.0,"a":1.0},"alignKind":"taLeft"},"txtPos":{"x":{"pos":0.8,"kind":"ukData","scale":{"low":0.0,"high":1.2},"axis":"akX"},"y":{"pos":1.036048843264598,"kind":"ukRelative"}},"txtAlign":"taCenter","txtRotate":0.0},{"name":"xtickLabel","children":[],"style":{"color":{"r":0.0,"g":0.0,"b":0.0,"a":0.0},"size":0.0,"lineType":"ltNone","lineWidth":0.0,"fillColor":{"r":0.0,"g":0.0,"b":0.0,"a":0.0},"marker":"mkCircle","errorBarKind":"ebLines","gradient":null,"font":{"family":"","size":0.0,"bold":false,"slant":"fsNormal","color":{"r":0.0,"g":0.0,"b":0.0,"a":0.0},"alignKind":"taLeft"}},"rotateInView":null,"rotate":null,"kind":"goTickLabel","txtText":"1","txtFont":{"family":"sans-serif","size":8.0,"bold":false,"slant":"fsNormal","color":{"r":0.0,"g":0.0,"b":0.0,"a":1.0},"alignKind":"taLeft"},"txtPos":{"x":{"pos":1.0,"kind":"ukData","scale":{"low":0.0,"high":1.2},"axis":"akX"},"y":{"pos":1.036048843264598,"kind":"ukRelative"}},"txtAlign":"taCenter","txtRotate":0.0},{"name":"xtickLabel","children":[],"style":{"color":{"r":0.0,"g":0.0,"b":0.0,"a":0.0},"size":0.0,"lineType":"ltNone","lineWidth":0.0,"fillColor":{"r":0.0,"g":0.0,"b":0.0,"a":0.0},"marker":"mkCircle","errorBarKind":"ebLines","gradient":null,"font":{"family":"","size":0.0,"bold":false,"slant":"fsNormal","color":{"r":0.0,"g":0.0,"b":0.0,"a":0.0},"alignKind":"taLeft"}},"rotateInView":null,"rotate":null,"kind":"goTickLabel","txtText":"1.2","txtFont":{"family":"sans-serif","size":8.0,"bold":false,"slant":"fsNormal","color":{"r":0.0,"g":0.0,"b":0.0,"a":1.0},"alignKind":"taLeft"},"txtPos":{"x":{"pos":1.2,"kind":"ukData","scale":{"low":0.0,"high":1.2},"axis":"akX"},"y":{"pos":1.036048843264598,"kind":"ukRelative"}},"txtAlign":"taCenter","txtRotate":0.0},{"name":"tick","children":[],"style":{"color":{"r":0.0,"g":0.0,"b":0.0,"a":1.0},"size":5.0,"lineType":"ltSolid","lineWidth":1.0,"fillColor":{"r":0.0,"g":0.0,"b":0.0,"a":0.0},"marker":"mkCircle","errorBarKind":"ebLines","gradient":null,"font":{"family":"","size":0.0,"bold":false,"slant":"fsNormal","color":{"r":0.0,"g":0.0,"b":0.0,"a":0.0},"alignKind":"taLeft"}},"rotateInView":null,"rotate":null,"kind":"goTick","tkMajor":true,"tkPos":{"x":{"pos":0.0,"kind":"ukRelative"},"y":{"pos":-1.387778780781446e-17,"kind":"ukData","scale":{"low":-0.05,"high":0.5},"axis":"akY"}},"tkAxis":"akY","tkKind":"tkOneSide","tkSecondary":false},{"name":"tick","children":[],"style":{"color":{"r":0.0,"g":0.0,"b":0.0,"a":1.0},"size":5.0,"lineType":"ltSolid","lineWidth":1.0,"fillColor":{"r":0.0,"g":0.0,"b":0.0,"a":0.0},"marker":"mkCircle","errorBarKind":"ebLines","gradient":null,"font":{"family":"","size":0.0,"bold":false,"slant":"fsNormal","color":{"r":0.0,"g":0.0,"b":0.0,"a":0.0},"alignKind":"taLeft"}},"rotateInView":null,"rotate":null,"kind":"goTick","tkMajor":true,"tkPos":{"x":{"pos":0.0,"kind":"ukRelative"},"y":{"pos":0.09999999999999998,"kind":"ukData","scale":{"low":-0.05,"high":0.5},"axis":"akY"}},"tkAxis":"akY","tkKind":"tkOneSide","tkSecondary":false},{"name":"tick","children":[],"style":{"color":{"r":0.0,"g":0.0,"b":0.0,"a":1.0},"size":5.0,"lineType":"ltSolid","lineWidth":1.0,"fillColor":{"r":0.0,"g":0.0,"b":0.0,"a":0.0},"marker":"mkCircle","errorBarKind":"ebLines","gradient":null,"font":{"family":"","size":0.0,"bold":false,"slant":"fsNormal","color":{"r":0.0,"g":0.0,"b":0.0,"a":0.0},"alignKind":"taLeft"}},"rotateInView":null,"rotate":null,"kind":"goTick","tkMajor":true,"tkPos":{"x":{"pos":0.0,"kind":"ukRelative"},"y":{"pos":0.2,"kind":"ukData","scale":{"low":-0.05,"high":0.5},"axis":"akY"}},"tkAxis":"akY","tkKind":"tkOneSide","tkSecondary":false},{"name":"tick","children":[],"style":{"color":{"r":0.0,"g":0.0,"b":0.0,"a":1.0},"size":5.0,"lineType":"ltSolid","lineWidth":1.0,"fillColor":{"r":0.0,"g":0.0,"b":0.0,"a":0.0},"marker":"mkCircle","errorBarKind":"ebLines","gradient":null,"font":{"family":"","size":0.0,"bold":false,"slant":"fsNormal","color":{"r":0.0,"g":0.0,"b":0.0,"a":0.0},"alignKind":"taLeft"}},"rotateInView":null,"rotate":null,"kind":"goTick","tkMajor":true,"tkPos":{"x":{"pos":0.0,"kind":"ukRelative"},"y":{"pos":0.2999999999999999,"kind":"ukData","scale":{"low":-0.05,"high":0.5},"axis":"akY"}},"tkAxis":"akY","tkKind":"tkOneSide","tkSecondary":false},{"name":"tick","children":[],"style":{"color":{"r":0.0,"g":0.0,"b":0.0,"a":1.0},"size":5.0,"lineType":"ltSolid","lineWidth":1.0,"fillColor":{"r":0.0,"g":0.0,"b":0.0,"a":0.0},"marker":"mkCircle","errorBarKind":"ebLines","gradient":null,"font":{"family":"","size":0.0,"bold":false,"slant":"fsNormal","color":{"r":0.0,"g":0.0,"b":0.0,"a":0.0},"alignKind":"taLeft"}},"rotateInView":null,"rotate":null,"kind":"goTick","tkMajor":true,"tkPos":{"x":{"pos":0.0,"kind":"ukRelative"},"y":{"pos":0.3999999999999999,"kind":"ukData","scale":{"low":-0.05,"high":0.5},"axis":"akY"}},"tkAxis":"akY","tkKind":"tkOneSide","tkSecondary":false},{"name":"tick","children":[],"style":{"color":{"r":0.0,"g":0.0,"b":0.0,"a":1.0},"size":5.0,"lineType":"ltSolid","lineWidth":1.0,"fillColor":{"r":0.0,"g":0.0,"b":0.0,"a":0.0},"marker":"mkCircle","errorBarKind":"ebLines","gradient":null,"font":{"family":"","size":0.0,"bold":false,"slant":"fsNormal","color":{"r":0.0,"g":0.0,"b":0.0,"a":0.0},"alignKind":"taLeft"}},"rotateInView":null,"rotate":null,"kind":"goTick","tkMajor":true,"tkPos":{"x":{"pos":0.0,"kind":"ukRelative"},"y":{"pos":0.4999999999999999,"kind":"ukData","scale":{"low":-0.05,"high":0.5},"axis":"akY"}},"tkAxis":"akY","tkKind":"tkOneSide","tkSecondary":false},{"name":"ytickLabel","children":[],"style":{"color":{"r":0.0,"g":0.0,"b":0.0,"a":0.0},"size":0.0,"lineType":"ltNone","lineWidth":0.0,"fillColor":{"r":0.0,"g":0.0,"b":0.0,"a":0.0},"marker":"mkCircle","errorBarKind":"ebLines","gradient":null,"font":{"family":"","size":0.0,"bold":false,"slant":"fsNormal","color":{"r":0.0,"g":0.0,"b":0.0,"a":0.0},"alignKind":"taLeft"}},"rotateInView":null,"rotate":null,"kind":"goTickLabel","txtText":"0","txtFont":{"family":"sans-serif","size":8.0,"bold":false,"slant":"fsNormal","color":{"r":0.0,"g":0.0,"b":0.0,"a":1.0},"alignKind":"taLeft"},"txtPos":{"x":{"pos":-0.0210599167307153,"kind":"ukRelative"},"y":{"pos":-1.387778780781446e-17,"kind":"ukData","scale":{"low":-0.05,"high":0.5},"axis":"akY"}},"txtAlign":"taRight","txtRotate":0.0},{"name":"ytickLabel","children":[],"style":{"color":{"r":0.0,"g":0.0,"b":0.0,"a":0.0},"size":0.0,"lineType":"ltNone","lineWidth":0.0,"fillColor":{"r":0.0,"g":0.0,"b":0.0,"a":0.0},"marker":"mkCircle","errorBarKind":"ebLines","gradient":null,"font":{"family":"","size":0.0,"bold":false,"slant":"fsNormal","color":{"r":0.0,"g":0.0,"b":0.0,"a":0.0},"alignKind":"taLeft"}},"rotateInView":null,"rotate":null,"kind":"goTickLabel","txtText":"0.1","txtFont":{"family":"sans-serif","size":8.0,"bold":false,"slant":"fsNormal","color":{"r":0.0,"g":0.0,"b":0.0,"a":1.0},"alignKind":"taLeft"},"txtPos":{"x":{"pos":-0.0210599167307153,"kind":"ukRelative"},"y":{"pos":0.09999999999999998,"kind":"ukData","scale":{"low":-0.05,"high":0.5},"axis":"akY"}},"txtAlign":"taRight","txtRotate":0.0},{"name":"ytickLabel","children":[],"style":{"color":{"r":0.0,"g":0.0,"b":0.0,"a":0.0},"size":0.0,"lineType":"ltNone","lineWidth":0.0,"fillColor":{"r":0.0,"g":0.0,"b":0.0,"a":0.0},"marker":"mkCircle","errorBarKind":"ebLines","gradient":null,"font":{"family":"","size":0.0,"bold":false,"slant":"fsNormal","color":{"r":0.0,"g":0.0,"b":0.0,"a":0.0},"alignKind":"taLeft"}},"rotateInView":null,"rotate":null,"kind":"goTickLabel","txtText":"0.2","txtFont":{"family":"sans-serif","size":8.0,"bold":false,"slant":"fsNormal","color":{"r":0.0,"g":0.0,"b":0.0,"a":1.0},"alignKind":"taLeft"},"txtPos":{"x":{"pos":-0.0210599167307153,"kind":"ukRelative"},"y":{"pos":0.2,"kind":"ukData","scale":{"low":-0.05,"high":0.5},"axis":"akY"}},"txtAlign":"taRight","txtRotate":0.0},{"name":"ytickLabel","children":[],"style":{"color":{"r":0.0,"g":0.0,"b":0.0,"a":0.0},"size":0.0,"lineType":"ltNone","lineWidth":0.0,"fillColor":{"r":0.0,"g":0.0,"b":0.0,"a":0.0},"marker":"mkCircle","errorBarKind":"ebLines","gradient":null,"font":{"family":"","size":0.0,"bold":false,"slant":"fsNormal","color":{"r":0.0,"g":0.0,"b":0.0,"a":0.0},"alignKind":"taLeft"}},"rotateInView":null,"rotate":null,"kind":"goTickLabel","txtText":"0.3","txtFont":{"family":"sans-serif","size":8.0,"bold":false,"slant":"fsNormal","color":{"r":0.0,"g":0.0,"b":0.0,"a":1.0},"alignKind":"taLeft"},"txtPos":{"x":{"pos":-0.0210599167307153,"kind":"ukRelative"},"y":{"pos":0.2999999999999999,"kind":"ukData","scale":{"low":-0.05,"high":0.5},"axis":"akY"}},"txtAlign":"taRight","txtRotate":0.0},{"name":"ytickLabel","children":[],"style":{"color":{"r":0.0,"g":0.0,"b":0.0,"a":0.0},"size":0.0,"lineType":"ltNone","lineWidth":0.0,"fillColor":{"r":0.0,"g":0.0,"b":0.0,"a":0.0},"marker":"mkCircle","errorBarKind":"ebLines","gradient":null,"font":{"family":"","size":0.0,"bold":false,"slant":"fsNormal","color":{"r":0.0,"g":0.0,"b":0.0,"a":0.0},"alignKind":"taLeft"}},"rotateInView":null,"rotate":null,"kind":"goTickLabel","txtText":"0.4","txtFont":{"family":"sans-serif","size":8.0,"bold":false,"slant":"fsNormal","color":{"r":0.0,"g":0.0,"b":0.0,"a":1.0},"alignKind":"taLeft"},"txtPos":{"x":{"pos":-0.0210599167307153,"kind":"ukRelative"},"y":{"pos":0.3999999999999999,"kind":"ukData","scale":{"low":-0.05,"high":0.5},"axis":"akY"}},"txtAlign":"taRight","txtRotate":0.0},{"name":"ytickLabel","children":[],"style":{"color":{"r":0.0,"g":0.0,"b":0.0,"a":0.0},"size":0.0,"lineType":"ltNone","lineWidth":0.0,"fillColor":{"r":0.0,"g":0.0,"b":0.0,"a":0.0},"marker":"mkCircle","errorBarKind":"ebLines","gradient":null,"font":{"family":"","size":0.0,"bold":false,"slant":"fsNormal","color":{"r":0.0,"g":0.0,"b":0.0,"a":0.0},"alignKind":"taLeft"}},"rotateInView":null,"rotate":null,"kind":"goTickLabel","txtText":"0.5","txtFont":{"family":"sans-serif","size":8.0,"bold":false,"slant":"fsNormal","color":{"r":0.0,"g":0.0,"b":0.0,"a":1.0},"alignKind":"taLeft"},"txtPos":{"x":{"pos":-0.0210599167307153,"kind":"ukRelative"},"y":{"pos":0.4999999999999999,"kind":"ukData","scale":{"low":-0.05,"high":0.5},"axis":"akY"}},"txtAlign":"taRight","txtRotate":0.0},{"name":"xLabel","children":[],"style":{"color":{"r":0.0,"g":0.0,"b":0.0,"a":0.0},"size":0.0,"lineType":"ltNone","lineWidth":0.0,"fillColor":{"r":0.0,"g":0.0,"b":0.0,"a":0.0},"marker":"mkCircle","errorBarKind":"ebLines","gradient":null,"font":{"family":"","size":0.0,"bold":false,"slant":"fsNormal","color":{"r":0.0,"g":0.0,"b":0.0,"a":0.0},"alignKind":"taLeft"}},"rotateInView":null,"rotate":null,"kind":"goLabel","txtText":"x","txtFont":{"family":"sans-serif","size":12.0,"bold":false,"slant":"fsNormal","color":{"r":0.0,"g":0.0,"b":0.0,"a":1.0},"alignKind":"taCenter"},"txtPos":{"x":{"pos":0.5,"kind":"ukRelative"},"y":{"pos":423.0944881889764,"kind":"ukPoint","length":{"val":394.6417322834646,"unit":"ukPoint"}}},"txtAlign":"taCenter","txtRotate":0.0},{"name":"yLabel","children":[],"style":{"color":{"r":0.0,"g":0.0,"b":0.0,"a":0.0},"size":0.0,"lineType":"ltNone","lineWidth":0.0,"fillColor":{"r":0.0,"g":0.0,"b":0.0,"a":0.0},"marker":"mkCircle","errorBarKind":"ebLines","gradient":null,"font":{"family":"","size":0.0,"bold":false,"slant":"fsNormal","color":{"r":0.0,"g":0.0,"b":0.0,"a":0.0},"alignKind":"taLeft"}},"rotateInView":null,"rotate":-90.0,"kind":"goLabel","txtText":"y","txtFont":{"family":"sans-serif","size":12.0,"bold":false,"slant":"fsNormal","color":{"r":0.0,"g":0.0,"b":0.0,"a":1.0},"alignKind":"taCenter"},"txtPos":{"x":{"pos":-35.76220472440944,"kind":"ukPoint","length":{"val":540.4153543307086,"unit":"ukPoint"}},"y":{"pos":0.5,"kind":"ukRelative"}},"txtAlign":"taCenter","txtRotate":0.0},{"name":"xGridLines","children":[],"style":{"color":{"r":1.0,"g":1.0,"b":1.0,"a":1.0},"size":0.0,"lineType":"ltSolid","lineWidth":1.0,"fillColor":{"r":0.0,"g":0.0,"b":0.0,"a":0.0},"marker":"mkCircle","errorBarKind":"ebLines","gradient":null,"font":{"family":"","size":0.0,"bold":false,"slant":"fsNormal","color":{"r":0.0,"g":0.0,"b":0.0,"a":0.0},"alignKind":"taLeft"}},"rotateInView":null,"rotate":null,"kind":"goGrid","gdOrigin":{"x":{"pos":0.0,"kind":"ukRelative"},"y":{"pos":0.0,"kind":"ukRelative"}},"gdOriginDiag":{"x":{"pos":0.0,"kind":"ukRelative"},"y":{"pos":0.0,"kind":"ukRelative"}},"gdXPos":[{"pos":0.0,"kind":"ukData","scale":{"low":0.0,"high":1.2},"axis":"akX"},{"pos":0.2,"kind":"ukData","scale":{"low":0.0,"high":1.2},"axis":"akX"},{"pos":0.4,"kind":"ukData","scale":{"low":0.0,"high":1.2},"axis":"akX"},{"pos":0.6000000000000001,"kind":"ukData","scale":{"low":0.0,"high":1.2},"axis":"akX"},{"pos":0.8,"kind":"ukData","scale":{"low":0.0,"high":1.2},"axis":"akX"},{"pos":1.0,"kind":"ukData","scale":{"low":0.0,"high":1.2},"axis":"akX"},{"pos":1.2,"kind":"ukData","scale":{"low":0.0,"high":1.2},"axis":"akX"}],"gdYPos":[{"pos":-1.387778780781446e-17,"kind":"ukData","scale":{"low":-0.05,"high":0.5},"axis":"akY"},{"pos":0.09999999999999998,"kind":"ukData","scale":{"low":-0.05,"high":0.5},"axis":"akY"},{"pos":0.2,"kind":"ukData","scale":{"low":-0.05,"high":0.5},"axis":"akY"},{"pos":0.2999999999999999,"kind":"ukData","scale":{"low":-0.05,"high":0.5},"axis":"akY"},{"pos":0.3999999999999999,"kind":"ukData","scale":{"low":-0.05,"high":0.5},"axis":"akY"},{"pos":0.4999999999999999,"kind":"ukData","scale":{"low":-0.05,"high":0.5},"axis":"akY"}]}],"children":[{"name":"data","parent":"plot","style":{"color":{"r":0.0,"g":0.0,"b":0.0,"a":0.0},"size":0.0,"lineType":"ltNone","lineWidth":0.0,"fillColor":{"r":0.0,"g":0.0,"b":0.0,"a":0.0},"marker":"mkCircle","errorBarKind":"ebLines","gradient":null,"font":{"family":"","size":0.0,"bold":false,"slant":"fsNormal","color":{"r":0.0,"g":0.0,"b":0.0,"a":0.0},"alignKind":"taLeft"}},"xScale":{"low":0.0,"high":1.2},"yScale":{"low":-0.05,"high":0.5},"rotate":null,"scale":null,"origin":{"x":{"pos":0.0,"kind":"ukRelative"},"y":{"pos":0.0,"kind":"ukRelative"}},"width":{"val":1.0,"unit":"ukRelative"},"height":{"val":1.0,"unit":"ukRelative"},"objects":[{"name":"point","children":[],"style":{"color":{"r":0.0,"g":0.0,"b":0.0,"a":0.0},"size":0.0,"lineType":"ltNone","lineWidth":0.0,"fillColor":{"r":0.0,"g":0.0,"b":0.0,"a":0.0},"marker":"mkCircle","errorBarKind":"ebLines","gradient":null,"font":{"family":"","size":0.0,"bold":false,"slant":"fsNormal","color":{"r":0.0,"g":0.0,"b":0.0,"a":0.0},"alignKind":"taLeft"}},"rotateInView":null,"rotate":null,"kind":"goPoint","ptMarker":"mkCircle","ptSize":3.0,"ptColor":{"r":0.0,"g":0.0,"b":0.0,"a":1.0},"ptPos":{"x":{"pos":0.0,"kind":"ukData","scale":{"low":0.0,"high":1.2},"axis":"akX"},"y":{"pos":0.0,"kind":"ukData","scale":{"low":-0.05,"high":0.5},"axis":"akY"}}},{"name":"point","children":[],"style":{"color":{"r":0.0,"g":0.0,"b":0.0,"a":0.0},"size":0.0,"lineType":"ltNone","lineWidth":0.0,"fillColor":{"r":0.0,"g":0.0,"b":0.0,"a":0.0},"marker":"mkCircle","errorBarKind":"ebLines","gradient":null,"font":{"family":"","size":0.0,"bold":false,"slant":"fsNormal","color":{"r":0.0,"g":0.0,"b":0.0,"a":0.0},"alignKind":"taLeft"}},"rotateInView":null,"rotate":null,"kind":"goPoint","ptMarker":"mkCircle","ptSize":3.0,"ptColor":{"r":0.0,"g":0.0,"b":0.0,"a":1.0},"ptPos":{"x":{"pos":0.1111111111111111,"kind":"ukData","scale":{"low":0.0,"high":1.2},"axis":"akX"},"y":{"pos":0.04224965706447188,"kind":"ukData","scale":{"low":-0.05,"high":0.5},"axis":"akY"}}},{"name":"point","children":[],"style":{"color":{"r":0.0,"g":0.0,"b":0.0,"a":0.0},"size":0.0,"lineType":"ltNone","lineWidth":0.0,"fillColor":{"r":0.0,"g":0.0,"b":0.0,"a":0.0},"marker":"mkCircle","errorBarKind":"ebLines","gradient":null,"font":{"family":"","size":0.0,"bold":false,"slant":"fsNormal","color":{"r":0.0,"g":0.0,"b":0.0,"a":0.0},"alignKind":"taLeft"}},"rotateInView":null,"rotate":null,"kind":"goPoint","ptMarker":"mkCircle","ptSize":3.0,"ptColor":{"r":0.0,"g":0.0,"b":0.0,"a":1.0},"ptPos":{"x":{"pos":0.2222222222222222,"kind":"ukData","scale":{"low":0.0,"high":1.2},"axis":"akX"},"y":{"pos":0.06392318244170096,"kind":"ukData","scale":{"low":-0.05,"high":0.5},"axis":"akY"}}},{"name":"point","children":[],"style":{"color":{"r":0.0,"g":0.0,"b":0.0,"a":0.0},"size":0.0,"lineType":"ltNone","lineWidth":0.0,"fillColor":{"r":0.0,"g":0.0,"b":0.0,"a":0.0},"marker":"mkCircle","errorBarKind":"ebLines","gradient":null,"font":{"family":"","size":0.0,"bold":false,"slant":"fsNormal","color":{"r":0.0,"g":0.0,"b":0.0,"a":0.0},"alignKind":"taLeft"}},"rotateInView":null,"rotate":null,"kind":"goPoint","ptMarker":"mkCircle","ptSize":3.0,"ptColor":{"r":0.0,"g":0.0,"b":0.0,"a":1.0},"ptPos":{"x":{"pos":0.3333333333333333,"kind":"ukData","scale":{"low":0.0,"high":1.2},"axis":"akX"},"y":{"pos":0.0740740740740741,"kind":"ukData","scale":{"low":-0.05,"high":0.5},"axis":"akY"}}},{"name":"point","children":[],"style":{"color":{"r":0.0,"g":0.0,"b":0.0,"a":0.0},"size":0.0,"lineType":"ltNone","lineWidth":0.0,"fillColor":{"r":0.0,"g":0.0,"b":0.0,"a":0.0},"marker":"mkCircle","errorBarKind":"ebLines","gradient":null,"font":{"family":"","size":0.0,"bold":false,"slant":"fsNormal","color":{"r":0.0,"g":0.0,"b":0.0,"a":0.0},"alignKind":"taLeft"}},"rotateInView":null,"rotate":null,"kind":"goPoint","ptMarker":"mkCircle","ptSize":3.0,"ptColor":{"r":0.0,"g":0.0,"b":0.0,"a":1.0},"ptPos":{"x":{"pos":0.4444444444444444,"kind":"ukData","scale":{"low":0.0,"high":1.2},"axis":"akX"},"y":{"pos":0.08175582990397805,"kind":"ukData","scale":{"low":-0.05,"high":0.5},"axis":"akY"}}},{"name":"point","children":[],"style":{"color":{"r":0.0,"g":0.0,"b":0.0,"a":0.0},"size":0.0,"lineType":"ltNone","lineWidth":0.0,"fillColor":{"r":0.0,"g":0.0,"b":0.0,"a":0.0},"marker":"mkCircle","errorBarKind":"ebLines","gradient":null,"font":{"family":"","size":0.0,"bold":false,"slant":"fsNormal","color":{"r":0.0,"g":0.0,"b":0.0,"a":0.0},"alignKind":"taLeft"}},"rotateInView":null,"rotate":null,"kind":"goPoint","ptMarker":"mkCircle","ptSize":3.0,"ptColor":{"r":0.0,"g":0.0,"b":0.0,"a":1.0},"ptPos":{"x":{"pos":0.5555555555555556,"kind":"ukData","scale":{"low":0.0,"high":1.2},"axis":"akX"},"y":{"pos":0.09602194787379981,"kind":"ukData","scale":{"low":-0.05,"high":0.5},"axis":"akY"}}},{"name":"point","children":[],"style":{"color":{"r":0.0,"g":0.0,"b":0.0,"a":0.0},"size":0.0,"lineType":"ltNone","lineWidth":0.0,"fillColor":{"r":0.0,"g":0.0,"b":0.0,"a":0.0},"marker":"mkCircle","errorBarKind":"ebLines","gradient":null,"font":{"family":"","size":0.0,"bold":false,"slant":"fsNormal","color":{"r":0.0,"g":0.0,"b":0.0,"a":0.0},"alignKind":"taLeft"}},"rotateInView":null,"rotate":null,"kind":"goPoint","ptMarker":"mkCircle","ptSize":3.0,"ptColor":{"r":0.0,"g":0.0,"b":0.0,"a":1.0},"ptPos":{"x":{"pos":0.6666666666666667,"kind":"ukData","scale":{"low":0.0,"high":1.2},"axis":"akX"},"y":{"pos":0.125925925925926,"kind":"ukData","scale":{"low":-0.05,"high":0.5},"axis":"akY"}}},{"name":"point","children":[],"style":{"color":{"r":0.0,"g":0.0,"b":0.0,"a":0.0},"size":0.0,"lineType":"ltNone","lineWidth":0.0,"fillColor":{"r":0.0,"g":0.0,"b":0.0,"a":0.0},"marker":"mkCircle","errorBarKind":"ebLines","gradient":null,"font":{"family":"","size":0.0,"bold":false,"slant":"fsNormal","color":{"r":0.0,"g":0.0,"b":0.0,"a":0.0},"alignKind":"taLeft"}},"rotateInView":null,"rotate":null,"kind":"goPoint","ptMarker":"mkCircle","ptSize":3.0,"ptColor":{"r":0.0,"g":0.0,"b":0.0,"a":1.0},"ptPos":{"x":{"pos":0.7777777777777779,"kind":"ukData","scale":{"low":0.0,"high":1.2},"axis":"akX"},"y":{"pos":0.1805212620027437,"kind":"ukData","scale":{"low":-0.05,"high":0.5},"axis":"akY"}}},{"name":"point","children":[],"style":{"color":{"r":0.0,"g":0.0,"b":0.0,"a":0.0},"size":0.0,"lineType":"ltNone","lineWidth":0.0,"fillColor":{"r":0.0,"g":0.0,"b":0.0,"a":0.0},"marker":"mkCircle","errorBarKind":"ebLines","gradient":null,"font":{"family":"","size":0.0,"bold":false,"slant":"fsNormal","color":{"r":0.0,"g":0.0,"b":0.0,"a":0.0},"alignKind":"taLeft"}},"rotateInView":null,"rotate":null,"kind":"goPoint","ptMarker":"mkCircle","ptSize":3.0,"ptColor":{"r":0.0,"g":0.0,"b":0.0,"a":1.0},"ptPos":{"x":{"pos":0.8888888888888891,"kind":"ukData","scale":{"low":0.0,"high":1.2},"axis":"akX"},"y":{"pos":0.2688614540466395,"kind":"ukData","scale":{"low":-0.05,"high":0.5},"axis":"akY"}}},{"name":"point","children":[],"style":{"color":{"r":0.0,"g":0.0,"b":0.0,"a":0.0},"size":0.0,"lineType":"ltNone","lineWidth":0.0,"fillColor":{"r":0.0,"g":0.0,"b":0.0,"a":0.0},"marker":"mkCircle","errorBarKind":"ebLines","gradient":null,"font":{"family":"","size":0.0,"bold":false,"slant":"fsNormal","color":{"r":0.0,"g":0.0,"b":0.0,"a":0.0},"alignKind":"taLeft"}},"rotateInView":null,"rotate":null,"kind":"goPoint","ptMarker":"mkCircle","ptSize":3.0,"ptColor":{"r":0.0,"g":0.0,"b":0.0,"a":1.0},"ptPos":{"x":{"pos":1.0,"kind":"ukData","scale":{"low":0.0,"high":1.2},"axis":"akX"},"y":{"pos":0.4000000000000005,"kind":"ukData","scale":{"low":-0.05,"high":0.5},"axis":"akY"}}}],"children":[{"name":"data/layout_0","parent":"data","style":{"color":{"r":0.0,"g":0.0,"b":0.0,"a":0.0},"size":0.0,"lineType":"ltNone","lineWidth":0.0,"fillColor":{"r":0.0,"g":0.0,"b":0.0,"a":0.0},"marker":"mkCircle","errorBarKind":"ebLines","gradient":null,"font":{"family":"","size":0.0,"bold":false,"slant":"fsNormal","color":{"r":0.0,"g":0.0,"b":0.0,"a":0.0},"alignKind":"taLeft"}},"xScale":{"low":0.0,"high":1.2},"yScale":{"low":-0.05,"high":0.5},"rotate":null,"scale":null,"origin":{"x":{"pos":0.0,"kind":"ukRelative"},"y":{"pos":0.0,"kind":"ukRelative"}},"width":{"val":1.0,"unit":"ukRelative"},"height":{"val":1.0,"unit":"ukRelative"},"objects":[],"children":[],"wView":{"val":540.4153543307086,"unit":"ukPoint"},"hView":{"val":394.6417322834646,"unit":"ukPoint"},"wImg":{"val":640.0,"unit":"ukPoint"},"hImg":{"val":480.0,"unit":"ukPoint"},"backend":"bkCairo"}],"wView":{"val":540.4153543307086,"unit":"ukPoint"},"hView":{"val":394.6417322834646,"unit":"ukPoint"},"wImg":{"val":640.0,"unit":"ukPoint"},"hImg":{"val":480.0,"unit":"ukPoint"},"backend":"bkCairo"},{"name":"data","parent":"plot","style":{"color":{"r":0.0,"g":0.0,"b":0.0,"a":0.0},"size":0.0,"lineType":"ltNone","lineWidth":0.0,"fillColor":{"r":0.0,"g":0.0,"b":0.0,"a":0.0},"marker":"mkCircle","errorBarKind":"ebLines","gradient":null,"font":{"family":"","size":0.0,"bold":false,"slant":"fsNormal","color":{"r":0.0,"g":0.0,"b":0.0,"a":0.0},"alignKind":"taLeft"}},"xScale":{"low":0.0,"high":1.2},"yScale":{"low":-0.05,"high":0.5},"rotate":null,"scale":null,"origin":{"x":{"pos":0.0,"kind":"ukRelative"},"y":{"pos":0.0,"kind":"ukRelative"}},"width":{"val":1.0,"unit":"ukRelative"},"height":{"val":1.0,"unit":"ukRelative"},"objects":[{"name":"errorBar","children":[{"name":"line","children":[],"style":{"color":{"r":0.2000000029802322,"g":0.2000000029802322,"b":0.2000000029802322,"a":1.0},"size":5.0,"lineType":"ltSolid","lineWidth":1.0,"fillColor":{"r":0.0,"g":0.0,"b":0.0,"a":0.0},"marker":"mkCircle","errorBarKind":"ebLinesT","gradient":null,"font":{"family":"","size":0.0,"bold":false,"slant":"fsNormal","color":{"r":0.2000000029802322,"g":0.2000000029802322,"b":0.2000000029802322,"a":1.0},"alignKind":"taLeft"}},"rotateInView":null,"rotate":null,"kind":"goLine","lnStart":{"x":{"pos":0.0,"kind":"ukData","scale":{"low":0.0,"high":1.2},"axis":"akX"},"y":{"pos":0.0,"kind":"ukData","scale":{"low":-0.05,"high":0.5},"axis":"akY"}},"lnStop":{"x":{"pos":0.0,"kind":"ukData","scale":{"low":0.0,"high":1.2},"axis":"akX"},"y":{"pos":-0.03,"kind":"ukData","scale":{"low":-0.05,"high":0.5},"axis":"akY"}}},{"name":"line","children":[],"style":{"color":{"r":0.2000000029802322,"g":0.2000000029802322,"b":0.2000000029802322,"a":1.0},"size":5.0,"lineType":"ltSolid","lineWidth":1.0,"fillColor":{"r":0.0,"g":0.0,"b":0.0,"a":0.0},"marker":"mkCircle","errorBarKind":"ebLinesT","gradient":null,"font":{"family":"","size":0.0,"bold":false,"slant":"fsNormal","color":{"r":0.2000000029802322,"g":0.2000000029802322,"b":0.2000000029802322,"a":1.0},"alignKind":"taLeft"}},"rotateInView":null,"rotate":null,"kind":"goLine","lnStart":{"x":{"pos":0.0,"kind":"ukData","scale":{"low":0.0,"high":1.2},"axis":"akX"},"y":{"pos":0.0,"kind":"ukData","scale":{"low":-0.05,"high":0.5},"axis":"akY"}},"lnStop":{"x":{"pos":0.0,"kind":"ukData","scale":{"low":0.0,"high":1.2},"axis":"akX"},"y":{"pos":0.05,"kind":"ukData","scale":{"low":-0.05,"high":0.5},"axis":"akY"}}},{"name":"line","children":[],"style":{"color":{"r":0.2000000029802322,"g":0.2000000029802322,"b":0.2000000029802322,"a":1.0},"size":5.0,"lineType":"ltSolid","lineWidth":1.0,"fillColor":{"r":0.0,"g":0.0,"b":0.0,"a":0.0},"marker":"mkCircle","errorBarKind":"ebLinesT","gradient":null,"font":{"family":"","size":0.0,"bold":false,"slant":"fsNormal","color":{"r":0.2000000029802322,"g":0.2000000029802322,"b":0.2000000029802322,"a":1.0},"alignKind":"taLeft"}},"rotateInView":null,"rotate":null,"kind":"goLine","lnStart":{"x":{"pos":-0.009252142745263741,"kind":"ukRelative"},"y":{"pos":0.05,"kind":"ukData","scale":{"low":-0.05,"high":0.5},"axis":"akY"}},"lnStop":{"x":{"pos":0.009252142745263741,"kind":"ukRelative"},"y":{"pos":0.05,"kind":"ukData","scale":{"low":-0.05,"high":0.5},"axis":"akY"}}},{"name":"line","children":[],"style":{"color":{"r":0.2000000029802322,"g":0.2000000029802322,"b":0.2000000029802322,"a":1.0},"size":5.0,"lineType":"ltSolid","lineWidth":1.0,"fillColor":{"r":0.0,"g":0.0,"b":0.0,"a":0.0},"marker":"mkCircle","errorBarKind":"ebLinesT","gradient":null,"font":{"family":"","size":0.0,"bold":false,"slant":"fsNormal","color":{"r":0.2000000029802322,"g":0.2000000029802322,"b":0.2000000029802322,"a":1.0},"alignKind":"taLeft"}},"rotateInView":null,"rotate":null,"kind":"goLine","lnStart":{"x":{"pos":-0.009252142745263741,"kind":"ukRelative"},"y":{"pos":-0.03,"kind":"ukData","scale":{"low":-0.05,"high":0.5},"axis":"akY"}},"lnStop":{"x":{"pos":0.009252142745263741,"kind":"ukRelative"},"y":{"pos":-0.03,"kind":"ukData","scale":{"low":-0.05,"high":0.5},"axis":"akY"}}}],"style":{"color":{"r":0.2000000029802322,"g":0.2000000029802322,"b":0.2000000029802322,"a":1.0},"size":5.0,"lineType":"ltSolid","lineWidth":1.0,"fillColor":{"r":0.0,"g":0.0,"b":0.0,"a":0.0},"marker":"mkCircle","errorBarKind":"ebLinesT","gradient":null,"font":{"family":"","size":0.0,"bold":false,"slant":"fsNormal","color":{"r":0.2000000029802322,"g":0.2000000029802322,"b":0.2000000029802322,"a":1.0},"alignKind":"taLeft"}},"rotateInView":null,"rotate":null,"kind":"goComposite","cmpKind":"cmpErrorBar"},{"name":"errorBar","children":[{"name":"line","children":[],"style":{"color":{"r":0.2000000029802322,"g":0.2000000029802322,"b":0.2000000029802322,"a":1.0},"size":5.0,"lineType":"ltSolid","lineWidth":1.0,"fillColor":{"r":0.0,"g":0.0,"b":0.0,"a":0.0},"marker":"mkCircle","errorBarKind":"ebLinesT","gradient":null,"font":{"family":"","size":0.0,"bold":false,"slant":"fsNormal","color":{"r":0.2000000029802322,"g":0.2000000029802322,"b":0.2000000029802322,"a":1.0},"alignKind":"taLeft"}},"rotateInView":null,"rotate":null,"kind":"goLine","lnStart":{"x":{"pos":0.1111111111111111,"kind":"ukData","scale":{"low":0.0,"high":1.2},"axis":"akX"},"y":{"pos":0.04224965706447188,"kind":"ukData","scale":{"low":-0.05,"high":0.5},"axis":"akY"}},"lnStop":{"x":{"pos":0.1111111111111111,"kind":"ukData","scale":{"low":0.0,"high":1.2},"axis":"akX"},"y":{"pos":0.01224965706447188,"kind":"ukData","scale":{"low":-0.05,"high":0.5},"axis":"akY"}}},{"name":"line","children":[],"style":{"color":{"r":0.2000000029802322,"g":0.2000000029802322,"b":0.2000000029802322,"a":1.0},"size":5.0,"lineType":"ltSolid","lineWidth":1.0,"fillColor":{"r":0.0,"g":0.0,"b":0.0,"a":0.0},"marker":"mkCircle","errorBarKind":"ebLinesT","gradient":null,"font":{"family":"","size":0.0,"bold":false,"slant":"fsNormal","color":{"r":0.2000000029802322,"g":0.2000000029802322,"b":0.2000000029802322,"a":1.0},"alignKind":"taLeft"}},"rotateInView":null,"rotate":null,"kind":"goLine","lnStart":{"x":{"pos":0.1111111111111111,"kind":"ukData","scale":{"low":0.0,"high":1.2},"axis":"akX"},"y":{"pos":0.04224965706447188,"kind":"ukData","scale":{"low":-0.05,"high":0.5},"axis":"akY"}},"lnStop":{"x":{"pos":0.1111111111111111,"kind":"ukData","scale":{"low":0.0,"high":1.2},"axis":"akX"},"y":{"pos":0.09224965706447188,"kind":"ukData","scale":{"low":-0.05,"high":0.5},"axis":"akY"}}},{"name":"line","children":[],"style":{"color":{"r":0.2000000029802322,"g":0.2000000029802322,"b":0.2000000029802322,"a":1.0},"size":5.0,"lineType":"ltSolid","lineWidth":1.0,"fillColor":{"r":0.0,"g":0.0,"b":0.0,"a":0.0},"marker":"mkCircle","errorBarKind":"ebLinesT","gradient":null,"font":{"family":"","size":0.0,"bold":false,"slant":"fsNormal","color":{"r":0.2000000029802322,"g":0.2000000029802322,"b":0.2000000029802322,"a":1.0},"alignKind":"taLeft"}},"rotateInView":null,"rotate":null,"kind":"goLine","lnStart":{"x":{"pos":0.08334044984732883,"kind":"ukRelative"},"y":{"pos":0.09224965706447188,"kind":"ukData","scale":{"low":-0.05,"high":0.5},"axis":"akY"}},"lnStop":{"x":{"pos":0.1018447353378563,"kind":"ukRelative"},"y":{"pos":0.09224965706447188,"kind":"ukData","scale":{"low":-0.05,"high":0.5},"axis":"akY"}}},{"name":"line","children":[],"style":{"color":{"r":0.2000000029802322,"g":0.2000000029802322,"b":0.2000000029802322,"a":1.0},"size":5.0,"lineType":"ltSolid","lineWidth":1.0,"fillColor":{"r":0.0,"g":0.0,"b":0.0,"a":0.0},"marker":"mkCircle","errorBarKind":"ebLinesT","gradient":null,"font":{"family":"","size":0.0,"bold":false,"slant":"fsNormal","color":{"r":0.2000000029802322,"g":0.2000000029802322,"b":0.2000000029802322,"a":1.0},"alignKind":"taLeft"}},"rotateInView":null,"rotate":null,"kind":"goLine","lnStart":{"x":{"pos":0.08334044984732883,"kind":"ukRelative"},"y":{"pos":0.01224965706447188,"kind":"ukData","scale":{"low":-0.05,"high":0.5},"axis":"akY"}},"lnStop":{"x":{"pos":0.1018447353378563,"kind":"ukRelative"},"y":{"pos":0.01224965706447188,"kind":"ukData","scale":{"low":-0.05,"high":0.5},"axis":"akY"}}}],"style":{"color":{"r":0.2000000029802322,"g":0.2000000029802322,"b":0.2000000029802322,"a":1.0},"size":5.0,"lineType":"ltSolid","lineWidth":1.0,"fillColor":{"r":0.0,"g":0.0,"b":0.0,"a":0.0},"marker":"mkCircle","errorBarKind":"ebLinesT","gradient":null,"font":{"family":"","size":0.0,"bold":false,"slant":"fsNormal","color":{"r":0.2000000029802322,"g":0.2000000029802322,"b":0.2000000029802322,"a":1.0},"alignKind":"taLeft"}},"rotateInView":null,"rotate":null,"kind":"goComposite","cmpKind":"cmpErrorBar"},{"name":"errorBar","children":[{"name":"line","children":[],"style":{"color":{"r":0.2000000029802322,"g":0.2000000029802322,"b":0.2000000029802322,"a":1.0},"size":5.0,"lineType":"ltSolid","lineWidth":1.0,"fillColor":{"r":0.0,"g":0.0,"b":0.0,"a":0.0},"marker":"mkCircle","errorBarKind":"ebLinesT","gradient":null,"font":{"family":"","size":0.0,"bold":false,"slant":"fsNormal","color":{"r":0.2000000029802322,"g":0.2000000029802322,"b":0.2000000029802322,"a":1.0},"alignKind":"taLeft"}},"rotateInView":null,"rotate":null,"kind":"goLine","lnStart":{"x":{"pos":0.2222222222222222,"kind":"ukData","scale":{"low":0.0,"high":1.2},"axis":"akX"},"y":{"pos":0.06392318244170096,"kind":"ukData","scale":{"low":-0.05,"high":0.5},"axis":"akY"}},"lnStop":{"x":{"pos":0.2222222222222222,"kind":"ukData","scale":{"low":0.0,"high":1.2},"axis":"akX"},"y":{"pos":0.03392318244170096,"kind":"ukData","scale":{"low":-0.05,"high":0.5},"axis":"akY"}}},{"name":"line","children":[],"style":{"color":{"r":0.2000000029802322,"g":0.2000000029802322,"b":0.2000000029802322,"a":1.0},"size":5.0,"lineType":"ltSolid","lineWidth":1.0,"fillColor":{"r":0.0,"g":0.0,"b":0.0,"a":0.0},"marker":"mkCircle","errorBarKind":"ebLinesT","gradient":null,"font":{"family":"","size":0.0,"bold":false,"slant":"fsNormal","color":{"r":0.2000000029802322,"g":0.2000000029802322,"b":0.2000000029802322,"a":1.0},"alignKind":"taLeft"}},"rotateInView":null,"rotate":null,"kind":"goLine","lnStart":{"x":{"pos":0.2222222222222222,"kind":"ukData","scale":{"low":0.0,"high":1.2},"axis":"akX"},"y":{"pos":0.06392318244170096,"kind":"ukData","scale":{"low":-0.05,"high":0.5},"axis":"akY"}},"lnStop":{"x":{"pos":0.2222222222222222,"kind":"ukData","scale":{"low":0.0,"high":1.2},"axis":"akX"},"y":{"pos":0.113923182441701,"kind":"ukData","scale":{"low":-0.05,"high":0.5},"axis":"akY"}}},{"name":"line","children":[],"style":{"color":{"r":0.2000000029802322,"g":0.2000000029802322,"b":0.2000000029802322,"a":1.0},"size":5.0,"lineType":"ltSolid","lineWidth":1.0,"fillColor":{"r":0.0,"g":0.0,"b":0.0,"a":0.0},"marker":"mkCircle","errorBarKind":"ebLinesT","gradient":null,"font":{"family":"","size":0.0,"bold":false,"slant":"fsNormal","color":{"r":0.2000000029802322,"g":0.2000000029802322,"b":0.2000000029802322,"a":1.0},"alignKind":"taLeft"}},"rotateInView":null,"rotate":null,"kind":"goLine","lnStart":{"x":{"pos":0.1759330424399214,"kind":"ukRelative"},"y":{"pos":0.113923182441701,"kind":"ukData","scale":{"low":-0.05,"high":0.5},"axis":"akY"}},"lnStop":{"x":{"pos":0.1944373279304489,"kind":"ukRelative"},"y":{"pos":0.113923182441701,"kind":"ukData","scale":{"low":-0.05,"high":0.5},"axis":"akY"}}},{"name":"line","children":[],"style":{"color":{"r":0.2000000029802322,"g":0.2000000029802322,"b":0.2000000029802322,"a":1.0},"size":5.0,"lineType":"ltSolid","lineWidth":1.0,"fillColor":{"r":0.0,"g":0.0,"b":0.0,"a":0.0},"marker":"mkCircle","errorBarKind":"ebLinesT","gradient":null,"font":{"family":"","size":0.0,"bold":false,"slant":"fsNormal","color":{"r":0.2000000029802322,"g":0.2000000029802322,"b":0.2000000029802322,"a":1.0},"alignKind":"taLeft"}},"rotateInView":null,"rotate":null,"kind":"goLine","lnStart":{"x":{"pos":0.1759330424399214,"kind":"ukRelative"},"y":{"pos":0.03392318244170096,"kind":"ukData","scale":{"low":-0.05,"high":0.5},"axis":"akY"}},"lnStop":{"x":{"pos":0.1944373279304489,"kind":"ukRelative"},"y":{"pos":0.03392318244170096,"kind":"ukData","scale":{"low":-0.05,"high":0.5},"axis":"akY"}}}],"style":{"color":{"r":0.2000000029802322,"g":0.2000000029802322,"b":0.2000000029802322,"a":1.0},"size":5.0,"lineType":"ltSolid","lineWidth":1.0,"fillColor":{"r":0.0,"g":0.0,"b":0.0,"a":0.0},"marker":"mkCircle","errorBarKind":"ebLinesT","gradient":null,"font":{"family":"","size":0.0,"bold":false,"slant":"fsNormal","color":{"r":0.2000000029802322,"g":0.2000000029802322,"b":0.2000000029802322,"a":1.0},"alignKind":"taLeft"}},"rotateInView":null,"rotate":null,"kind":"goComposite","cmpKind":"cmpErrorBar"},{"name":"errorBar","children":[{"name":"line","children":[],"style":{"color":{"r":0.2000000029802322,"g":0.2000000029802322,"b":0.2000000029802322,"a":1.0},"size":5.0,"lineType":"ltSolid","lineWidth":1.0,"fillColor":{"r":0.0,"g":0.0,"b":0.0,"a":0.0},"marker":"mkCircle","errorBarKind":"ebLinesT","gradient":null,"font":{"family":"","size":0.0,"bold":false,"slant":"fsNormal","color":{"r":0.2000000029802322,"g":0.2000000029802322,"b":0.2000000029802322,"a":1.0},"alignKind":"taLeft"}},"rotateInView":null,"rotate":null,"kind":"goLine","lnStart":{"x":{"pos":0.3333333333333333,"kind":"ukData","scale":{"low":0.0,"high":1.2},"axis":"akX"},"y":{"pos":0.0740740740740741,"kind":"ukData","scale":{"low":-0.05,"high":0.5},"axis":"akY"}},"lnStop":{"x":{"pos":0.3333333333333333,"kind":"ukData","scale":{"low":0.0,"high":1.2},"axis":"akX"},"y":{"pos":0.0440740740740741,"kind":"ukData","scale":{"low":-0.05,"high":0.5},"axis":"akY"}}},{"name":"line","children":[],"style":{"color":{"r":0.2000000029802322,"g":0.2000000029802322,"b":0.2000000029802322,"a":1.0},"size":5.0,"lineType":"ltSolid","lineWidth":1.0,"fillColor":{"r":0.0,"g":0.0,"b":0.0,"a":0.0},"marker":"mkCircle","errorBarKind":"ebLinesT","gradient":null,"font":{"family":"","size":0.0,"bold":false,"slant":"fsNormal","color":{"r":0.2000000029802322,"g":0.2000000029802322,"b":0.2000000029802322,"a":1.0},"alignKind":"taLeft"}},"rotateInView":null,"rotate":null,"kind":"goLine","lnStart":{"x":{"pos":0.3333333333333333,"kind":"ukData","scale":{"low":0.0,"high":1.2},"axis":"akX"},"y":{"pos":0.0740740740740741,"kind":"ukData","scale":{"low":-0.05,"high":0.5},"axis":"akY"}},"lnStop":{"x":{"pos":0.3333333333333333,"kind":"ukData","scale":{"low":0.0,"high":1.2},"axis":"akX"},"y":{"pos":0.1240740740740741,"kind":"ukData","scale":{"low":-0.05,"high":0.5},"axis":"akY"}}},{"name":"line","children":[],"style":{"color":{"r":0.2000000029802322,"g":0.2000000029802322,"b":0.2000000029802322,"a":1.0},"size":5.0,"lineType":"ltSolid","lineWidth":1.0,"fillColor":{"r":0.0,"g":0.0,"b":0.0,"a":0.0},"marker":"mkCircle","errorBarKind":"ebLinesT","gradient":null,"font":{"family":"","size":0.0,"bold":false,"slant":"fsNormal","color":{"r":0.2000000029802322,"g":0.2000000029802322,"b":0.2000000029802322,"a":1.0},"alignKind":"taLeft"}},"rotateInView":null,"rotate":null,"kind":"goLine","lnStart":{"x":{"pos":0.268525635032514,"kind":"ukRelative"},"y":{"pos":0.1240740740740741,"kind":"ukData","scale":{"low":-0.05,"high":0.5},"axis":"akY"}},"lnStop":{"x":{"pos":0.2870299205230415,"kind":"ukRelative"},"y":{"pos":0.1240740740740741,"kind":"ukData","scale":{"low":-0.05,"high":0.5},"axis":"akY"}}},{"name":"line","children":[],"style":{"color":{"r":0.2000000029802322,"g":0.2000000029802322,"b":0.2000000029802322,"a":1.0},"size":5.0,"lineType":"ltSolid","lineWidth":1.0,"fillColor":{"r":0.0,"g":0.0,"b":0.0,"a":0.0},"marker":"mkCircle","errorBarKind":"ebLinesT","gradient":null,"font":{"family":"","size":0.0,"bold":false,"slant":"fsNormal","color":{"r":0.2000000029802322,"g":0.2000000029802322,"b":0.2000000029802322,"a":1.0},"alignKind":"taLeft"}},"rotateInView":null,"rotate":null,"kind":"goLine","lnStart":{"x":{"pos":0.268525635032514,"kind":"ukRelative"},"y":{"pos":0.0440740740740741,"kind":"ukData","scale":{"low":-0.05,"high":0.5},"axis":"akY"}},"lnStop":{"x":{"pos":0.2870299205230415,"kind":"ukRelative"},"y":{"pos":0.0440740740740741,"kind":"ukData","scale":{"low":-0.05,"high":0.5},"axis":"akY"}}}],"style":{"color":{"r":0.2000000029802322,"g":0.2000000029802322,"b":0.2000000029802322,"a":1.0},"size":5.0,"lineType":"ltSolid","lineWidth":1.0,"fillColor":{"r":0.0,"g":0.0,"b":0.0,"a":0.0},"marker":"mkCircle","errorBarKind":"ebLinesT","gradient":null,"font":{"family":"","size":0.0,"bold":false,"slant":"fsNormal","color":{"r":0.2000000029802322,"g":0.2000000029802322,"b":0.2000000029802322,"a":1.0},"alignKind":"taLeft"}},"rotateInView":null,"rotate":null,"kind":"goComposite","cmpKind":"cmpErrorBar"},{"name":"errorBar","children":[{"name":"line","children":[],"style":{"color":{"r":0.2000000029802322,"g":0.2000000029802322,"b":0.2000000029802322,"a":1.0},"size":5.0,"lineType":"ltSolid","lineWidth":1.0,"fillColor":{"r":0.0,"g":0.0,"b":0.0,"a":0.0},"marker":"mkCircle","errorBarKind":"ebLinesT","gradient":null,"font":{"family":"","size":0.0,"bold":false,"slant":"fsNormal","color":{"r":0.2000000029802322,"g":0.2000000029802322,"b":0.2000000029802322,"a":1.0},"alignKind":"taLeft"}},"rotateInView":null,"rotate":null,"kind":"goLine","lnStart":{"x":{"pos":0.4444444444444444,"kind":"ukData","scale":{"low":0.0,"high":1.2},"axis":"akX"},"y":{"pos":0.08175582990397805,"kind":"ukData","scale":{"low":-0.05,"high":0.5},"axis":"akY"}},"lnStop":{"x":{"pos":0.4444444444444444,"kind":"ukData","scale":{"low":0.0,"high":1.2},"axis":"akX"},"y":{"pos":0.05175582990397805,"kind":"ukData","scale":{"low":-0.05,"high":0.5},"axis":"akY"}}},{"name":"line","children":[],"style":{"color":{"r":0.2000000029802322,"g":0.2000000029802322,"b":0.2000000029802322,"a":1.0},"size":5.0,"lineType":"ltSolid","lineWidth":1.0,"fillColor":{"r":0.0,"g":0.0,"b":0.0,"a":0.0},"marker":"mkCircle","errorBarKind":"ebLinesT","gradient":null,"font":{"family":"","size":0.0,"bold":false,"slant":"fsNormal","color":{"r":0.2000000029802322,"g":0.2000000029802322,"b":0.2000000029802322,"a":1.0},"alignKind":"taLeft"}},"rotateInView":null,"rotate":null,"kind":"goLine","lnStart":{"x":{"pos":0.4444444444444444,"kind":"ukData","scale":{"low":0.0,"high":1.2},"axis":"akX"},"y":{"pos":0.08175582990397805,"kind":"ukData","scale":{"low":-0.05,"high":0.5},"axis":"akY"}},"lnStop":{"x":{"pos":0.4444444444444444,"kind":"ukData","scale":{"low":0.0,"high":1.2},"axis":"akX"},"y":{"pos":0.1317558299039781,"kind":"ukData","scale":{"low":-0.05,"high":0.5},"axis":"akY"}}},{"name":"line","children":[],"style":{"color":{"r":0.2000000029802322,"g":0.2000000029802322,"b":0.2000000029802322,"a":1.0},"size":5.0,"lineType":"ltSolid","lineWidth":1.0,"fillColor":{"r":0.0,"g":0.0,"b":0.0,"a":0.0},"marker":"mkCircle","errorBarKind":"ebLinesT","gradient":null,"font":{"family":"","size":0.0,"bold":false,"slant":"fsNormal","color":{"r":0.2000000029802322,"g":0.2000000029802322,"b":0.2000000029802322,"a":1.0},"alignKind":"taLeft"}},"rotateInView":null,"rotate":null,"kind":"goLine","lnStart":{"x":{"pos":0.3611182276251065,"kind":"ukRelative"},"y":{"pos":0.1317558299039781,"kind":"ukData","scale":{"low":-0.05,"high":0.5},"axis":"akY"}},"lnStop":{"x":{"pos":0.3796225131156341,"kind":"ukRelative"},"y":{"pos":0.1317558299039781,"kind":"ukData","scale":{"low":-0.05,"high":0.5},"axis":"akY"}}},{"name":"line","children":[],"style":{"color":{"r":0.2000000029802322,"g":0.2000000029802322,"b":0.2000000029802322,"a":1.0},"size":5.0,"lineType":"ltSolid","lineWidth":1.0,"fillColor":{"r":0.0,"g":0.0,"b":0.0,"a":0.0},"marker":"mkCircle","errorBarKind":"ebLinesT","gradient":null,"font":{"family":"","size":0.0,"bold":false,"slant":"fsNormal","color":{"r":0.2000000029802322,"g":0.2000000029802322,"b":0.2000000029802322,"a":1.0},"alignKind":"taLeft"}},"rotateInView":null,"rotate":null,"kind":"goLine","lnStart":{"x":{"pos":0.3611182276251065,"kind":"ukRelative"},"y":{"pos":0.05175582990397805,"kind":"ukData","scale":{"low":-0.05,"high":0.5},"axis":"akY"}},"lnStop":{"x":{"pos":0.3796225131156341,"kind":"ukRelative"},"y":{"pos":0.05175582990397805,"kind":"ukData","scale":{"low":-0.05,"high":0.5},"axis":"akY"}}}],"style":{"color":{"r":0.2000000029802322,"g":0.2000000029802322,"b":0.2000000029802322,"a":1.0},"size":5.0,"lineType":"ltSolid","lineWidth":1.0,"fillColor":{"r":0.0,"g":0.0,"b":0.0,"a":0.0},"marker":"mkCircle","errorBarKind":"ebLinesT","gradient":null,"font":{"family":"","size":0.0,"bold":false,"slant":"fsNormal","color":{"r":0.2000000029802322,"g":0.2000000029802322,"b":0.2000000029802322,"a":1.0},"alignKind":"taLeft"}},"rotateInView":null,"rotate":null,"kind":"goComposite","cmpKind":"cmpErrorBar"},{"name":"errorBar","children":[{"name":"line","children":[],"style":{"color":{"r":0.2000000029802322,"g":0.2000000029802322,"b":0.2000000029802322,"a":1.0},"size":5.0,"lineType":"ltSolid","lineWidth":1.0,"fillColor":{"r":0.0,"g":0.0,"b":0.0,"a":0.0},"marker":"mkCircle","errorBarKind":"ebLinesT","gradient":null,"font":{"family":"","size":0.0,"bold":false,"slant":"fsNormal","color":{"r":0.2000000029802322,"g":0.2000000029802322,"b":0.2000000029802322,"a":1.0},"alignKind":"taLeft"}},"rotateInView":null,"rotate":null,"kind":"goLine","lnStart":{"x":{"pos":0.5555555555555556,"kind":"ukData","scale":{"low":0.0,"high":1.2},"axis":"akX"},"y":{"pos":0.09602194787379981,"kind":"ukData","scale":{"low":-0.05,"high":0.5},"axis":"akY"}},"lnStop":{"x":{"pos":0.5555555555555556,"kind":"ukData","scale":{"low":0.0,"high":1.2},"axis":"akX"},"y":{"pos":0.06602194787379981,"kind":"ukData","scale":{"low":-0.05,"high":0.5},"axis":"akY"}}},{"name":"line","children":[],"style":{"color":{"r":0.2000000029802322,"g":0.2000000029802322,"b":0.2000000029802322,"a":1.0},"size":5.0,"lineType":"ltSolid","lineWidth":1.0,"fillColor":{"r":0.0,"g":0.0,"b":0.0,"a":0.0},"marker":"mkCircle","errorBarKind":"ebLinesT","gradient":null,"font":{"family":"","size":0.0,"bold":false,"slant":"fsNormal","color":{"r":0.2000000029802322,"g":0.2000000029802322,"b":0.2000000029802322,"a":1.0},"alignKind":"taLeft"}},"rotateInView":null,"rotate":null,"kind":"goLine","lnStart":{"x":{"pos":0.5555555555555556,"kind":"ukData","scale":{"low":0.0,"high":1.2},"axis":"akX"},"y":{"pos":0.09602194787379981,"kind":"ukData","scale":{"low":-0.05,"high":0.5},"axis":"akY"}},"lnStop":{"x":{"pos":0.5555555555555556,"kind":"ukData","scale":{"low":0.0,"high":1.2},"axis":"akX"},"y":{"pos":0.1460219478737998,"kind":"ukData","scale":{"low":-0.05,"high":0.5},"axis":"akY"}}},{"name":"line","children":[],"style":{"color":{"r":0.2000000029802322,"g":0.2000000029802322,"b":0.2000000029802322,"a":1.0},"size":5.0,"lineType":"ltSolid","lineWidth":1.0,"fillColor":{"r":0.0,"g":0.0,"b":0.0,"a":0.0},"marker":"mkCircle","errorBarKind":"ebLinesT","gradient":null,"font":{"family":"","size":0.0,"bold":false,"slant":"fsNormal","color":{"r":0.2000000029802322,"g":0.2000000029802322,"b":0.2000000029802322,"a":1.0},"alignKind":"taLeft"}},"rotateInView":null,"rotate":null,"kind":"goLine","lnStart":{"x":{"pos":0.4537108202176992,"kind":"ukRelative"},"y":{"pos":0.1460219478737998,"kind":"ukData","scale":{"low":-0.05,"high":0.5},"axis":"akY"}},"lnStop":{"x":{"pos":0.4722151057082267,"kind":"ukRelative"},"y":{"pos":0.1460219478737998,"kind":"ukData","scale":{"low":-0.05,"high":0.5},"axis":"akY"}}},{"name":"line","children":[],"style":{"color":{"r":0.2000000029802322,"g":0.2000000029802322,"b":0.2000000029802322,"a":1.0},"size":5.0,"lineType":"ltSolid","lineWidth":1.0,"fillColor":{"r":0.0,"g":0.0,"b":0.0,"a":0.0},"marker":"mkCircle","errorBarKind":"ebLinesT","gradient":null,"font":{"family":"","size":0.0,"bold":false,"slant":"fsNormal","color":{"r":0.2000000029802322,"g":0.2000000029802322,"b":0.2000000029802322,"a":1.0},"alignKind":"taLeft"}},"rotateInView":null,"rotate":null,"kind":"goLine","lnStart":{"x":{"pos":0.4537108202176992,"kind":"ukRelative"},"y":{"pos":0.06602194787379981,"kind":"ukData","scale":{"low":-0.05,"high":0.5},"axis":"akY"}},"lnStop":{"x":{"pos":0.4722151057082267,"kind":"ukRelative"},"y":{"pos":0.06602194787379981,"kind":"ukData","scale":{"low":-0.05,"high":0.5},"axis":"akY"}}}],"style":{"color":{"r":0.2000000029802322,"g":0.2000000029802322,"b":0.2000000029802322,"a":1.0},"size":5.0,"lineType":"ltSolid","lineWidth":1.0,"fillColor":{"r":0.0,"g":0.0,"b":0.0,"a":0.0},"marker":"mkCircle","errorBarKind":"ebLinesT","gradient":null,"font":{"family":"","size":0.0,"bold":false,"slant":"fsNormal","color":{"r":0.2000000029802322,"g":0.2000000029802322,"b":0.2000000029802322,"a":1.0},"alignKind":"taLeft"}},"rotateInView":null,"rotate":null,"kind":"goComposite","cmpKind":"cmpErrorBar"},{"name":"errorBar","children":[{"name":"line","children":[],"style":{"color":{"r":0.2000000029802322,"g":0.2000000029802322,"b":0.2000000029802322,"a":1.0},"size":5.0,"lineType":"ltSolid","lineWidth":1.0,"fillColor":{"r":0.0,"g":0.0,"b":0.0,"a":0.0},"marker":"mkCircle","errorBarKind":"ebLinesT","gradient":null,"font":{"family":"","size":0.0,"bold":false,"slant":"fsNormal","color":{"r":0.2000000029802322,"g":0.2000000029802322,"b":0.2000000029802322,"a":1.0},"alignKind":"taLeft"}},"rotateInView":null,"rotate":null,"kind":"goLine","lnStart":{"x":{"pos":0.6666666666666667,"kind":"ukData","scale":{"low":0.0,"high":1.2},"axis":"akX"},"y":{"pos":0.125925925925926,"kind":"ukData","scale":{"low":-0.05,"high":0.5},"axis":"akY"}},"lnStop":{"x":{"pos":0.6666666666666667,"kind":"ukData","scale":{"low":0.0,"high":1.2},"axis":"akX"},"y":{"pos":0.095925925925926,"kind":"ukData","scale":{"low":-0.05,"high":0.5},"axis":"akY"}}},{"name":"line","children":[],"style":{"color":{"r":0.2000000029802322,"g":0.2000000029802322,"b":0.2000000029802322,"a":1.0},"size":5.0,"lineType":"ltSolid","lineWidth":1.0,"fillColor":{"r":0.0,"g":0.0,"b":0.0,"a":0.0},"marker":"mkCircle","errorBarKind":"ebLinesT","gradient":null,"font":{"family":"","size":0.0,"bold":false,"slant":"fsNormal","color":{"r":0.2000000029802322,"g":0.2000000029802322,"b":0.2000000029802322,"a":1.0},"alignKind":"taLeft"}},"rotateInView":null,"rotate":null,"kind":"goLine","lnStart":{"x":{"pos":0.6666666666666667,"kind":"ukData","scale":{"low":0.0,"high":1.2},"axis":"akX"},"y":{"pos":0.125925925925926,"kind":"ukData","scale":{"low":-0.05,"high":0.5},"axis":"akY"}},"lnStop":{"x":{"pos":0.6666666666666667,"kind":"ukData","scale":{"low":0.0,"high":1.2},"axis":"akX"},"y":{"pos":0.175925925925926,"kind":"ukData","scale":{"low":-0.05,"high":0.5},"axis":"akY"}}},{"name":"line","children":[],"style":{"color":{"r":0.2000000029802322,"g":0.2000000029802322,"b":0.2000000029802322,"a":1.0},"size":5.0,"lineType":"ltSolid","lineWidth":1.0,"fillColor":{"r":0.0,"g":0.0,"b":0.0,"a":0.0},"marker":"mkCircle","errorBarKind":"ebLinesT","gradient":null,"font":{"family":"","size":0.0,"bold":false,"slant":"fsNormal","color":{"r":0.2000000029802322,"g":0.2000000029802322,"b":0.2000000029802322,"a":1.0},"alignKind":"taLeft"}},"rotateInView":null,"rotate":null,"kind":"goLine","lnStart":{"x":{"pos":0.5463034128102918,"kind":"ukRelative"},"y":{"pos":0.175925925925926,"kind":"ukData","scale":{"low":-0.05,"high":0.5},"axis":"akY"}},"lnStop":{"x":{"pos":0.5648076983008193,"kind":"ukRelative"},"y":{"pos":0.175925925925926,"kind":"ukData","scale":{"low":-0.05,"high":0.5},"axis":"akY"}}},{"name":"line","children":[],"style":{"color":{"r":0.2000000029802322,"g":0.2000000029802322,"b":0.2000000029802322,"a":1.0},"size":5.0,"lineType":"ltSolid","lineWidth":1.0,"fillColor":{"r":0.0,"g":0.0,"b":0.0,"a":0.0},"marker":"mkCircle","errorBarKind":"ebLinesT","gradient":null,"font":{"family":"","size":0.0,"bold":false,"slant":"fsNormal","color":{"r":0.2000000029802322,"g":0.2000000029802322,"b":0.2000000029802322,"a":1.0},"alignKind":"taLeft"}},"rotateInView":null,"rotate":null,"kind":"goLine","lnStart":{"x":{"pos":0.5463034128102918,"kind":"ukRelative"},"y":{"pos":0.095925925925926,"kind":"ukData","scale":{"low":-0.05,"high":0.5},"axis":"akY"}},"lnStop":{"x":{"pos":0.5648076983008193,"kind":"ukRelative"},"y":{"pos":0.095925925925926,"kind":"ukData","scale":{"low":-0.05,"high":0.5},"axis":"akY"}}}],"style":{"color":{"r":0.2000000029802322,"g":0.2000000029802322,"b":0.2000000029802322,"a":1.0},"size":5.0,"lineType":"ltSolid","lineWidth":1.0,"fillColor":{"r":0.0,"g":0.0,"b":0.0,"a":0.0},"marker":"mkCircle","errorBarKind":"ebLinesT","gradient":null,"font":{"family":"","size":0.0,"bold":false,"slant":"fsNormal","color":{"r":0.2000000029802322,"g":0.2000000029802322,"b":0.2000000029802322,"a":1.0},"alignKind":"taLeft"}},"rotateInView":null,"rotate":null,"kind":"goComposite","cmpKind":"cmpErrorBar"},{"name":"errorBar","children":[{"name":"line","children":[],"style":{"color":{"r":0.2000000029802322,"g":0.2000000029802322,"b":0.2000000029802322,"a":1.0},"size":5.0,"lineType":"ltSolid","lineWidth":1.0,"fillColor":{"r":0.0,"g":0.0,"b":0.0,"a":0.0},"marker":"mkCircle","errorBarKind":"ebLinesT","gradient":null,"font":{"family":"","size":0.0,"bold":false,"slant":"fsNormal","color":{"r":0.2000000029802322,"g":0.2000000029802322,"b":0.2000000029802322,"a":1.0},"alignKind":"taLeft"}},"rotateInView":null,"rotate":null,"kind":"goLine","lnStart":{"x":{"pos":0.7777777777777779,"kind":"ukData","scale":{"low":0.0,"high":1.2},"axis":"akX"},"y":{"pos":0.1805212620027437,"kind":"ukData","scale":{"low":-0.05,"high":0.5},"axis":"akY"}},"lnStop":{"x":{"pos":0.7777777777777779,"kind":"ukData","scale":{"low":0.0,"high":1.2},"axis":"akX"},"y":{"pos":0.1505212620027437,"kind":"ukData","scale":{"low":-0.05,"high":0.5},"axis":"akY"}}},{"name":"line","children":[],"style":{"color":{"r":0.2000000029802322,"g":0.2000000029802322,"b":0.2000000029802322,"a":1.0},"size":5.0,"lineType":"ltSolid","lineWidth":1.0,"fillColor":{"r":0.0,"g":0.0,"b":0.0,"a":0.0},"marker":"mkCircle","errorBarKind":"ebLinesT","gradient":null,"font":{"family":"","size":0.0,"bold":false,"slant":"fsNormal","color":{"r":0.2000000029802322,"g":0.2000000029802322,"b":0.2000000029802322,"a":1.0},"alignKind":"taLeft"}},"rotateInView":null,"rotate":null,"kind":"goLine","lnStart":{"x":{"pos":0.7777777777777779,"kind":"ukData","scale":{"low":0.0,"high":1.2},"axis":"akX"},"y":{"pos":0.1805212620027437,"kind":"ukData","scale":{"low":-0.05,"high":0.5},"axis":"akY"}},"lnStop":{"x":{"pos":0.7777777777777779,"kind":"ukData","scale":{"low":0.0,"high":1.2},"axis":"akX"},"y":{"pos":0.2305212620027436,"kind":"ukData","scale":{"low":-0.05,"high":0.5},"axis":"akY"}}},{"name":"line","children":[],"style":{"color":{"r":0.2000000029802322,"g":0.2000000029802322,"b":0.2000000029802322,"a":1.0},"size":5.0,"lineType":"ltSolid","lineWidth":1.0,"fillColor":{"r":0.0,"g":0.0,"b":0.0,"a":0.0},"marker":"mkCircle","errorBarKind":"ebLinesT","gradient":null,"font":{"family":"","size":0.0,"bold":false,"slant":"fsNormal","color":{"r":0.2000000029802322,"g":0.2000000029802322,"b":0.2000000029802322,"a":1.0},"alignKind":"taLeft"}},"rotateInView":null,"rotate":null,"kind":"goLine","lnStart":{"x":{"pos":0.6388960054028844,"kind":"ukRelative"},"y":{"pos":0.2305212620027436,"kind":"ukData","scale":{"low":-0.05,"high":0.5},"axis":"akY"}},"lnStop":{"x":{"pos":0.6574002908934119,"kind":"ukRelative"},"y":{"pos":0.2305212620027436,"kind":"ukData","scale":{"low":-0.05,"high":0.5},"axis":"akY"}}},{"name":"line","children":[],"style":{"color":{"r":0.2000000029802322,"g":0.2000000029802322,"b":0.2000000029802322,"a":1.0},"size":5.0,"lineType":"ltSolid","lineWidth":1.0,"fillColor":{"r":0.0,"g":0.0,"b":0.0,"a":0.0},"marker":"mkCircle","errorBarKind":"ebLinesT","gradient":null,"font":{"family":"","size":0.0,"bold":false,"slant":"fsNormal","color":{"r":0.2000000029802322,"g":0.2000000029802322,"b":0.2000000029802322,"a":1.0},"alignKind":"taLeft"}},"rotateInView":null,"rotate":null,"kind":"goLine","lnStart":{"x":{"pos":0.6388960054028844,"kind":"ukRelative"},"y":{"pos":0.1505212620027437,"kind":"ukData","scale":{"low":-0.05,"high":0.5},"axis":"akY"}},"lnStop":{"x":{"pos":0.6574002908934119,"kind":"ukRelative"},"y":{"pos":0.1505212620027437,"kind":"ukData","scale":{"low":-0.05,"high":0.5},"axis":"akY"}}}],"style":{"color":{"r":0.2000000029802322,"g":0.2000000029802322,"b":0.2000000029802322,"a":1.0},"size":5.0,"lineType":"ltSolid","lineWidth":1.0,"fillColor":{"r":0.0,"g":0.0,"b":0.0,"a":0.0},"marker":"mkCircle","errorBarKind":"ebLinesT","gradient":null,"font":{"family":"","size":0.0,"bold":false,"slant":"fsNormal","color":{"r":0.2000000029802322,"g":0.2000000029802322,"b":0.2000000029802322,"a":1.0},"alignKind":"taLeft"}},"rotateInView":null,"rotate":null,"kind":"goComposite","cmpKind":"cmpErrorBar"},{"name":"errorBar","children":[{"name":"line","children":[],"style":{"color":{"r":0.2000000029802322,"g":0.2000000029802322,"b":0.2000000029802322,"a":1.0},"size":5.0,"lineType":"ltSolid","lineWidth":1.0,"fillColor":{"r":0.0,"g":0.0,"b":0.0,"a":0.0},"marker":"mkCircle","errorBarKind":"ebLinesT","gradient":null,"font":{"family":"","size":0.0,"bold":false,"slant":"fsNormal","color":{"r":0.2000000029802322,"g":0.2000000029802322,"b":0.2000000029802322,"a":1.0},"alignKind":"taLeft"}},"rotateInView":null,"rotate":null,"kind":"goLine","lnStart":{"x":{"pos":0.8888888888888891,"kind":"ukData","scale":{"low":0.0,"high":1.2},"axis":"akX"},"y":{"pos":0.2688614540466395,"kind":"ukData","scale":{"low":-0.05,"high":0.5},"axis":"akY"}},"lnStop":{"x":{"pos":0.8888888888888891,"kind":"ukData","scale":{"low":0.0,"high":1.2},"axis":"akX"},"y":{"pos":0.2388614540466395,"kind":"ukData","scale":{"low":-0.05,"high":0.5},"axis":"akY"}}},{"name":"line","children":[],"style":{"color":{"r":0.2000000029802322,"g":0.2000000029802322,"b":0.2000000029802322,"a":1.0},"size":5.0,"lineType":"ltSolid","lineWidth":1.0,"fillColor":{"r":0.0,"g":0.0,"b":0.0,"a":0.0},"marker":"mkCircle","errorBarKind":"ebLinesT","gradient":null,"font":{"family":"","size":0.0,"bold":false,"slant":"fsNormal","color":{"r":0.2000000029802322,"g":0.2000000029802322,"b":0.2000000029802322,"a":1.0},"alignKind":"taLeft"}},"rotateInView":null,"rotate":null,"kind":"goLine","lnStart":{"x":{"pos":0.8888888888888891,"kind":"ukData","scale":{"low":0.0,"high":1.2},"axis":"akX"},"y":{"pos":0.2688614540466395,"kind":"ukData","scale":{"low":-0.05,"high":0.5},"axis":"akY"}},"lnStop":{"x":{"pos":0.8888888888888891,"kind":"ukData","scale":{"low":0.0,"high":1.2},"axis":"akX"},"y":{"pos":0.3188614540466395,"kind":"ukData","scale":{"low":-0.05,"high":0.5},"axis":"akY"}}},{"name":"line","children":[],"style":{"color":{"r":0.2000000029802322,"g":0.2000000029802322,"b":0.2000000029802322,"a":1.0},"size":5.0,"lineType":"ltSolid","lineWidth":1.0,"fillColor":{"r":0.0,"g":0.0,"b":0.0,"a":0.0},"marker":"mkCircle","errorBarKind":"ebLinesT","gradient":null,"font":{"family":"","size":0.0,"bold":false,"slant":"fsNormal","color":{"r":0.2000000029802322,"g":0.2000000029802322,"b":0.2000000029802322,"a":1.0},"alignKind":"taLeft"}},"rotateInView":null,"rotate":null,"kind":"goLine","lnStart":{"x":{"pos":0.7314885979954771,"kind":"ukRelative"},"y":{"pos":0.3188614540466395,"kind":"ukData","scale":{"low":-0.05,"high":0.5},"axis":"akY"}},"lnStop":{"x":{"pos":0.7499928834860046,"kind":"ukRelative"},"y":{"pos":0.3188614540466395,"kind":"ukData","scale":{"low":-0.05,"high":0.5},"axis":"akY"}}},{"name":"line","children":[],"style":{"color":{"r":0.2000000029802322,"g":0.2000000029802322,"b":0.2000000029802322,"a":1.0},"size":5.0,"lineType":"ltSolid","lineWidth":1.0,"fillColor":{"r":0.0,"g":0.0,"b":0.0,"a":0.0},"marker":"mkCircle","errorBarKind":"ebLinesT","gradient":null,"font":{"family":"","size":0.0,"bold":false,"slant":"fsNormal","color":{"r":0.2000000029802322,"g":0.2000000029802322,"b":0.2000000029802322,"a":1.0},"alignKind":"taLeft"}},"rotateInView":null,"rotate":null,"kind":"goLine","lnStart":{"x":{"pos":0.7314885979954771,"kind":"ukRelative"},"y":{"pos":0.2388614540466395,"kind":"ukData","scale":{"low":-0.05,"high":0.5},"axis":"akY"}},"lnStop":{"x":{"pos":0.7499928834860046,"kind":"ukRelative"},"y":{"pos":0.2388614540466395,"kind":"ukData","scale":{"low":-0.05,"high":0.5},"axis":"akY"}}}],"style":{"color":{"r":0.2000000029802322,"g":0.2000000029802322,"b":0.2000000029802322,"a":1.0},"size":5.0,"lineType":"ltSolid","lineWidth":1.0,"fillColor":{"r":0.0,"g":0.0,"b":0.0,"a":0.0},"marker":"mkCircle","errorBarKind":"ebLinesT","gradient":null,"font":{"family":"","size":0.0,"bold":false,"slant":"fsNormal","color":{"r":0.2000000029802322,"g":0.2000000029802322,"b":0.2000000029802322,"a":1.0},"alignKind":"taLeft"}},"rotateInView":null,"rotate":null,"kind":"goComposite","cmpKind":"cmpErrorBar"},{"name":"errorBar","children":[{"name":"line","children":[],"style":{"color":{"r":0.2000000029802322,"g":0.2000000029802322,"b":0.2000000029802322,"a":1.0},"size":5.0,"lineType":"ltSolid","lineWidth":1.0,"fillColor":{"r":0.0,"g":0.0,"b":0.0,"a":0.0},"marker":"mkCircle","errorBarKind":"ebLinesT","gradient":null,"font":{"family":"","size":0.0,"bold":false,"slant":"fsNormal","color":{"r":0.2000000029802322,"g":0.2000000029802322,"b":0.2000000029802322,"a":1.0},"alignKind":"taLeft"}},"rotateInView":null,"rotate":null,"kind":"goLine","lnStart":{"x":{"pos":1.0,"kind":"ukData","scale":{"low":0.0,"high":1.2},"axis":"akX"},"y":{"pos":0.4000000000000005,"kind":"ukData","scale":{"low":-0.05,"high":0.5},"axis":"akY"}},"lnStop":{"x":{"pos":1.0,"kind":"ukData","scale":{"low":0.0,"high":1.2},"axis":"akX"},"y":{"pos":0.3700000000000004,"kind":"ukData","scale":{"low":-0.05,"high":0.5},"axis":"akY"}}},{"name":"line","children":[],"style":{"color":{"r":0.2000000029802322,"g":0.2000000029802322,"b":0.2000000029802322,"a":1.0},"size":5.0,"lineType":"ltSolid","lineWidth":1.0,"fillColor":{"r":0.0,"g":0.0,"b":0.0,"a":0.0},"marker":"mkCircle","errorBarKind":"ebLinesT","gradient":null,"font":{"family":"","size":0.0,"bold":false,"slant":"fsNormal","color":{"r":0.2000000029802322,"g":0.2000000029802322,"b":0.2000000029802322,"a":1.0},"alignKind":"taLeft"}},"rotateInView":null,"rotate":null,"kind":"goLine","lnStart":{"x":{"pos":1.0,"kind":"ukData","scale":{"low":0.0,"high":1.2},"axis":"akX"},"y":{"pos":0.4000000000000005,"kind":"ukData","scale":{"low":-0.05,"high":0.5},"axis":"akY"}},"lnStop":{"x":{"pos":1.0,"kind":"ukData","scale":{"low":0.0,"high":1.2},"axis":"akX"},"y":{"pos":0.4500000000000005,"kind":"ukData","scale":{"low":-0.05,"high":0.5},"axis":"akY"}}},{"name":"line","children":[],"style":{"color":{"r":0.2000000029802322,"g":0.2000000029802322,"b":0.2000000029802322,"a":1.0},"size":5.0,"lineType":"ltSolid","lineWidth":1.0,"fillColor":{"r":0.0,"g":0.0,"b":0.0,"a":0.0},"marker":"mkCircle","errorBarKind":"ebLinesT","gradient":null,"font":{"family":"","size":0.0,"bold":false,"slant":"fsNormal","color":{"r":0.2000000029802322,"g":0.2000000029802322,"b":0.2000000029802322,"a":1.0},"alignKind":"taLeft"}},"rotateInView":null,"rotate":null,"kind":"goLine","lnStart":{"x":{"pos":0.8240811905880696,"kind":"ukRelative"},"y":{"pos":0.4500000000000005,"kind":"ukData","scale":{"low":-0.05,"high":0.5},"axis":"akY"}},"lnStop":{"x":{"pos":0.8425854760785971,"kind":"ukRelative"},"y":{"pos":0.4500000000000005,"kind":"ukData","scale":{"low":-0.05,"high":0.5},"axis":"akY"}}},{"name":"line","children":[],"style":{"color":{"r":0.2000000029802322,"g":0.2000000029802322,"b":0.2000000029802322,"a":1.0},"size":5.0,"lineType":"ltSolid","lineWidth":1.0,"fillColor":{"r":0.0,"g":0.0,"b":0.0,"a":0.0},"marker":"mkCircle","errorBarKind":"ebLinesT","gradient":null,"font":{"family":"","size":0.0,"bold":false,"slant":"fsNormal","color":{"r":0.2000000029802322,"g":0.2000000029802322,"b":0.2000000029802322,"a":1.0},"alignKind":"taLeft"}},"rotateInView":null,"rotate":null,"kind":"goLine","lnStart":{"x":{"pos":0.8240811905880696,"kind":"ukRelative"},"y":{"pos":0.3700000000000004,"kind":"ukData","scale":{"low":-0.05,"high":0.5},"axis":"akY"}},"lnStop":{"x":{"pos":0.8425854760785971,"kind":"ukRelative"},"y":{"pos":0.3700000000000004,"kind":"ukData","scale":{"low":-0.05,"high":0.5},"axis":"akY"}}}],"style":{"color":{"r":0.2000000029802322,"g":0.2000000029802322,"b":0.2000000029802322,"a":1.0},"size":5.0,"lineType":"ltSolid","lineWidth":1.0,"fillColor":{"r":0.0,"g":0.0,"b":0.0,"a":0.0},"marker":"mkCircle","errorBarKind":"ebLinesT","gradient":null,"font":{"family":"","size":0.0,"bold":false,"slant":"fsNormal","color":{"r":0.2000000029802322,"g":0.2000000029802322,"b":0.2000000029802322,"a":1.0},"alignKind":"taLeft"}},"rotateInView":null,"rotate":null,"kind":"goComposite","cmpKind":"cmpErrorBar"}],"children":[{"name":"data/layout_0","parent":"data","style":{"color":{"r":0.0,"g":0.0,"b":0.0,"a":0.0},"size":0.0,"lineType":"ltNone","lineWidth":0.0,"fillColor":{"r":0.0,"g":0.0,"b":0.0,"a":0.0},"marker":"mkCircle","errorBarKind":"ebLines","gradient":null,"font":{"family":"","size":0.0,"bold":false,"slant":"fsNormal","color":{"r":0.0,"g":0.0,"b":0.0,"a":0.0},"alignKind":"taLeft"}},"xScale":{"low":0.0,"high":1.2},"yScale":{"low":-0.05,"high":0.5},"rotate":null,"scale":null,"origin":{"x":{"pos":0.0,"kind":"ukRelative"},"y":{"pos":0.0,"kind":"ukRelative"}},"width":{"val":1.0,"unit":"ukRelative"},"height":{"val":1.0,"unit":"ukRelative"},"objects":[],"children":[],"wView":{"val":540.4153543307086,"unit":"ukPoint"},"hView":{"val":394.6417322834646,"unit":"ukPoint"},"wImg":{"val":640.0,"unit":"ukPoint"},"hImg":{"val":480.0,"unit":"ukPoint"},"backend":"bkCairo"}],"wView":{"val":540.4153543307086,"unit":"ukPoint"},"hView":{"val":394.6417322834646,"unit":"ukPoint"},"wImg":{"val":640.0,"unit":"ukPoint"},"hImg":{"val":480.0,"unit":"ukPoint"},"backend":"bkCairo"}],"wView":{"val":640.0,"unit":"ukPoint"},"hView":{"val":480.0,"unit":"ukPoint"},"wImg":{"val":640.0,"unit":"ukPoint"},"hImg":{"val":480.0,"unit":"ukPoint"},"backend":"bkCairo"},{"name":"noLegend","parent":"root","style":{"color":{"r":0.0,"g":0.0,"b":0.0,"a":0.0},"size":0.0,"lineType":"ltNone","lineWidth":0.0,"fillColor":{"r":0.0,"g":0.0,"b":0.0,"a":0.0},"marker":"mkCircle","errorBarKind":"ebLines","gradient":null,"font":{"family":"","size":0.0,"bold":false,"slant":"fsNormal","color":{"r":0.0,"g":0.0,"b":0.0,"a":0.0},"alignKind":"taLeft"}},"xScale":{"low":0.0,"high":0.0},"yScale":{"low":0.0,"high":0.0},"rotate":null,"scale":null,"origin":{"x":{"pos":21.49342742493427,"kind":"ukCentimeter","length":{"val":22.49342742493427,"unit":"ukCentimeter"}},"y":{"pos":0.9999999999999999,"kind":"ukCentimeter","length":{"val":16.87007056870071,"unit":"ukCentimeter"}}},"width":{"val":0.9999999999999999,"unit":"ukCentimeter"},"height":{"val":0.8221702755905512,"unit":"ukRelative"},"objects":[],"children":[],"wView":{"val":640.0,"unit":"ukPoint"},"hView":{"val":480.0,"unit":"ukPoint"},"wImg":{"val":640.0,"unit":"ukPoint"},"hImg":{"val":480.0,"unit":"ukPoint"},"backend":"bkCairo"},{"name":"bottomLeft","parent":"root","style":{"color":{"r":0.0,"g":0.0,"b":0.0,"a":0.0},"size":0.0,"lineType":"ltNone","lineWidth":0.0,"fillColor":{"r":0.0,"g":0.0,"b":0.0,"a":0.0},"marker":"mkCircle","errorBarKind":"ebLines","gradient":null,"font":{"family":"","size":0.0,"bold":false,"slant":"fsNormal","color":{"r":0.0,"g":0.0,"b":0.0,"a":0.0},"alignKind":"taLeft"}},"xScale":{"low":0.0,"high":0.0},"yScale":{"low":0.0,"high":0.0},"rotate":null,"scale":null,"origin":{"x":{"pos":0.0,"kind":"ukRelative"},"y":{"pos":14.87007056870071,"kind":"ukCentimeter","length":{"val":16.87007056870071,"unit":"ukCentimeter"}}},"width":{"val":2.5,"unit":"ukCentimeter"},"height":{"val":2.0,"unit":"ukCentimeter"},"objects":[],"children":[],"wView":{"val":640.0,"unit":"ukPoint"},"hView":{"val":480.0,"unit":"ukPoint"},"wImg":{"val":640.0,"unit":"ukPoint"},"hImg":{"val":480.0,"unit":"ukPoint"},"backend":"bkCairo"},{"name":"xLabel","parent":"root","style":{"color":{"r":0.0,"g":0.0,"b":0.0,"a":0.0},"size":0.0,"lineType":"ltNone","lineWidth":0.0,"fillColor":{"r":0.0,"g":0.0,"b":0.0,"a":0.0},"marker":"mkCircle","errorBarKind":"ebLines","gradient":null,"font":{"family":"","size":0.0,"bold":false,"slant":"fsNormal","color":{"r":0.0,"g":0.0,"b":0.0,"a":0.0},"alignKind":"taLeft"}},"xScale":{"low":0.0,"high":0.0},"yScale":{"low":0.0,"high":0.0},"rotate":null,"scale":null,"origin":{"x":{"pos":2.5,"kind":"ukCentimeter","length":{"val":22.49342742493427,"unit":"ukCentimeter"}},"y":{"pos":14.87007056870071,"kind":"ukCentimeter","length":{"val":16.87007056870071,"unit":"ukCentimeter"}}},"width":{"val":0.8443989911417322,"unit":"ukRelative"},"height":{"val":2.0,"unit":"ukCentimeter"},"objects":[],"children":[],"wView":{"val":640.0,"unit":"ukPoint"},"hView":{"val":480.0,"unit":"ukPoint"},"wImg":{"val":640.0,"unit":"ukPoint"},"hImg":{"val":480.0,"unit":"ukPoint"},"backend":"bkCairo"},{"name":"bottomRight","parent":"root","style":{"color":{"r":0.0,"g":0.0,"b":0.0,"a":0.0},"size":0.0,"lineType":"ltNone","lineWidth":0.0,"fillColor":{"r":0.0,"g":0.0,"b":0.0,"a":0.0},"marker":"mkCircle","errorBarKind":"ebLines","gradient":null,"font":{"family":"","size":0.0,"bold":false,"slant":"fsNormal","color":{"r":0.0,"g":0.0,"b":0.0,"a":0.0},"alignKind":"taLeft"}},"xScale":{"low":0.0,"high":0.0},"yScale":{"low":0.0,"high":0.0},"rotate":null,"scale":null,"origin":{"x":{"pos":21.49342742493427,"kind":"ukCentimeter","length":{"val":22.49342742493427,"unit":"ukCentimeter"}},"y":{"pos":14.87007056870071,"kind":"ukCentimeter","length":{"val":16.87007056870071,"unit":"ukCentimeter"}}},"width":{"val":0.9999999999999999,"unit":"ukCentimeter"},"height":{"val":2.0,"unit":"ukCentimeter"},"objects":[],"children":[],"wView":{"val":640.0,"unit":"ukPoint"},"hView":{"val":480.0,"unit":"ukPoint"},"wImg":{"val":640.0,"unit":"ukPoint"},"hImg":{"val":480.0,"unit":"ukPoint"},"backend":"bkCairo"}],"wView":{"val":640.0,"unit":"ukPoint"},"hView":{"val":480.0,"unit":"ukPoint"},"wImg":{"val":640.0,"unit":"ukPoint"},"hImg":{"val":480.0,"unit":"ukPoint"},"backend":"bkCairo"}